Workbook

Sheet PO
A1: BMCT WO
A3: Work Order Date | B3: 46105
A4: WO No. | B4: PMUMB/2026/OPS/WO-01
A5: Client | B5: Bharat Mumbai Container Terminals Pvt. Ltd. (BMCT) / PSA Mumbai
A6: Service Provider | B6: M/s. Ekta Enterprises
A7: Vendor Address | B7: A-19, Vidyut Nagar, Prince Road, Vaishali Nagar, Jaipur, Rajasthan, Pin 302021
A8: Vendor Mobile | B8: +91 97854 81867
A9: Vendor Email | B9: vikasjain@ektaenterprises.net
A10: Kind Attention | B10: Mr. Vikas Jain
A11: Subject | B11: Provide Two (2) New Reachstacker (RS) services to Bharat Mumbai Container Terminals Private Limited (BMCT)
A12: Reference | B12: BMCT RFQ through email dated 23.03.2026; final quote through email dated 23.03.2026
A13: Scope | B13: Provide 2 new RS on monthly rental basis with trained, experienced operators on 24x7, 365 days basis to BMCT for handling 20'/40' empty/ laden containers in BMCT container yard.
A14: Quantity | B14: 2 nos. new Reachstackers
A15: Make | B15: XCMG / SANY / HYSTER
... A28: Accommodation | B28: L&T will try to provide bachelor accommodation; otherwise reimbursable up to ₹1,500/person/month

Sheet Sheet1
A1: SANY RST-8 DAILY EQUIPMENT REPORT - AUG-26 | K1: OPERATORS DUTY SHIFT RECORD | O1: SANY RST-9 DAILY EQUIPMENT REPORT - AUG-26 | Y1: OPERATORS DUTY SHIFT RECORD
A2: Date | B2: SHIFT | C2: HMR START | D2: HMR END | E2: TOTAL HMR | F2: CC NO START | G2: CC NO END | H2: TOTAL CC NO | I2: FUEL FILL BY BMCT | J2: COOLING PERIOD | K2: DAY | L2: NIGHT | M2: Remarks | O2: Date | P2: SHIFT | Q2: HMR START | R2: HMR END | S2: TOTAL HMR | T2: CC NO START | U2: CC NO END | V2: TOTAL CC NO | W2: FUEL FILL BY BMCT | X2: COOLING PERIOD | Y2: DAY | Z2: NIGHT | AA2: Remarks
A3: 46235 | B3: DAY | C3: ='Aug-26'!C4 | D3: ='Aug-26'!D4 | E3: =D3-C3 | F3: ='Aug-26'!N4 | G3: ='Aug-26'!O4 | H3: =G3-F3 | I3: 270 | J3: 1 Hrs | K3: Pankaj Choudhary | L3: Kanhaiya Lal | O3: 46235 | P3: DAY | Q3: ='Aug-26'!T4 | R3: ='Aug-26'!U4 | S3: =R3-Q3 | T3: ='Aug-26'!AE4 | U3: ='Aug-26'!AF4 | V3: =U3-T3 | W3: 200 | X3: 1 Hrs | Y3: Aman Gupta | Z3: Rajkumar
B4: NIGHT | C4: =D3 | D4: ='Aug-26'!D5 | E4: =D4-C4 | F4: =G3 | G4: ='Aug-26'!O5 | H4: =G4-F4 | P4: NIGHT | Q4: =R3 | R4: ='Aug-26'!U5 | S4: =R4-Q4 | T4: =U3 | U4: ='Aug-26'!AF5 | V4: =U4-T4
A5: =A3+1 | B5: DAY | C5: =D4 | D5: ='Aug-26'!D6 | E5: =D5-C5 | F5: =G4 | G5: ='Aug-26'!O6 | H5: =G5-F5 | I5: 240 | J5: 1 Hrs | K5: Pankaj Choudhary | L5: Kanhaiya Lal | O5: =O3+1 | P5: DAY | Q5: =R4 | R5: ='Aug-26'!U6 | S5: =R5-Q5 | T5: =U4 | U5: ='Aug-26'!AF6 | V5: =U5-T5 | W5: 230 | X5: 1 Hrs | Y5: Aman Gupta | Z5: Nazeer Choudhary
B6: NIGHT | C6: =D5 | D6: ='Aug-26'!D7 | E6: =D6-C6 | F6: =G5 | G6: ='Aug-26'!O7 | H6: =G6-F6 | P6: NIGHT | Q6: =R5 | R6: ='Aug-26'!U7 | S6: =R6-Q6 | T6: =U5 | U6: ='Aug-26'!AF7 | V6: =U6-T6
A7: =A5+1 | B7: DAY | C7: =D6 | D7: ='Aug-26'!D8 | E7: =D7-C7 | F7: =G6 | G7: ='Aug-26'!O8 | H7: =G7-F7 | I7: 230 | J7: 1 Hrs | K7: Pankaj Choudhary | L7: Kanhaiya Lal | O7: =O5+1 | P7: DAY | Q7: =R6 | R7: ='Aug-26'!U8 | S7: =R7-Q7 | T7: =U6 | U7: ='Aug-26'!AF8 | V7: =U7-T7 | W7: 250 | X7: 1 Hrs | Y7: Rajkumar | Z7: Nazeer Choudhary
B8: NIGHT | C8: =D7 | D8: ='Aug-26'!D9 | E8: =D8-C8 | F8: =G7 | G8: ='Aug-26'!O9 | H8: =G8-F8 | P8: NIGHT | Q8: =R7 | R8: ='Aug-26'!U9 | S8: =R8-Q8 | T8: =U7 | U8: ='Aug-26'!AF9 | V8: =U8-T8
A9: =A7+1 | B9: DAY | C9: =D8 | D9: ='Aug-26'!D10 | E9: =D9-C9 | F9: =G8 | G9: ='Aug-26'!O10 | H9: =G9-F9 | I9: 230 | J9: 1 Hrs | K9: Pankaj Choudhary | L9: Kanhaiya Lal | O9: =O7+1 | P9: DAY | Q9: =R8 | R9: ='Aug-26'!U10 | S9: =R9-Q9 | T9: =U8 | U9: ='Aug-26'!AF10 | V9: =U9-T9 | W9: 250 | X9: 1 Hrs | Y9: Rajkumar | Z9: Aman Gupta
B10: NIGHT | C10: =D9 | D10: ='Aug-26'!D11 | E10: =D10-C10 | F10: =G9 | G10: ='Aug-26'!O11 | H10: =G10-F10 | P10: NIGHT | Q10: =R9 | R10: ='Aug-26'!U11 | S10: =R10-Q10 | T10: =U9 | U10: ='Aug-26'!AF11 | V10: =U10-T10
A11: =A9+1 | B11: DAY | C11: =D10 | D11: ='Aug-26'!D12 | E11: =D11-C11 | F11: =G10 | G11: ='Aug-26'!O12 | H11: =G11-F11 | I11: 270 | J11: 1 Hrs | K11: Nazeer Choudhary | L11: Pankaj Choudhary | O11: =O9+1 | P11: DAY | Q11: =R10 | R11: ='Aug-26'!U12 | S11: =R11-Q11 | T11: =U10 | U11: ='Aug-26'!AF12 | V11: =U11-T11 | W11: 250 | X11: 1 Hrs | Y11: Rajkumar | Z11: Aman Gupta
B12: NIGHT | C12: =D11 | D12: ='Aug-26'!D13 | E12: =D12-C12 | F12: =G11 | G12: ='Aug-26'!O13 | H12: =G12-F12 | P12: NIGHT | Q12: =R11 | R12: ='Aug-26'!U13 | S12: =R12-Q12 | T12: =U11 | U12: ='Aug-26'!AF13 | V12: =U12-T12
A13: =A11+1 | B13: DAY | C13: =D12 | D13: ='Aug-26'!D14 | E13: =D13-C13 | F13: =G12 | G13: ='Aug-26'!O14 | H13: =G13-F13 | I13: 150 | J13: 1 Hrs | K13: Kanhaiya Lal | L13: Pankaj Choudhary | O13: =O11+1 | P13: DAY | Q13: =R12 | R13: ='Aug-26'!U14 | S13: =R13-Q13 | T13: =U12 | U13: ='Aug-26'!AF14 | V13: =U13-T13 | W13: 200 | X13: 1 Hrs | Y13: Nazeer Choudhary | Z13: Aman Gupta
B14: NIGHT | C14: =D13 | D14: ='Aug-26'!D15 | E14: =D14-C14 | F14: =G13 | G14: ='Aug-26'!O15 | H14: =G14-F14 | P14: NIGHT | Q14: =R13 | R14: ='Aug-26'!U15 | S14: =R14-Q14 | T14: =U13 | U14: ='Aug-26'!AF15 | V14: =U14-T14
A15: =A13+1 | B15: DAY | C15: =D14 | D15: ='Aug-26'!D16 | E15: =D15-C15 | F15: =G14 | G15: ='Aug-26'!O16 | H15: =G15-F15 | I15: 250 | J15: 1 Hrs | K15: Kanhaiya Lal | L15: Pankaj Choudhary | O15: =O13+1 | P15: DAY | Q15: =R14 | R15: ='Aug-26'!U16 | S15: =R15-Q15 | T15: =U14 | U15: ='Aug-26'!AF16 | V15: =U15-T15 | W15: 200 | X15: 1 Hrs | Y15: Nazeer Choudhary | Z15: Rajkumar
B16: NIGHT | C16: =D15 | D16: ='Aug-26'!D17 | E16: =D16-C16 | F16: =G15 | G16: ='Aug-26'!O17 | H16: =G16-F16 | P16: NIGHT | Q16: =R15 | R16: ='Aug-26'!U17 | S16: =R16-Q16 | T16: =U15 | U16: ='Aug-26'!AF17 | V16: =U16-T16
A17: =A15+1 | B17: DAY | C17: =D16 | D17: ='Aug-26'!D18 | E17: =D17-C17 | F17: =G16 | G17: ='Aug-26'!O18 | H17: =G17-F17 | I17: 230 | J17: 1 Hrs | K17: Kanhaiya Lal | L17: Pankaj Choudhary | O17: =O15+1 | P17: DAY | Q17: =R16 | R17: ='Aug-26'!U18 | S17: =R17-Q17 | T17: =U16 | U17: ='Aug-26'!AF18 | V17: =U17-T17 | W17: 170 | X17: 1 Hrs | Y17: Aman Gupta | Z17: Rajkumar
B18: NIGHT | C18: =D17 | D18: ='Aug-26'!D19 | E18: =D18-C18 | F18: =G17 | G18: ='Aug-26'!O19 | H18: =G18-F18 | P18: NIGHT | Q18: =R17 | R18: ='Aug-26'!U19 | S18: =R18-Q18 | T18: =U17 | U18: ='Aug-26'!AF19 | V18: =U18-T18
A19: =A17+1 | B19: DAY | C19: =D18 | D19: ='Aug-26'!D20 | E19: =D19-C19 | F19: =G18 | G19: ='Aug-26'!O20 | H19: =G19-F19 | I19: 200 | J19: 1 Hrs | K19: Kanhaiya Lal | L19: Nazeer Choudhary | O19: =O17+1 | P19: DAY | Q19: =R18 | R19: ='Aug-26'!U20 | S19: =R19-Q19 | T19: =U18 | U19: ='Aug-26'!AF20 | V19: =U19-T19 | W19: 230 | X19: 1 Hrs | Y19: Aman Gupta | Z19: Rajkumar
B20: NIGHT | C20: =D19 | D20: ='Aug-26'!D21 | E20: =D20-C20 | F20: =G19 | G20: ='Aug-26'!O21 | H20: =G20-F20 | P20: NIGHT | Q20: =R19 | R20: ='Aug-26'!U21 | S20: =R20-Q20 | T20: =U19 | U20: ='Aug-26'!AF21 | V20: =U20-T20
A21: =A19+1 | B21: DAY | C21: =D20 | D21: ='Aug-26'!D22 | E21: =D21-C21 | F21: =G20 | G21: ='Aug-26'!O22 | H21: =G21-F21 | I21: 340 | J21: 1 Hrs | K21: Pankaj Choudhary | L21: Nazeer Choudhary | O21: =O19+1 | P21: DAY | Q21: =R20 | R21: ='Aug-26'!U22 | S21: =R21-Q21 | T21: =U20 | U21: ='Aug-26'!AF22 | V21: =U21-T21 | W21: 350 | X21: 1 Hrs | Y21: Aman Gupta | Z21: Rajkumar
B22: NIGHT | C22: =D21 | D22: ='Aug-26'!D23 | E22: =D22-C22 | F22: =G21 | G22: ='Aug-26'!O23 | H22: =G22-F22 | P22: NIGHT | Q22: =R21 | R22: ='Aug-26'!U23 | S22: =R22-Q22 | T22: =U21 | U22: ='Aug-26'!AF23 | V22: =U22-T22
A23: =A21+1 | B23: DAY | C23: =D22 | D23: ='Aug-26'!D24 | E23: =D23-C23 | F23: =G22 | G23: ='Aug-26'!O24 | H23: =G23-F23 | I23: 240 | J23: 1 Hrs | K23: Pankaj Choudhary | L23: Nazeer Choudhary | O23: =O21+1 | P23: DAY | Q23: =R22 | R23: ='Aug-26'!U24 | S23: =R23-Q23 | T23: =U22 | U23: ='Aug-26'!AF24 | V23: =U23-T23 | W23: 260 | X23: 1 Hrs | Y23: Aman Gupta | Z23: Nazeer Choudhary
B24: NIGHT | C24: =D23 | D24: ='Aug-26'!D25 | E24: =D24-C24 | F24: =G23 | G24: ='Aug-26'!O25 | H24: =G24-F24 | P24: NIGHT | Q24: =R23 | R24: ='Aug-26'!U25 | S24: =R24-Q24 | T24: =U23 | U24: ='Aug-26'!AF25 | V24: =U24-T24
A25: =A23+1 | B25: DAY | C25: =D24 | D25: ='Aug-26'!D26 | E25: =D25-C25 | F25: =G24 | G25: ='Aug-26'!O26 | H25: =G25-F25 | I25: 180 | J25: 1 Hrs | K25: Pankaj Choudhary | L25: Saidullah Choudhary | O25: =O23+1 | P25: DAY | Q25: =R24 | R25: ='Aug-26'!U26 | S25: =R25-Q25 | T25: =U24 | U25: ='Aug-26'!AF26 | V25: =U25-T25 | W25: 150 | X25: 1 Hrs | Y25: Rajkumar | Z25: Kanhaiya Lal
B26: NIGHT | C26: =D25 | D26: ='Aug-26'!D27 | E26: =D26-C26 | F26: =G25 | G26: ='Aug-26'!O27 | H26: =G26-F26 | P26: NIGHT | Q26: =R25 | R26: ='Aug-26'!U27 | S26: =R26-Q26 | T26: =U25 | U26: ='Aug-26'!AF27 | V26: =U26-T26
A27: =A25+1 | B27: DAY | C27: =D26 | D27: ='Aug-26'!D28 | E27: =D27-C27 | F27: =G26 | G27: ='Aug-26'!O28 | H27: =G27-F27 | I27: 150 | J27: 1 Hrs | K27: Pankaj Choudhary | L27: Saidullah Choudhary | O27: =O25+1 | P27: DAY | Q27: =R26 | R27: ='Aug-26'!U28 | S27: =R27-Q27 | T27: =U26 | U27: ='Aug-26'!AF28 | V27: =U27-T27 | W27: 160 | X27: 1 Hrs | Y27: Aman Gupta | Z27: Kanhaiya Lal
B28: NIGHT | C28: =D27 | D28: ='Aug-26'!D29 | E28: =D28-C28 | F28: =G27 | G28: ='Aug-26'!O29 | H28: =G28-F28 | P28: NIGHT | Q28: =R27 | R28: ='Aug-26'!U29 | S28: =R28-Q28 | T28: =U27 | U28: ='Aug-26'!AF29 | V28: =U28-T28
A29: =A27+1 | B29: DAY | C29: =D28 | D29: ='Aug-26'!D30 | E29: =D29-C29 | F29: =G28 | G29: ='Aug-26'!O30 | H29: =G29-F29 | I29: 250 | J29: 1 Hrs | K29: Pankaj Choudhary | L29: Saidullah Choudhary | O29: =O27+1 | P29: DAY | Q29: =R28 | R29: ='Aug-26'!U30 | S29: =R29-Q29 | T29: =U28 | U29: ='Aug-26'!AF30 | V29: =U29-T29 | W29: 250 | X29: 1 Hrs | Y29: Nazeer Choudhary | Z29: Rajkumar
B30: NIGHT | C30: =D29 | D30: ='Aug-26'!D31 | E30: =D30-C30 | F30: =G29 | G30: ='Aug-26'!O31 | H30: =G30-F30 | P30: NIGHT | Q30: =R29 | R30: ='Aug-26'!U31 | S30: =R30-Q30 | T30: =U29 | U30: ='Aug-26'!AF31 | V30: =U30-T30
A31: =A29+1 | B31: DAY | C31: =D30 | D31: ='Aug-26'!D32 | E31: =D31-C31 | F31: =G30 | G31: ='Aug-26'!O32 | H31: =G31-F31 | I31: 230 | J31: 1 Hrs | K31: Kanhaiya Lal | L31: Nazeer Choudhary | O31: =O29+1 | P31: DAY | Q31: =R30 | R31: ='Aug-26'!U32 | S31: =R31-Q31 | T31: =U30 | U31: ='Aug-26'!AF32 | V31: =U31-T31 | W31: 260 | X31: 1 Hrs | Y31: Aman Gupta | Z31: Rajkumar
B32: NIGHT | C32: =D31 | D32: ='Aug-26'!D33 | E32: =D32-C32 | F32: =G31 | G32: ='Aug-26'!O33 | H32: =G32-F32 | P32: NIGHT | Q32: =R31 | R32: ='Aug-26'!U33 | S32: =R32-Q32 | T32: =U31 | U32: ='Aug-26'!AF33 | V32: =U32-T32
A33: =A31+1 | B33: DAY | C33: =D32 | D33: ='Aug-26'!D34 | E33: =D33-C33 | F33: =G32 | G33: ='Aug-26'!O34 | H33: =G33-F33 | I33: 150 | J33: 1 Hrs | K33: Saidullah Choudhary | L33: Nazeer Choudhary | O33: =O31+1 | P33: DAY | Q33: =R32 | R33: ='Aug-26'!U34 | S33: =R33-Q33 | T33: =U32 | U33: ='Aug-26'!AF34 | V33: =U33-T33 | W33: 110 | X33: 1 Hrs | Y33: Kanhaiya Lal | Z33: Aman Gupta
B34: NIGHT | C34: =D33 | D34: ='Aug-26'!D35 | E34: =D34-C34 | F34: =G33 | G34: ='Aug-26'!O35 | H34: =G34-F34 | P34: NIGHT | Q34: =R33 | R34: ='Aug-26'!U35 | S34: =R34-Q34 | T34: =U33 | U34: ='Aug-26'!AF35 | V34: =U34-T34
A35: =A33+1 | B35: DAY | C35: =D34 | D35: ='Aug-26'!D36 | E35: =D35-C35 | F35: =G34 | G35: ='Aug-26'!O36 | H35: =G35-F35 | I35: 320 | J35: 1 Hrs | K35: Pankaj Choudhary | L35: Saidullah Choudhary | O35: =O33+1 | P35: DAY | Q35: =R34 | R35: ='Aug-26'!U36 | S35: =R35-Q35 | T35: =U34 | U35: ='Aug-26'!AF36 | V35: =U35-T35 | W35: 340 | X35: 1 Hrs | Y35: Rajkumar | Z35: Aman Gupta
B36: NIGHT | C36: =D35 | D36: ='Aug-26'!D37 | E36: =D36-C36 | F36: =G35 | G36: ='Aug-26'!O37 | H36: =G36-F36 | P36: NIGHT | Q36: =R35 | R36: ='Aug-26'!U37 | S36: =R36-Q36 | T36: =U35 | U36: ='Aug-26'!AF37 | V36: =U36-T36
A37: =A35+1 | B37: DAY | C37: =D36 | D37: ='Aug-26'!D38 | E37: =D37-C37 | F37: =G36 | G37: ='Aug-26'!O38 | H37: =G37-F37 | J37: 1 Hrs | K37: Pankaj Choudhary | L37: Kanhaiya Lal | O37: =O35+1 | P37: DAY | Q37: =R36 | R37: ='Aug-26'!U38 | S37: =R37-Q37 | T37: =U36 | U37: ='Aug-26'!AF38 | V37: =U37-T37 | W37: 270 | X37: 1 Hrs | Y37: Rajkumar | Z37: Saidullah Choudhary
B38: NIGHT | C38: =D37 | D38: ='Aug-26'!D39 | E38: =D38-C38 | F38: =G37 | G38: ='Aug-26'!O39 | H38: =G38-F38 | P38: NIGHT | Q38: =R37 | R38: ='Aug-26'!U39 | S38: =R38-Q38 | T38: =U37 | U38: ='Aug-26'!AF39 | V38: =U38-T38
A39: =A37+1 | B39: DAY | C39: =D38 | D39: ='Aug-26'!D40 | E39: =D39-C39 | F39: =G38 | G39: ='Aug-26'!O40 | H39: =G39-F39 | I39: 300 | J39: 1 Hrs | K39: Nazeer Choudhary | L39: Saidullah Choudhary | O39: =O37+1 | P39: DAY | Q39: =R38 | R39: ='Aug-26'!U40 | S39: =R39-Q39 | T39: =U38 | U39: ='Aug-26'!AF40 | V39: =U39-T39 | W39: 240 | X39: 1 Hrs | Y39: Aman Gupta | Z39: Kanhaiya Lal
B40: NIGHT | C40: =D39 | D40: ='Aug-26'!D41 | E40: =D40-C40 | F40: =G39 | G40: ='Aug-26'!O41 | H40: =G40-F40 | P40: NIGHT | Q40: =R39 | R40: ='Aug-26'!U41 | S40: =R40-Q40 | T40: =U39 | U40: ='Aug-26'!AF41 | V40: =U40-T40
A41: =A39+1 | B41: DAY | C41: =D40 | D41: ='Aug-26'!D42 | E41: =D41-C41 | F41: =G40 | G41: ='Aug-26'!O42 | H41: =G41-F41 | I41: 200 | J41: 1 Hrs | K41: Nazeer Choudhary | L41: Pankaj Choudhary | O41: =O39+1 | P41: DAY | Q41: =R40 | R41: ='Aug-26'!U42 | S41: =R41-Q41 | T41: =U40 | U41: ='Aug-26'!AF42 | V41: =U41-T41 | W41: 270 | X41: 1 Hrs | Y41: Aman Gupta | Z41: Rajkumar
B42: NIGHT | C42: =D41 | D42: ='Aug-26'!D43 | E42: =D42-C42 | F42: =G41 | G42: ='Aug-26'!O43 | H42: =G42-F42 | P42: NIGHT | Q42: =R41 | R42: ='Aug-26'!U43 | S42: =R42-Q42 | T42: =U41 | U42: ='Aug-26'!AF43 | V42: =U42-T42
A43: =A41+1 | B43: DAY | C43: =D42 | D43: ='Aug-26'!D44 | E43: =D43-C43 | F43: =G42 | G43: ='Aug-26'!O44 | H43: =G43-F43 | I43: 250 | J43: 1 Hrs | K43: Saidullah Choudhary | L43: Pankaj Choudhary | O43: =O41+1 | P43: DAY | Q43: =R42 | R43: ='Aug-26'!U44 | S43: =R43-Q43 | T43: =U42 | U43: ='Aug-26'!AF44 | V43: =U43-T43 | W43: 200 | X43: 1 Hrs | Y43: Kanhaiya Lal | Z43: Rajkumar
B44: NIGHT | C44: =D43 | D44: ='Aug-26'!D45 | E44: =D44-C44 | F44: =G43 | G44: ='Aug-26'!O45 | H44: =G44-F44 | P44: NIGHT | Q44: =R43 | R44: ='Aug-26'!U45 | S44: =R44-Q44 | T44: =U43 | U44: ='Aug-26'!AF45 | V44: =U44-T44
A45: =A43+1 | B45: DAY | C45: =D44 | D45: ='Aug-26'!D46 | E45: =D45-C45 | F45: =G44 | G45: ='Aug-26'!O46 | H45: =G45-F45 | I45: 210 | J45: 1 Hrs | K45: Saidullah Choudhary | L45: Nazeer Choudhary | O45: =O43+1 | P45: DAY | Q45: =R44 | R45: ='Aug-26'!U46 | S45: =R45-Q45 | T45: =U44 | U45: ='Aug-26'!AF46 | V45: =U45-T45 | W45: 170 | X45: 1 Hrs | Y45: Kanhaiya Lal | Z45: Aman Gupta
B46: NIGHT | C46: =D45 | D46: ='Aug-26'!D47 | E46: =D46-C46 | F46: =G45 | G46: ='Aug-26'!O47 | H46: =G46-F46 | P46: NIGHT | Q46: =R45 | R46: ='Aug-26'!U47 | S46: =R46-Q46 | T46: =U45 | U46: ='Aug-26'!AF47 | V46: =U46-T46
A47: =A45+1 | B47: DAY | C47: =D46 | D47: ='Aug-26'!D48 | E47: =D47-C47 | F47: =G46 | G47: ='Aug-26'!O48 | H47: =G47-F47 | I47: 200 | J47: 1 Hrs | K47: Pankaj Choudhary | L47: Nazeer Choudhary | O47: =O45+1 | P47: DAY | Q47: =R46 | R47: ='Aug-26'!U48 | S47: =R47-Q47 | T47: =U46 | U47: ='Aug-26'!AF48 | V47: =U47-T47 | W47: 250 | X47: 1 Hrs | Y47: Rajkumar | Z47: Aman Gupta
B48: NIGHT | C48: =D47 | D48: ='Aug-26'!D49 | E48: =D48-C48 | F48: =G47 | G48: ='Aug-26'!O49 | H48: =G48-F48 | P48: NIGHT | Q48: =R47 | R48: ='Aug-26'!U49 | S48: =R48-Q48 | T48: =U47 | U48: ='Aug-26'!AF49 | V48: =U48-T48
A49: =A47+1 | B49: DAY | C49: =D48 | D49: ='Aug-26'!D50 | E49: =D49-C49 | F49: =G48 | G49: ='Aug-26'!O50 | H49: =G49-F49 | I49: 250 | J49: 1 Hrs | K49: Pankaj Choudhary | L49: Saidullah Choudhary | O49: =O47+1 | P49: DAY | Q49: =R48 | R49: ='Aug-26'!U50 | S49: =R49-Q49 | T49: =U48 | U49: ='Aug-26'!AF50 | V49: =U49-T49 | W49: 220 | X49: 1 Hrs | Y49: Rajkumar | Z49: Kanhaiya Lal
B50: NIGHT | C50: =D49 | D50: ='Aug-26'!D51 | E50: =D50-C50 | F50: =G49 | G50: ='Aug-26'!O51 | H50: =G50-F50 | P50: NIGHT | Q50: =R49 | R50: ='Aug-26'!U51 | S50: =R50-Q50 | T50: =U49 | U50: ='Aug-26'!AF51 | V50: =U50-T50
A51: =A49+1 | B51: DAY | C51: =D50 | D51: ='Aug-26'!D52 | E51: =D51-C51 | F51: =G50 | G51: ='Aug-26'!O52 | H51: =G51-F51 | I51: 260 | J51: 1 Hrs | K51: Nazeer Choudhary | L51: Saidullah Choudhary | O51: =O49+1 | P51: DAY | Q51: =R50 | R51: ='Aug-26'!U52 | S51: =R51-Q51 | T51: =U50 | U51: ='Aug-26'!AF52 | V51: =U51-T51 | W51: 270 | X51: 1 Hrs | Y51: Aman Gupta | Z51: Kanhaiya Lal
B52: NIGHT | C52: =D51 | D52: ='Aug-26'!D53 | E52: =D52-C52 | F52: =G51 | G52: ='Aug-26'!O53 | H52: =G52-F52 | P52: NIGHT | Q52: =R51 | R52: ='Aug-26'!U53 | S52: =R52-Q52 | T52: =U51 | U52: ='Aug-26'!AF53 | V52: =U52-T52
A53: =A51+1 | B53: DAY | C53: =D52 | D53: ='Aug-26'!D54 | E53: =D53-C53 | F53: =G52 | G53: ='Aug-26'!O54 | H53: =G53-F53 | I53: 140 | J53: 1 Hrs | K53: Rajkumar | L53: Pankaj Choudhary | O53: =O51+1 | P53: DAY | Q53: =R52 | R53: ='Aug-26'!U54 | S53: =R53-Q53 | T53: =U52 | U53: ='Aug-26'!AF54 | V53: =U53-T53 | W53: 150 | X53: 1 Hrs | Y53: Aman Gupta | Z53: Kanhaiya Lal
B54: NIGHT | C54: =D53 | D54: ='Aug-26'!D55 | E54: =D54-C54 | F54: =G53 | G54: ='Aug-26'!O55 | H54: =G54-F54 | P54: NIGHT | Q54: =R53 | R54: ='Aug-26'!U55 | S54: =R54-Q54 | T54: =U53 | U54: ='Aug-26'!AF55 | V54: =U54-T54
A55: =A53+1 | B55: DAY | C55: =D54 | D55: ='Aug-26'!D56 | E55: =D55-C55 | F55: =G54 | G55: ='Aug-26'!O56 | H55: =G55-F55 | I55: 300 | J55: 1 Hrs | K55: Nazeer Choudhary | L55: Pankaj Choudhary | O55: =O53+1 | P55: DAY | Q55: =R54 | R55: ='Aug-26'!U56 | S55: =R55-Q55 | T55: =U54 | U55: ='Aug-26'!AF56 | V55: =U55-T55 | W55: 260 | X55: 1 Hrs | Y55: Aman Gupta | Z55: Rajkumar
B56: NIGHT | C56: =D55 | D56: ='Aug-26'!D57 | E56: =D56-C56 | F56: =G55 | G56: ='Aug-26'!O57 | H56: =G56-F56 | P56: NIGHT | Q56: =R55 | R56: ='Aug-26'!U57 | S56: =R56-Q56 | T56: =U55 | U56: ='Aug-26'!AF57 | V56: =U56-T56
A57: =A55+1 | B57: DAY | C57: =D56 | D57: ='Aug-26'!D58 | E57: =D57-C57 | F57: =G56 | G57: ='Aug-26'!O58 | H57: =G57-F57 | I57: 200 | J57: 1 Hrs | K57: Saidullah Choudhary | L57: Nazeer Choudhary | O57: =O55+1 | P57: DAY | Q57: =R56 | R57: ='Aug-26'!U58 | S57: =R57-Q57 | T57: =U56 | U57: ='Aug-26'!AF58 | V57: =U57-T57 | W57: 220 | X57: 1 Hrs | Y57: Kanhaiya Lal | Z57: Rajkumar
B58: NIGHT | C58: =D57 | D58: ='Aug-26'!D59 | E58: =D58-C58 | F58: =G57 | G58: ='Aug-26'!O59 | H58: =G58-F58 | P58: NIGHT | Q58: =R57 | R58: ='Aug-26'!U59 | S58: =R58-Q58 | T58: =U57 | U58: ='Aug-26'!AF59 | V58: =U58-T58
A59: =A57+1 | B59: DAY | C59: =D58 | D59: ='Aug-26'!D60 | E59: =D59-C59 | F59: =G58 | G59: ='Aug-26'!O60 | H59: =G59-F59 | I59: 200 | J59: 1 Hrs | K59: Pankaj Choudhary | L59: Kanhaiya Lal | O59: =O57+1 | P59: DAY | Q59: =R58 | R59: ='Aug-26'!U60 | S59: =R59-Q59 | T59: =U58 | U59: ='Aug-26'!AF60 | V59: =U59-T59 | W59: 180 | X59: 1 Hrs | Y59: Saidullah Choudhary | Z59: Aman Gupta
B60: NIGHT | C60: =D59 | D60: ='Aug-26'!D61 | E60: =D60-C60 | F60: =G59 | G60: ='Aug-26'!O61 | H60: =G60-F60 | P60: NIGHT | Q60: =R59 | R60: ='Aug-26'!U61 | S60: =R60-Q60 | T60: =U59 | U60: ='Aug-26'!AF61 | V60: =U60-T60 | W60: 180
A61: =A59+1 | B61: DAY | C61: =D60 | D61: ='Aug-26'!D62 | E61: =D61-C61 | F61: =G60 | G61: ='Aug-26'!O62 | H61: =G61-F61 | I61: 160 | J61: 1 Hrs | K61: Pankaj Choudhary | L61: Saidullah Choudhary | O61: =O59+1 | P61: DAY | Q61: =R60 | R61: ='Aug-26'!U62 | S61: =R61-Q61 | T61: =U60 | U61: ='Aug-26'!AF62 | V61: =U61-T61 | X61: 1 Hrs | Y61: Rajkumar | Z61: Aman Gupta
B62: NIGHT | C62: =D61 | D62: ='Aug-26'!D63 | E62: =D62-C62 | F62: =G61 | G62: ='Aug-26'!O63 | H62: =G62-F62 | P62: NIGHT | Q62: =R61 | R62: ='Aug-26'!U63 | S62: =R62-Q62 | T62: =U61 | U62: ='Aug-26'!AF63 | V62: =U62-T62
A63: =A61+1 | B63: DAY | C63: =D62 | D63: ='Aug-26'!D64 | E63: =D63-C63 | F63: =G62 | G63: ='Aug-26'!O64 | H63: =G63-F63 | I63: 370 | J63: 1 Hrs | K63: Pankaj Choudhary | L63: Saidullah Choudhary | O63: =O61+1 | P63: DAY | Q63: =R62 | R63: ='Aug-26'!U64 | S63: =R63-Q63 | T63: =U62 | U63: ='Aug-26'!AF64 | V63: =U63-T63 | W63: 380 | X63: 1 Hrs | Y63: Rajkumar | Z63: Kanhaiya Lal
B64: NIGHT | C64: =D63 | D64: ='Aug-26'!D65 | E64: =D64-C64 | F64: =G63 | G64: ='Aug-26'!O65 | H64: =G64-F64 | P64: NIGHT | Q64: =R63 | R64: ='Aug-26'!U65 | S64: =R64-Q64 | T64: =U63 | U64: ='Aug-26'!AF65 | V64: =U64-T64
A65: HMR TOTAL | E65: =SUBTOTAL(9,E3:E64) | H65: =SUBTOTAL(9,H3:H64) | I65: =SUBTOTAL(9,I3:I64) | O65: HMR TOTAL | S65: =SUBTOTAL(9,S3:S64) | V65: =SUBTOTAL(9,V3:V64) | W65: =SUBTOTAL(9,W3:W64)

Sheet Apr-26
A1: NEW MACHINE NO - XCMG-8 | J1: BREAKDOWN TIME/Cooling | R1: NEW MACHINE NO - SANY-9 | AA1: BREAKDOWN TIME/Cooling
A2: DATE | B2: SHIFT | C2: SHIFT START - HMR | D2: SHIFT END - HMR | E2: HOURS | F2: DIESEL | G2: HMR | H2: HOURS | I2: AVERAGE | J2: START TIME | K2: END TIME | L2: TOTAL HRS | M2: Remarks | N2: Container Start Count | O2: Container End Count | P2: Total | R2: DATE | S2: SHIFT | T2: SHIFT START - HMR | U2: SHIFT END - HMR | V2: HOURS | W2: DIESEL | X2: HMR | Y2: HOURS | Z2: AVERAGE | AA2: START TIME | AB2: END TIME | AC2: TOTAL HRS | AD2: Remarks | AE2: Container Start Count | AF2: Container End Count | AG2: Total
A3: 46113 | B3: DAY | R3: 46113 | S3: DAY
A4: =A3 | B4: NIGHT | R4: =R3 | S4: NIGHT
A5: =A4+1 | B5: DAY | R5: =R4+1 | S5: DAY
A6: =A5 | B6: NIGHT | R6: =R5 | S6: NIGHT
A7: =A6+1 | B7: DAY | R7: =R6+1 | S7: DAY
A8: =A7 | B8: NIGHT | R8: =R7 | S8: NIGHT
A9: =A8+1 | B9: DAY | R9: =R8+1 | S9: DAY
A10: =A9 | B10: NIGHT | R10: =R9 | S10: NIGHT
A11: =A10+1 | B11: DAY | R11: =R10+1 | S11: DAY
A12: =A11 | B12: NIGHT | R12: =R11 | S12: NIGHT
A13: =A12+1 | B13: DAY | R13: =R12+1 | S13: DAY
A14: =A13 | B14: NIGHT | R14: =R13 | S14: NIGHT
A15: =A14+1 | B15: DAY | R15: =R14+1 | S15: DAY
A16: =A15 | B16: NIGHT | R16: =R15 | S16: NIGHT
A17: =A16+1 | B17: DAY | R17: =R16+1 | S17: DAY
A18: =A17 | B18: NIGHT | R18: =R17 | S18: NIGHT
A19: =A18+1 | B19: DAY | R19: =R18+1 | S19: DAY
A20: =A19 | B20: NIGHT | R20: =R19 | S20: NIGHT
A21: =A20+1 | B21: DAY | R21: =R20+1 | S21: DAY
A22: =A21 | B22: NIGHT | R22: =R21 | S22: NIGHT
A23: =A22+1 | B23: DAY | R23: =R22+1 | S23: DAY
A24: =A23 | B24: NIGHT | R24: =R23 | S24: NIGHT
A25: =A24+1 | B25: DAY | R25: =R24+1 | S25: DAY
A26: =A25 | B26: NIGHT | R26: =R25 | S26: NIGHT
A27: =A26+1 | B27: DAY | R27: =R26+1 | S27: DAY
A28: =A27 | B28: NIGHT | R28: =R27 | S28: NIGHT
A29: =A28+1 | B29: DAY | R29: =R28+1 | S29: DAY
A30: =A29 | B30: NIGHT | R30: =R29 | S30: NIGHT
A31: =A30+1 | B31: DAY | R31: =R30+1 | S31: DAY
A32: =A31 | B32: NIGHT | R32: =R31 | S32: NIGHT
A33: =A32+1 | B33: DAY | R33: =R32+1 | S33: DAY
A34: =A33 | B34: NIGHT | R34: =R33 | S34: NIGHT
A35: =A34+1 | B35: DAY | F35: 500 | G35: 45 | R35: =R34+1 | S35: DAY
A36: =A35 | B36: NIGHT | R36: =R35 | S36: NIGHT
A37: =A36+1 | B37: DAY | R37: =R36+1 | S37: DAY
A38: =A37 | B38: NIGHT | J38: 0.083333333 | K38: 0.5 | L38: =K38-J38 | M38: Electric problem | R38: =R37 | S38: NIGHT
A39: =A38+1 | B39: DAY | J39: =K38 | K39: 0.66666667 | L39: =K39-J39 | M39: Electric problem | R39: =R38+1 | S39: DAY
A40: =A39 | B40: NIGHT | R40: =R39 | S40: NIGHT
A41: =A40+1 | B41: DAY | P41: =O41-N41 | R41: =R40+1 | S41: DAY
A42: =A41 | B42: NIGHT | P42: =O42-N42 | R42: =R41 | S42: NIGHT
A43: =A42+1 | B43: DAY | C43: 62 | D43: 72 | E43: =D43-C43 | F43: 230 | G43: 69 | H43: =G43-G35 | I43: =(F43+F35)/H43 | N43: 534 | O43: 685 | P43: =O43-N43 | R43: =R42+1 | S43: DAY
A44: =A43 | B44: NIGHT | C44: =D43 | D44: 82 | E44: =D44-C44 | N44: =O43 | O44: 779 | P44: =O44-N44 | R44: =R43 | S44: NIGHT
A45: =A44+1 | B45: DAY | C45: =D44 | D45: 88 | E45: =D45-C45 | F45: 130.1 | G45: 85 | H45: =G45-G43 | I45: =F45/H45 | N45: 779 | O45: 836 | P45: =O45-N45 | R45: =R44+1 | S45: DAY
A46: =A45 | B46: NIGHT | C46: =D45 | D46: 95 | E46: =D46-C46 | N46: =O45 | O46: 902 | P46: =O46-N46 | R46: =R45 | S46: NIGHT
A47: =A46+1 | B47: DAY | C47: =D46 | D47: 101 | E47: =D47-C47 | F47: 160 | G47: 98 | H47: =G47-G45 | I47: =F47/H47 | N47: =O46 | O47: 973 | P47: =O47-N47 | R47: =R46+1 | S47: DAY
A48: =A47 | B48: NIGHT | C48: =D47 | D48: 112 | E48: =D48-C48 | N48: =O47 | O48: 1088 | P48: =O48-N48 | R48: =R47 | S48: NIGHT
A49: =A48+1 | B49: DAY | C49: =D48 | D49: 122 | E49: =D49-C49 | F49: 208 | G49: 117 | H49: =G49-G47 | I49: =F49/H49 | N49: =O48 | O49: 1207 | P49: =O49-N49 | R49: =R48+1 | S49: DAY
A50: =A49 | B50: NIGHT | C50: =D49 | D50: 131 | E50: =D50-C50 | N50: =O49 | O50: 1306 | P50: =O50-N50 | R50: =R49 | S50: NIGHT
A51: =A50+1 | B51: DAY | C51: =D50 | D51: 141 | E51: =D51-C51 | F51: 250 | G51: 136 | H51: =G51-G49 | I51: =F51/H51 | N51: =O50 | O51: 1419 | P51: =O51-N51 | R51: =R50+1 | S51: DAY
A52: =A51 | B52: NIGHT | C52: =D51 | D52: 150 | E52: =D52-C52 | N52: =O51 | O52: 1529 | P52: =O52-N52 | R52: =R51 | S52: NIGHT
A53: =A52+1 | B53: DAY | C53: =D52 | D53: 159 | E53: =D53-C53 | F53: 180 | G53: 153 | H53: =G53-G51 | I53: =F53/H53 | N53: =O52 | O53: 1615 | P53: =O53-N53 | R53: =R52+1 | S53: DAY
A54: =A53 | B54: NIGHT | C54: =D53 | D54: 169 | E54: =D54-C54 | N54: =O53 | O54: 1699 | P54: =O54-N54 | R54: =R53 | S54: NIGHT
A55: =A54+1 | B55: DAY | C55: =D54 | D55: 180 | E55: =D55-C55 | F55: 180 | G55: 173 | H55: =G55-G53 | I55: =F55/H55 | N55: =O54 | O55: 1824 | P55: =O55-N55 | R55: =R54+1 | S55: DAY
A56: =A55 | B56: NIGHT | C56: =D55 | D56: 190 | E56: =D56-C56 | N56: =O55 | O56: 1917 | P56: =O56-N56 | R56: =R55 | S56: NIGHT
A57: =A56+1 | B57: DAY | C57: =D56 | D57: 197 | E57: =D57-C57 | F57: 290 | G57: 195 | H57: =G57-G55 | I57: =F57/H57 | N57: =O56 | O57: 1990 | P57: =O57-N57 | R57: =R56+1 | S57: DAY
A58: =A57 | B58: NIGHT | C58: =D57 | D58: 208 | E58: =D58-C58 | N58: =O57 | O58: 2115 | P58: =O58-N58 | R58: =R57 | S58: NIGHT
A59: =A58+1 | B59: DAY | C59: =D58 | D59: 218 | E59: =D59-C59 | F59: 170 | G59: 211 | H59: =G59-G57 | I59: =F59/H59 | N59: =O58 | O59: 2212 | P59: =O59-N59 | R59: =R58+1 | S59: DAY | T59: 9 | U59: 12 | V59: =U59-T59 | W59: 560 | X59: 11 | AE59: 1 | AF59: 22 | AG59: 22
A60: =A59 | B60: NIGHT | C60: =D59 | D60: 228 | E60: =D60-C60 | N60: =O59 | O60: 2329 | P60: =O60-N60 | R60: =R59 | S60: NIGHT | T60: 12 | U60: 21 | V60: =U60-T60 | AE60: 22 | AF60: 75 | AG60: =AF60-AE60
A61: =A60+1 | B61: DAY | C61: =D60 | D61: 235 | E61: =D61-C61 | F61: 230 | G61: 231 | H61: =G61-G59 | I61: =F61/H61 | N61: =O60 | O61: 2410 | P61: =O61-N61 | R61: =R60+1 | S61: DAY | T61: =U60 | U61: 28 | V61: =U61-T61 | W61: 150 | X61: 27 | Y61: =X61-X59 | Z61: =W61/Y61 | AE61: =AF60 | AF61: 106 | AG61: =AF61-AE61
A62: =A61 | B62: NIGHT | C62: =D61 | D62: 246 | E62: =D62-C62 | N62: =O61 | O62: 2516 | P62: =O62-N62 | R62: =R61 | S62: NIGHT | T62: =U61 | U62: 37 | V62: =U62-T62 | AE62: =AF61 | AF62: 225 | AG62: =AF62-AE62
A63: TOTAL Running Hours: | E63: =SUBTOTAL(9,E3:E62) | F63: =SUBTOTAL(9,F3:F62) | I63: =F63/E63 | J63: TOTAL BREAKDOWN 14:00Hrs | P63: =SUBTOTAL(9,P3:P62) | R63: TOTAL Running Hours: | V63: =SUBTOTAL(9,V3:V62) | W63: =SUBTOTAL(9,W3:W62) | Z63: =W63/V63 | AA63: TOTAL BREAKDOWN 0:00 | AG63: =SUBTOTAL(9,AG3:AG62)
B66: Tax invoice raised on 27-05-26 month of April-26 | R66: Tax invoice raised on 27-05-26 month of April-26

Sheet May-26
A1: NEW MACHINE NO - XCMG-8 | J1: BREAKDOWN TIME/Cooling | R1: NEW MACHINE NO - SANY-9 | AA1: BREAKDOWN TIME/Cooling
A2: DATE | B2: SHIFT | C2: SHIFT START - HMR | D2: SHIFT END - HMR | E2: HOURS | F2: DIESEL | G2: HMR | H2: HOURS | I2: AVERAGE | J2: START TIME | K2: END TIME | L2: TOTAL HRS | M2: Remarks | N2: Container Start Count | O2: Container End Count | P2: Total | R2: DATE | S2: SHIFT | T2: SHIFT START - HMR | U2: SHIFT END - HMR | V2: HOURS | W2: DIESEL | X2: HMR | Y2: HOURS | Z2: AVERAGE | AA2: START TIME | AB2: END TIME | AC2: TOTAL HRS | AD2: Remarks | AE2: Container Start Count | AF2: Container End Count | AG2: Total
G3: 231 | X3: 27
A4: 46143 | B4: DAY | C4: 246 | D4: 252 | E4: =D4-C4 | F4: 200 | G4: 250 | H4: =G4-G3 | I4: =F4/H4 | J4: 0.29166667 | K4: 0.33333333 | L4: 0.041666667 | M4: Cooling | N4: 2516 | O4: 2634 | P4: =O4-N4 | R4: 46143 | S4: DAY | T4: 37 | U4: 42 | V4: =U4-T4 | W4: 100 | X4: 37 | Y4: =X4-X3 | Z4: =W4/Y4 | AA4: 0.29166667 | AB4: 0.33333333 | AC4: =AB4-AA4 | AD4: Cooling | AE4: 225 | AF4: 316 | AG4: =AF4-AE4
A5: =A4 | B5: NIGHT | C5: =D4 | D5: 263 | E5: =D5-C5 | N5: =O4 | O5: 2712 | P5: =O5-N5 | R5: =R4 | S5: NIGHT | T5: =U4 | U5: 49 | V5: =U5-T5 | AE5: =AF4 | AF5: 429 | AG5: =AF5-AE5
A6: =A5+1 | B6: DAY | C6: =D5 | D6: 270 | E6: =D6-C6 | F6: 170 | G6: 267 | H6: =G6-G4 | I6: =F6/H6 | N6: =O5 | O6: 2798 | P6: =O6-N6 | R6: =R5+1 | S6: DAY | T6: =U5 | U6: 54 | V6: =U6-T6 | W6: 200 | X6: 50 | Y6: =X6-X4 | Z6: =W6/Y6 | AA6: 0.10416667 | AB6: 0.14583333 | AC6: =AB6-AA6 | AD6: Cooling | AE6: =AF5 | AF6: 511 | AG6: =AF6-AE6
A7: =A6 | B7: NIGHT | C7: =D6 | D7: 280 | E7: =D7-C7 | N7: =O6 | O7: 2862 | P7: =O7-N7 | R7: =R6 | S7: NIGHT | T7: =U6 | U7: 59 | V7: =U7-T7 | AE7: =AF6 | AF7: 580 | AG7: =AF7-AE7
A8: =A7+1 | B8: DAY | C8: =D7 | D8: 280 | E8: =D8-C8 | F8: 120 | G8: 280 | H8: =G8-G6 | I8: =F8/H8 | J8: 0.33333333 | K8: 0.83333333 | L8: =K8-J8 | M8: No Operator | N8: =O7 | O8: 2862 | P8: =O8-N8 | R8: =R7+1 | S8: DAY | T8: =U7 | U8: 69 | V8: =U8-T8 | W8: 140 | X8: 61 | Y8: =X8-X6 | Z8: =W8/Y8 | AE8: =AF7 | AF8: 704 | AG8: =AF8-AE8
A9: =A8 | B9: NIGHT | C9: =D8 | D9: 290 | E9: =D9-C9 | N9: =O8 | O9: 2985 | P9: =O9-N9 | R9: =R8 | S9: NIGHT | T9: =U8 | U9: 77 | V9: =U9-T9 | AE9: =AF8 | AF9: 825 | AG9: =AF9-AE9
A10: =A9+1 | B10: DAY | C10: =D9 | D10: 290 | E10: =D10-C10 | J10: 0.33333333 | K10: 0.83333333 | L10: =K10-J10 | M10: No Operator | N10: =O9 | O10: 2985 | P10: =O10-N10 | R10: =R9+1 | S10: DAY | T10: =U9 | U10: 87 | V10: =U10-T10 | W10: 280 | X10: 82 | Y10: =X10-X8 | Z10: =W10/Y10 | AE10: =AF9 | AF10: 936 | AG10: =AF10-AE10
A11: =A10 | B11: NIGHT | C11: =D10 | D11: 301 | E11: =D11-C11 | N11: =O10 | O11: 3090 | P11: =O11-N11 | R11: =R10 | S11: NIGHT | T11: =U10 | U11: 97 | V11: =U11-T11 | AE11: =AF10 | AF11: 1116 | AG11: =AF11-AE11
A12: =A11+1 | B12: DAY | C12: =D11 | D12: 310 | E12: =D12-C12 | F12: 90 | G12: 304 | H12: =G12-G8 | I12: =F12/H12 | N12: =O11 | O12: 3211 | P12: =O12-N12 | R12: =R11+1 | S12: DAY | T12: =U11 | U12: 105 | V12: =U12-T12 | W12: 200 | X12: 104 | Y12: =X12-X10 | Z12: =W12/Y12 | AE12: =AF11 | AF12: 1170 | AG12: =AF12-AE12
A13: =A12 | B13: NIGHT | C13: =D12 | D13: 310 | E13: =D13-C13 | J13: 0.33333333 | K13: 0.83333333 | L13: =K13-J13 | M13: No Operator | N13: =O12 | O13: 3211 | P13: =O13-N13 | R13: =R12 | S13: NIGHT | T13: =U12 | U13: 116 | V13: =U13-T13 | AE13: =AF12 | AF13: 1272 | AG13: =AF13-AE13
A14: =A13+1 | B14: DAY | C14: =D13 | D14: 320 | E14: =D14-C14 | F14: 180 | G14: 316 | H14: =G14-G12 | I14: =F14/H14 | N14: =O13 | O14: 3415 | P14: =O14-N14 | R14: =R13+1 | S14: DAY | T14: =U13 | U14: 123 | V14: =U14-T14 | AA14: 0.29166667 | AB14: 0.33333333 | AC14: 0.041666667 | AD14: Cooling | AE14: =AF13 | AF14: 1345 | AG14: =AF14-AE14
A15: =A14 | B15: NIGHT | C15: =D14 | D15: 320 | E15: =D15-C15 | J15: 0.33333333 | K15: 0.83333333 | L15: =K15-J15 | M15: No Operator | N15: =O14 | O15: 3415 | P15: =O15-N15 | R15: =R14 | S15: NIGHT | T15: =U14 | U15: 134 | V15: =U15-T15 | AE15: =AF14 | AF15: 1461 | AG15: =AF15-AE15
A16: =A15+1 | B16: DAY | C16: =D15 | D16: 329 | E16: =D16-C16 | F16: 130 | G16: 324 | H16: =G16-G14 | I16: =F16/H16 | N16: =O15 | O16: 3575 | P16: =O16-N16 | R16: =R15+1 | S16: DAY | T16: =U15 | U16: 139 | V16: =U16-T16 | W16: 200 | X16: 137 | Y16: =X16-X12 | Z16: =W16/Y16 | AA16: 0.29166667 | AB16: 0.33333333 | AC16: 0.041666667 | AD16: Cooling | AE16: =AF15 | AF16: 1510 | AG16: =AF16-AE16
A17: =A16 | B17: NIGHT | C17: =D16 | D17: 329 | E17: =D17-C17 | J17: 0.33333333 | K17: 0.83333333 | L17: =K17-J17 | M17: No Operator | N17: =O16 | O17: 3575 | P17: =O17-N17 | R17: =R16 | S17: NIGHT | T17: =U16 | U17: 150 | V17: =U17-T17 | AE17: =AF16 | AF17: 1595 | AG17: =AF17-AE17
A18: =A17+1 | B18: DAY | C18: =D17 | D18: 336 | E18: =D18-C18 | F18: 120 | G18: 334 | H18: =G18-G16 | I18: =F18/H18 | J18: 0.27083333 | K18: 0.33333333 | L18: =K18-J18 | M18: Cooling | N18: =O17 | O18: 3700 | P18: =O18-N18 | R18: =R17+1 | S18: DAY | T18: =U17 | U18: 160 | V18: =U18-T18 | W18: 130 | X18: 153 | Y18: =X18-X16 | Z18: =W18/Y18 | AE18: =AF17 | AF18: 1742 | AG18: =AF18-AE18
A19: =A18 | B19: NIGHT | C19: =D18 | D19: 336 | E19: =D19-C19 | J19: 0.33333333 | K19: 0.83333333 | L19: =K19-J19 | M19: No Operator | N19: =O18 | O19: 3700 | P19: =O19-N19 | R19: =R18 | S19: NIGHT | T19: =U18 | U19: 171 | V19: =U19-T19 | AE19: =AF18 | AF19: 1799 | AG19: =AF19-AE19
A20: =A19+1 | B20: DAY | C20: =D19 | D20: 341 | E20: =D20-C20 | F20: 71 | G20: 339 | H20: =G20-G18 | I20: =F20/H20 | J20: 0.29166667 | K20: 0.33333333 | L20: =K20-J20 | M20: Cooling | N20: =O19 | O20: 3758 | P20: =O20-N20 | R20: =R19+1 | S20: DAY | T20: =U19 | U20: 179 | V20: =U20-T20 | W20: 250 | X20: 175 | Y20: =X20-X18 | Z20: =W20/Y20 | AE20: =AF19 | AF20: 1907 | AG20: =AF20-AE20
A21: =A20 | B21: NIGHT | C21: =D20 | D21: 351 | E21: =D21-C21 | J21: 0.33333333 | K21: 0.83333333 | L21: =K21-J21 | M21: No Operator | N21: =O20 | O21: 3804 | P21: =O21-N21 | R21: =R20 | S21: NIGHT | T21: =U20 | U21: 189 | V21: =U21-T21 | AE21: =AF20 | AF21: 1961 | AG21: =AF21-AE21
A22: =A21+1 | B22: DAY | C22: =D21 | D22: 351 | E22: =D22-C22 | J22: 0.33333333 | K22: 0.83333333 | L22: =K22-J22 | M22: No Operator | N22: =O21 | O22: 3804 | P22: =O22-N22 | R22: =R21+1 | S22: DAY | T22: =U21 | U22: 200 | V22: =U22-T22 | W22: 140 | X22: 191 | Y22: =X22-X20 | Z22: =W22/Y22 | AE22: =AF21 | AF22: 2060 | AG22: =AF22-AE22
A23: =A22 | B23: NIGHT | C23: =D22 | D23: 361 | E23: =D23-C23 | N23: =O22 | O23: 3855 | P23: =O23-N23 | R23: =R22 | S23: NIGHT | T23: =U22 | U23: 211 | V23: =U23-T23 | AE23: =AF22 | AF23: 2128 | AG23: =AF23-AE23
A24: =A23+1 | B24: DAY | C24: =D23 | D24: 367 | E24: =D24-C24 | F24: 200 | G24: 361 | H24: =G24-G20 | I24: =F24/H24 | J24: 0.097222222 | K24: 0.21875 | L24: =K24-J24 | M24: Joystick communication error | N24: =O23 | O24: 3957 | P24: =O24-N24 | R24: =R23+1 | S24: DAY | T24: =U23 | U24: 219 | V24: =U24-T24 | W24: 220 | X24: 214 | Y24: =X24-X22 | Z24: =W24/Y24 | AE24: =AF23 | AF24: 2203 | AG24: =AF24-AE24
A25: =A24 | B25: NIGHT | C25: =D24 | D25: 367 | E25: =D25-C25 | J25: 0.33333333 | K25: 0.83333333 | L25: =K25-J25 | M25: No Operator | N25: =O24 | O25: 3957 | P25: =O25-N25 | R25: =R24 | S25: NIGHT | T25: =U24 | U25: 230 | V25: =U25-T25 | AE25: =AF24 | AF25: 2268 | AG25: =AF25-AE25
A26: =A25+1 | B26: DAY | C26: =D25 | D26: 377 | E26: =D26-C26 | F26: 91 | G26: 372 | H26: =G26-G24 | I26: =F26/H26 | N26: =O25 | O26: 4073 | P26: =O26-N26 | R26: =R25+1 | S26: DAY | T26: =U25 | U26: 241 | V26: =U26-T26 | W26: 250 | X26: 237 | Y26: =X26-X24 | Z26: =W26/Y26 | AE26: =AF25 | AF26: 2420 | AG26: =AF26-AE26
A27: =A26 | B27: NIGHT | C27: =D26 | D27: 377 | E27: =D27-C27 | J27: 0.33333333 | K27: 0.83333333 | L27: =K27-J27 | M27: No Operator | N27: =O26 | O27: 4073 | P27: =O27-N27 | R27: =R26 | S27: NIGHT | T27: =U26 | U27: 252 | V27: =U27-T27 | AE27: =AF26 | AF27: 2552 | AG27: =AF27-AE27
A28: =A27+1 | B28: DAY | C28: =D27 | D28: 383 | E28: =D28-C28 | F28: 80 | G28: 379 | H28: =G28-G26 | I28: =F28/H28 | J28: 0.52083333 | K28: 0.72222222 | L28: =K28-J28 | M28: A/C PROBLEM | N28: =O27 | O28: 4178 | P28: =O28-N28 | R28: =R27+1 | S28: DAY | T28: =U27 | U28: 263 | V28: =U28-T28 | W28: 240 | X28: 255 | Y28: =X28-X26 | Z28: =W28/Y28 | AE28: =AF27 | AF28: 2730 | AG28: =AF28-AE28
A29: =A28 | B29: NIGHT | C29: =D28 | D29: 383 | E29: =D29-C29 | J29: 0.33333333 | K29: 0.83333333 | L29: =K29-J29 | M29: No Operator | N29: =O28 | O29: 4178 | P29: =O29-N29 | R29: =R28 | S29: NIGHT | T29: =U28 | U29: 275 | V29: =U29-T29 | AE29: =AF28 | AF29: 2840 | AG29: =AF29-AE29
A30: =A29+1 | B30: DAY | C30: =D29 | D30: 392 | E30: =D30-C30 | N30: =O29 | O30: 4263 | P30: =O30-N30 | R30: =R29+1 | S30: DAY | T30: =U29 | U30: 281 | V30: =U30-T30 | W30: 200 | X30: 276 | Y30: =X30-X28 | Z30: =W30/Y30 | AE30: =AF29 | AF30: 2925 | AG30: =AF30-AE30
A31: =A30 | B31: NIGHT | C31: =D30 | D31: 400 | E31: =D31-C31 | N31: =O30 | O31: 4378 | P31: =O31-N31 | R31: =R30 | S31: NIGHT | T31: =U30 | U31: 291 | V31: =U31-T31 | AE31: =AF30 | AF31: 2979 | AG31: =AF31-AE31
A32: =A31+1 | B32: DAY | C32: =D31 | D32: 410 | E32: =D32-C32 | F32: 250 | G32: 402 | H32: =G32-G28 | I32: =F32/H32 | J32: 0.45833333 | K32: 0.54166667 | L32: =K32-J32 | M32: Maintnance | N32: =O31 | O32: 4472 | P32: =O32-N32 | R32: =R31+1 | S32: DAY | T32: =U31 | U32: 298 | V32: =U32-T32 | W32: 90 | X32: 292 | Y32: =X32-X30 | Z32: =W32/Y32 | AE32: =AF31 | AF32: 3061 | AG32: =AF32-AE32
A33: =A32 | B33: NIGHT | C33: =D32 | D33: 419 | E33: =D33-C33 | N33: =O32 | O33: 4520 | P33: =O33-N33 | R33: =R32 | S33: NIGHT | T33: =U32 | U33: 302 | V33: =U33-T33 | AE33: =AF32 | AF33: 3104 | AG33: =AF33-AE33
A34: =A33+1 | B34: DAY | C34: =D33 | D34: 429 | E34: =D34-C34 | F34: 210 | G34: 425 | H34: =G34-G32 | I34: =F34/H34 | N34: =O33 | O34: 4604 | P34: =O34-N34 | R34: =R33+1 | S34: DAY | T34: =U33 | U34: 310 | V34: =U34-T34 | W34: 230 | X34: 304 | Y34: =X34-X32 | Z34: =W34/Y34 | AE34: =AF33 | AF34: 3177 | AG34: =AF34-AE34
A35: =A34 | B35: NIGHT | C35: =D34 | D35: 437 | E35: =D35-C35 | N35: =O34 | O35: 4766 | P35: =O35-N35 | R35: =R34 | S35: NIGHT | T35: =U34 | U35: 321 | V35: =U35-T35 | AE35: =AF34 | AF35: 3289 | AG35: =AF35-AE35
A36: =A35+1 | B36: DAY | C36: =D35 | D36: 437 | E36: =D36-C36 | J36: 0.33333333 | K36: 0.83333333 | L36: =K36-J36 | M36: No Operator | N36: =O35 | O36: 4766 | P36: =O36-N36 | R36: =R35+1 | S36: DAY | T36: =U35 | U36: 329 | V36: =U36-T36 | W36: 190 | X36: 323 | Y36: =X36-X34 | Z36: =W36/Y36 | AE36: =AF35 | AF36: 3371 | AG36: =AF36-AE36
A37: =A36 | B37: NIGHT | C37: =D36 | D37: 437 | E37: =D37-C37 | J37: 0.33333333 | K37: 0.83333333 | L37: =K37-J37 | M37: No Operator | N37: =O36 | O37: 4766 | P37: =O37-N37 | R37: =R36 | S37: NIGHT | T37: =U36 | U37: 339 | V37: =U37-T37 | AE37: =AF36 | AF37: 3517 | AG37: =AF37-AE37
A38: =A37+1 | B38: DAY | C38: =D37 | D38: 446 | E38: =D38-C38 | F38: 190 | G38: 440 | H38: =G38-G34 | I38: =F38/H38 | N38: =O37 | O38: 4869 | P38: =O38-N38 | R38: =R37+1 | S38: DAY | T38: =U37 | U38: 347 | V38: =U38-T38 | W38: 290 | X38: 344 | Y38: =X38-X36 | Z38: =W38/Y38 | AE38: =AF37 | AF38: 3633 | AG38: =AF38-AE38
A39: =A38 | B39: NIGHT | C39: =D38 | D39: 456 | E39: =D39-C39 | N39: =O38 | O39: 4909 | P39: =O39-N39 | R39: =R38 | S39: NIGHT | T39: =U38 | U39: 355 | V39: =U39-T39 | AE39: =AF38 | AF39: 3681 | AG39: =AF39-AE39
A40: =A39+1 | B40: DAY | C40: =D39 | D40: 461 | E40: =D40-C40 | F40: 90 | G40: 456 | H40: =G40-G38 | I40: =F40/H40 | J40: 0.54166667 | K40: 0.83333333 | L40: =K40-J40 | M40: Break oil leakage | N40: =O39 | O40: 4925 | P40: =O40-N40 | R40: =R39+1 | S40: DAY | T40: =U39 | U40: 363 | V40: =U40-T40 | W40: 160 | X40: 356 | Y40: =X40-X38 | Z40: =W40/Y40 | AE40: =AF39 | AF40: 3764 | AG40: =AF40-AE40
A41: =A40 | B41: NIGHT | C41: =D40 | D41: 461 | E41: =D41-C41 | J41: 0.83333333 | K41: 0.33333333 | L41: =J41-K41 | M41: Break oil leakage | N41: =O40 | O41: 4925 | P41: =O41-N41 | R41: =R40 | S41: NIGHT | T41: =U40 | U41: 372 | V41: =U41-T41 | AE41: =AF40 | AF41: 3842 | AG41: =AF41-AE41
A42: =A41+1 | B42: DAY | C42: =D41 | D42: 461 | E42: =D42-C42 | J42: 0.33333333 | K42: 0.83333333 | L42: =K42-J42 | M42: Break oil leakage | N42: =O41 | O42: 4925 | P42: =O42-N42 | R42: =R41+1 | S42: DAY | T42: =U41 | U42: 378 | V42: =U42-T42 | W42: 160 | X42: 373 | Y42: =X42-X40 | Z42: =W42/Y42 | AE42: =AF41 | AF42: 3940 | AG42: =AF42-AE42
A43: =A42 | B43: NIGHT | C43: =D42 | D43: 461 | E43: =D43-C43 | J43: 0.83333333 | K43: 0.33333333 | L43: =J43-K43 | M43: Break oil leakage | N43: =O42 | O43: 4925 | P43: =O43-N43 | R43: =R42 | S43: NIGHT | T43: =U42 | U43: 387 | V43: =U43-T43 | AE43: =AF42 | AF43: 3995 | AG43: =AF43-AE43
A44: =A43+1 | B44: DAY | C44: =D43 | D44: 462 | E44: =D44-C44 | N44: =O43 | O44: 4932 | P44: =O44-N44 | R44: =R43+1 | S44: DAY | T44: =U43 | U44: 391 | V44: =U44-T44 | W44: 240 | X44: 389 | Y44: =X44-X42 | Z44: =W44/Y44 | AE44: =AF43 | AF44: 4025 | AG44: =AF44-AE44
A45: =A44 | B45: NIGHT | C45: =D44 | D45: 472 | E45: =D45-C45 | N45: =O44 | O45: 5003 | P45: =O45-N45 | R45: =R44 | S45: NIGHT | T45: =U44 | U45: 398 | V45: =U45-T45 | AE45: =AF44 | AF45: 4095 | AG45: =AF45-AE45
A46: =A45+1 | B46: DAY | C46: =D45 | D46: 474 | E46: =D46-C46 | N46: =O45 | O46: 5004 | P46: =O46-N46 | R46: =R45+1 | S46: DAY | T46: =U45 | U46: 405 | V46: =U46-T46 | W46: 180 | X46: 402 | Y46: =X46-X44 | Z46: =W46/Y46 | AE46: =AF45 | AF46: 4153 | AG46: =AF46-AE46
A47: =A46 | B47: NIGHT | C47: =D46 | D47: 474 | E47: =D47-C47 | J47: 0.83333333 | K47: 0.33333333 | L47: =J47-K47 | M47: Break oil leakage | N47: =O46 | O47: 5004 | P47: =O47-N47 | R47: =R46 | S47: NIGHT | T47: =U46 | U47: 416 | V47: =U47-T47 | AE47: =AF46 | AF47: 4233 | AG47: =AF47-AE47
A48: =A47+1 | B48: DAY | C48: =D47 | D48: 476 | E48: =D48-C48 | J48: 0.33333333 | K48: 0.83333333 | L48: =K48-J48 | M48: Break oil leakage | N48: =O47 | O48: 5004 | P48: =O48-N48 | R48: =R47+1 | S48: DAY | T48: =U47 | U48: 425 | V48: =U48-T48 | W48: 170 | X48: 421 | Y48: =X48-X46 | Z48: =W48/Y48 | AE48: =AF47 | AF48: 4298 | AG48: =AF48-AE48
A49: =A48 | B49: NIGHT | C49: =D48 | D49: 486 | E49: =D49-C49 | N49: =O48 | O49: 5048 | P49: =O49-N49 | R49: =R48 | S49: NIGHT | T49: =U48 | U49: 431 | V49: =U49-T49 | AE49: =AF48 | AF49: 4334 | AG49: =AF49-AE49
A50: =A49+1 | B50: DAY | C50: =D49 | D50: 492 | E50: =D50-C50 | F50: 290 | G50: 489 | H50: =G50-G40 | I50: =F50/H50 | N50: =O49 | O50: 5104 | P50: =O50-N50 | R50: =R49+1 | S50: DAY | T50: =U49 | U50: 434 | V50: =U50-T50 | W50: 110 | X50: 433 | Y50: =X50-X48 | Z50: =W50/Y50 | AE50: =AF49 | AF50: 4348 | AG50: =AF50-AE50
A51: =A50 | B51: NIGHT | C51: =D50 | D51: 498 | E51: =D51-C51 | N51: =O50 | O51: 5194 | P51: =O51-N51 | R51: =R50 | S51: NIGHT | T51: =U50 | U51: 444 | V51: =U51-T51 | AE51: =AF50 | AF51: 4452 | AG51: =AF51-AE51
A52: =A51+1 | B52: DAY | C52: =D51 | D52: 507 | E52: =D52-C52 | F52: 170 | G52: 504 | H52: =G52-G50 | I52: =F52/H52 | N52: =O51 | O52: 5271 | P52: =O52-N52 | R52: =R51+1 | S52: DAY | T52: =U51 | U52: 452 | V52: =U52-T52 | W52: 180 | X52: 449 | Y52: =X52-X50 | Z52: =W52/Y52 | AE52: =AF51 | AF52: 4570 | AG52: =AF52-AE52
A53: =A52 | B53: NIGHT | C53: =D52 | D53: 517 | E53: =D53-C53 | N53: =O52 | O53: 5326 | P53: =O53-N53 | R53: =R52 | S53: NIGHT | T53: =U52 | U53: 459 | V53: =U53-T53 | AE53: =AF52 | AF53: 4616 | AG53: =AF53-AE53
A54: =A53+1 | B54: DAY | C54: =D53 | D54: 524 | E54: =D54-C54 | F54: 120 | G54: 519 | H54: =G54-G52 | I54: =F54/H54 | N54: =O53 | O54: 5418 | P54: =O54-N54 | R54: =R53+1 | S54: DAY | T54: =U53 | U54: 468 | V54: =U54-T54 | W54: 150 | X54: 462 | Y54: =X54-X52 | Z54: =W54/Y54 | AE54: =AF53 | AF54: 4693 | AG54: =AF54-AE54
A55: =A54 | B55: NIGHT | C55: =D54 | D55: 531 | E55: =D55-C55 | N55: =O54 | O55: 5504 | P55: =O55-N55 | R55: =R54 | S55: NIGHT | T55: =U54 | U55: 479 | V55: =U55-T55 | AE55: =AF54 | AF55: 4779 | AG55: =AF55-AE55
A56: =A55+1 | B56: DAY | C56: =D55 | D56: 540 | E56: =D56-C56 | F56: 160 | G56: 534 | H56: =G56-G54 | I56: =F56/H56 | N56: =O55 | O56: 5579 | P56: =O56-N56 | R56: =R55+1 | S56: DAY | T56: =U55 | U56: 486 | V56: =U56-T56 | W56: 200 | X56: 481 | Y56: =X56-X54 | Z56: =W56/Y56 | AE56: =AF55 | AF56: 4835 | AG56: =AF56-AE56
A57: =A56 | B57: NIGHT | C57: =D56 | D57: 549 | E57: =D57-C57 | N57: =O56 | O57: 5609 | P57: =O57-N57 | R57: =R56 | S57: NIGHT | T57: =U56 | U57: 493 | V57: =U57-T57 | AE57: =AF56 | AF57: 4877 | AG57: =AF57-AE57
A58: =A57+1 | B58: DAY | C58: =D57 | D58: 551 | E58: =D58-C58 | F58: 150 | G58: 550 | H58: =G58-G56 | I58: =F58/H58 | N58: =O57 | O58: 5622 | P58: =O58-N58 | R58: =R57+1 | S58: DAY | T58: =U57 | U58: 498 | V58: =U58-T58 | W58: 160 | X58: 496 | Y58: =X58-X56 | Z58: =W58/Y58 | AE58: =AF57 | AF58: 4927 | AG58: =AF58-AE58
A59: =A58 | B59: NIGHT | C59: =D58 | D59: 560 | E59: =D59-C59 | N59: =O58 | O59: 5784 | P59: =O59-N59 | R59: =R58 | S59: NIGHT | T59: =U58 | U59: 508 | V59: =U59-T59 | AE59: =AF58 | AF59: 5023 | AG59: =AF59-AE59
A60: =A59+1 | B60: DAY | C60: =D59 | D60: 567 | E60: =D60-C60 | F60: 140 | G60: 564 | H60: =G60-G58 | I60: =F60/H60 | N60: =O59 | O60: 5883 | P60: =O60-N60 | R60: =R59+1 | S60: DAY | T60: =U59 | U60: 517 | V60: =U60-T60 | W60: 200 | X60: 514 | Y60: =X60-X58 | Z60: =W60/Y60 | AE60: =AF59 | AF60: 5108 | AG60: =AF60-AE60
A61: =A60 | B61: NIGHT | C61: =D60 | D61: 574 | E61: =D61-C61 | N61: =O60 | O61: 5951 | P61: =O61-N61 | R61: =R60 | S61: NIGHT | T61: =U60 | U61: 523 | V61: =U61-T61 | AE61: =AF60 | AF61: 5160 | AG61: =AF61-AE61
A62: =A61+1 | B62: DAY | C62: =D61 | D62: 580 | E62: =D62-C62 | F62: 150 | G62: 575 | H62: =G62-G60 | I62: =F62/H62 | N62: =O61 | O62: 6019 | P62: =O62-N62 | R62: =R61+1 | S62: DAY | T62: =U61 | U62: 528 | V62: =U62-T62 | W62: 140 | X62: 526 | Y62: =X62-X60 | Z62: =W62/Y62 | AE62: =AF61 | AF62: 5237 | AG62: =AF62-AE62
A63: =A62 | B63: NIGHT | C63: =D62 | D63: 588 | E63: =D63-C63 | N63: =O62 | O63: 6112 | P63: =O63-N63 | R63: =R62 | S63: NIGHT | T63: =U62 | U63: 538 | V63: =U63-T63 | AE63: =AF62 | AF63: 5311 | AG63: =AF63-AE63
A64: =A63+1 | B64: DAY | C64: =D63 | D64: 597 | E64: =D64-C64 | F64: 120 | G64: 589 | H64: =G64-G62 | I64: =F64/H64 | N64: =O63 | O64: 6193 | P64: =O64-N64 | R64: =R63+1 | S64: DAY | T64: =U63 | U64: 544 | V64: =U64-T64 | W64: 130 | X64: 539 | Y64: =X64-X62 | Z64: =W64/Y64 | AE64: =AF63 | AF64: 5379 | AG64: =AF64-AE64
A65: =A64 | B65: NIGHT | C65: =D64 | D65: 605 | E65: =D65-C65 | N65: =O64 | O65: 6261 | P65: =O65-N65 | R65: =R64 | S65: NIGHT | T65: =U64 | U65: 551 | V65: =U65-T65 | AE65: =AF64 | AF65: 5436 | AG65: =AF65-AE65
A66: TOTAL Running Hours: | E66: =SUBTOTAL(9,E4:E65) | F66: =SUBTOTAL(9,F4:F65) | I66: =F66/E66 | J66: TOTAL BREAKDOWN 74:45 Hrs | P66: =SUBTOTAL(9,P4:P65) | R66: TOTAL Running Hours: | V66: =SUBTOTAL(9,V4:V65) | W66: =SUBTOTAL(9,W4:W65) | Z66: =W66/V66 | AA66: TOTAL BREAKDOWN 0:00 | AG66: =SUBTOTAL(9,AG4:AG65)
E67: Total diesel according to bmct | F67: =F66-90
A69: Tax invoice raised on 11-06-26 month of April-26 | S69: Tax invoice raised on 10-06-26 month of April-26

Sheet June-26
A1: NEW MACHINE NO - XCMG-8 | J1: BREAKDOWN TIME/Cooling | R1: NEW MACHINE NO - SANY-9 | AA1: BREAKDOWN TIME/Cooling
A2: DATE | B2: SHIFT | C2: SHIFT START - HMR | D2: SHIFT END - HMR | E2: HOURS | F2: DIESEL | G2: HMR | H2: HOURS | I2: AVERAGE | J2: START TIME | K2: END TIME | L2: TOTAL HRS | M2: Remarks | N2: Container Start Count | O2: Container End Count | P2: Total | R2: DATE | S2: SHIFT | T2: SHIFT START - HMR | U2: SHIFT END - HMR | V2: HOURS | W2: DIESEL | X2: HMR | Y2: HOURS | Z2: AVERAGE | AA2: START TIME | AB2: END TIME | AC2: TOTAL HRS | AD2: Remarks | AE2: Container Start Count | AF2: Container End Count | AG2: Total
G3: 589 | X3: 539
A4: 46174 | B4: DAY | C4: 605 | D4: 616 | E4: =D4-C4 | F4: 180 | G4: 608 | H4: =G4-G3 | I4: =F4/H4 | J4: XCMG(RST-08) MOVE TO TALOJA FROM BMCT PORT 10-JUN-26 & THEN RST DEPLOYED IN KATTUPALLI 17-06-26. | N4: 6261 | O4: 6362 | P4: =O4-N4 | R4: 46174 | S4: DAY | T4: 551 | U4: 558 | V4: =U4-T4 | W4: 150 | X4: 552 | Y4: =X4-X3 | Z4: =W4/Y4 | AE4: 5436 | AF4: 5500 | AG4: =AF4-AE4
A5: =A4 | B5: NIGHT | C5: =D4 | D5: 624 | E5: =D5-C5 | N5: =O4 | O5: 6515 | P5: =O5-N5 | R5: =R4 | S5: NIGHT | T5: =U4 | U5: 567 | V5: =U5-T5 | AE5: =AF4 | AF5: 5592 | AG5: =AF5-AE5
A6: =A5+1 | B6: DAY | C6: =D5 | D6: 629 | E6: =D6-C6 | F6: 240 | G6: 627 | H6: =G6-G4 | I6: =F6/H6 | N6: =O5 | O6: 6527 | P6: =O6-N6 | R6: =R5+1 | S6: DAY | T6: =U5 | U6: 573 | V6: =U6-T6 | W6: 200 | X6: 570 | Y6: =X6-X4 | Z6: =W6/Y6 | AE6: =AF5 | AF6: 5622 | AG6: =AF6-AE6
A7: =A6 | B7: NIGHT | C7: =D6 | D7: 638 | E7: =D7-C7 | N7: =O6 | O7: 6576 | P7: =O7-N7 | R7: =R6 | S7: NIGHT | T7: =U6 | U7: 581 | V7: =U7-T7 | AE7: =AF6 | AF7: 5688 | AG7: =AF7-AE7
A8: =A7+1 | B8: DAY | C8: =D7 | D8: 645 | E8: =D8-C8 | F8: 110 | G8: 638 | H8: =G8-G6 | I8: =F8/H8 | N8: =O7 | O8: 6633 | P8: =O8-N8 | R8: =R7+1 | S8: DAY | T8: =U7 | U8: 592 | V8: =U8-T8 | W8: 190 | X8: 585 | Y8: =X8-X6 | Z8: =W8/Y8 | AE8: =AF7 | AF8: 5741 | AG8: =AF8-AE8
A9: =A8 | B9: NIGHT | C9: =D8 | D9: 652 | E9: =D9-C9 | N9: =O8 | O9: 6713 | P9: =O9-N9 | R9: =R8 | S9: NIGHT | T9: =U8 | U9: 600 | V9: =U9-T9 | AE9: =AF8 | AF9: 5853 | AG9: =AF9-AE9
A10: =A9+1 | B10: DAY | C10: =D9 | D10: 662 | E10: =D10-C10 | F10: 150 | G10: 656 | H10: =G10-G8 | I10: =F10/H10 | N10: =O9 | O10: 6933 | P10: =O10-N10 | R10: =R9+1 | S10: DAY | T10: =U9 | U10: 612 | V10: =U10-T10 | W10: 250 | X10: 605 | Y10: =X10-X8 | Z10: =W10/Y10 | AE10: =AF9 | AF10: 5996 | AG10: =AF10-AE10
A11: =A10 | B11: NIGHT | C11: =D10 | D11: 672 | E11: =D11-C11 | N11: =O10 | O11: 7071 | P11: =O11-N11 | R11: =R10 | S11: NIGHT | T11: =U10 | U11: 619 | V11: =U11-T11 | AE11: =AF10 | AF11: 6053 | AG11: =AF11-AE11
A12: =A11+1 | B12: DAY | C12: 10 | D12: 15 | E12: =D12-C12 | F12: 400 | G12: 12 | J12: NEW SANY (RST-08) MACHINE START ON 05-06-26 | N12: 24 | O12: 52 | P12: =O12-N12 | R12: =R11+1 | S12: DAY | T12: =U11 | U12: 630 | V12: =U12-T12 | W12: 200 | X12: 626 | Y12: =X12-X10 | Z12: =W12/Y12 | AE12: =AF11 | AF12: 6169 | AG12: =AF12-AE12
A13: =A12 | B13: NIGHT | C13: =D12 | D13: 24 | E13: =D13-C13 | N13: =O12 | O13: 153 | P13: =O13-N13 | R13: =R12 | S13: NIGHT | T13: =U12 | U13: 639 | V13: =U13-T13 | AE13: =AF12 | AF13: 6258 | AG13: =AF13-AE13
A14: =A13+1 | B14: DAY | C14: =D13 | D14: 34 | E14: =D14-C14 | F14: 220 | G14: 26 | H14: =G14-G12 | I14: =F14/H14 | N14: =O13 | O14: 271 | P14: =O14-N14 | R14: =R13+1 | S14: DAY | T14: =U13 | U14: 647 | V14: =U14-T14 | W14: 200 | X14: 641 | Y14: =X14-X12 | Z14: =W14/Y14 | AE14: =AF13 | AF14: 6345 | AG14: =AF14-AE14
A15: =A14 | B15: NIGHT | C15: =D14 | D15: 44 | E15: =D15-C15 | N15: =O14 | O15: 369 | P15: =O15-N15 | R15: =R14 | S15: NIGHT | T15: =U14 | U15: 654 | V15: =U15-T15 | AE15: =AF14 | AF15: 6423 | AG15: =AF15-AE15
A16: =A15+1 | B16: DAY | C16: =D15 | D16: 51 | E16: =D16-C16 | F16: 210 | G16: 47 | H16: =G16-G14 | I16: =F16/H16 | N16: =O15 | O16: 446 | P16: =O16-N16 | R16: =R15+1 | S16: DAY | T16: =U15 | U16: 662 | V16: =U16-T16 | W16: 190 | X16: 657 | Y16: =X16-X14 | Z16: =W16/Y16 | AE16: =AF15 | AF16: 6508 | AG16: =AF16-AE16
A17: =A16 | B17: NIGHT | C17: =D16 | D17: 62 | E17: =D17-C17 | N17: =O16 | O17: 535 | P17: =O17-N17 | R17: =R16 | S17: NIGHT | T17: =U16 | U17: 671 | V17: =U17-T17 | AE17: =AF16 | AF17: 6617 | AG17: =AF17-AE17
A18: =A17+1 | B18: DAY | C18: =D17 | D18: 71 | E18: =D18-C18 | F18: 180 | G18: 69 | H18: =G18-G16 | I18: =F18/H18 | N18: =O17 | O18: 636 | P18: =O18-N18 | R18: =R17+1 | S18: DAY | T18: =U17 | U18: 682 | V18: =U18-T18 | W18: 220 | X18: 677 | Y18: =X18-X16 | Z18: =W18/Y18 | AE18: =AF17 | AF18: 6788 | AG18: =AF18-AE18
A19: =A18 | B19: NIGHT | C19: =D18 | D19: 76 | E19: =D19-C19 | N19: =O18 | O19: 702 | P19: =O19-N19 | R19: =R18 | S19: NIGHT | T19: =U18 | U19: 688 | V19: =U19-T19 | AE19: =AF18 | AF19: 6860 | AG19: =AF19-AE19
A20: =A19+1 | B20: DAY | C20: =D19 | D20: 83 | E20: =D20-C20 | F20: 150 | G20: 76 | H20: =G20-G16 | I20: =F20/H20 | N20: =O19 | O20: 747 | P20: =O20-N20 | R20: =R19+1 | S20: DAY | T20: =U19 | U20: 698 | V20: =U20-T20 | W20: 190 | X20: 691 | Y20: =X20-X18 | Z20: =W20/Y20 | AE20: =AF19 | AF20: 6966 | AG20: =AF20-AE20
A21: =A20 | B21: NIGHT | C21: =D20 | D21: 89 | E21: =D21-C21 | N21: =O20 | O21: 787 | P21: =O21-N21 | R21: =R20 | S21: NIGHT | T21: =U20 | U21: 700 | V21: =U21-T21 | AE21: =AF20 | AF21: 6976 | AG21: =AF21-AE21
A22: =A21+1 | B22: DAY | C22: =D21 | D22: 98 | E22: =D22-C22 | F22: 160 | G22: 91 | H22: =G22-G20 | I22: =F22/H22 | N22: =O21 | O22: 862 | P22: =O22-N22 | R22: =R21+1 | S22: DAY | T22: =U21 | U22: 704 | V22: =U22-T22 | W22: 70 | X22: 700 | Y22: =X22-X20 | Z22: =W22/Y22 | AE22: =AF21 | AF22: 6997 | AG22: =AF22-AE22
A23: =A22 | B23: NIGHT | C23: =D22 | D23: 102 | E23: =D23-C23 | N23: =O22 | O23: 906 | P23: =O23-N23 | R23: =R22 | S23: NIGHT | T23: =U22 | U23: 713 | V23: =U23-T23 | AE23: =AF22 | AF23: 7090 | AG23: =AF23-AE23
A24: =A23+1 | B24: DAY | C24: =D23 | D24: 112 | E24: =D24-C24 | F24: 110 | G24: 108 | H24: =G24-G22 | I24: =F24/H24 | N24: =O23 | O24: 1009 | P24: =O24-N24 | R24: =R23+1 | S24: DAY | T24: =U23 | U24: 720 | V24: =U24-T24 | W24: 130 | X24: 716 | Y24: =X24-X22 | Z24: =W24/Y24 | AE24: =AF23 | AF24: 7123 | AG24: =AF24-AE24
A25: =A24 | B25: NIGHT | C25: =D24 | D25: 117 | E25: =D25-C25 | N25: =O24 | O25: 1058 | P25: =O25-N25 | R25: =R24 | S25: NIGHT | T25: =U24 | U25: 729 | V25: =U25-T25 | AE25: =AF24 | AF25: 7232 | AG25: =AF25-AE25
A26: =A25+1 | B26: DAY | C26: =D25 | D26: 128 | E26: =D26-C26 | F26: 190 | G26: 122 | H26: =G26-G24 | I26: =F26/H26 | N26: =O25 | O26: 1132 | P26: =O26-N26 | R26: =R25+1 | S26: DAY | T26: =U25 | U26: 739 | V26: =U26-T26 | W26: 170 | X26: 733 | Y26: =X26-X24 | Z26: =W26/Y26 | AE26: =AF25 | AF26: 7353 | AG26: =AF26-AE26
A27: =A26 | B27: NIGHT | C27: =D26 | D27: 135 | E27: =D27-C27 | N27: =O26 | O27: 1181 | P27: =O27-N27 | R27: =R26 | S27: NIGHT | T27: =U26 | U27: 749 | V27: =U27-T27 | AE27: =AF26 | AF27: 7465 | AG27: =AF27-AE27
A28: =A27+1 | B28: DAY | C28: =D27 | D28: 143 | E28: =D28-C28 | F28: 200 | G28: 138 | H28: =G28-G26 | I28: =F28/H28 | N28: =O27 | O28: 1329 | P28: =O28-N28 | R28: =R27+1 | S28: DAY | T28: =U27 | U28: 757 | V28: =U28-T28 | W28: 220 | X28: 751 | Y28: =X28-X26 | Z28: =W28/Y28 | AE28: =AF27 | AF28: 7578 | AG28: =AF28-AE28
A29: =A28 | B29: NIGHT | C29: =D28 | D29: 154 | E29: =D29-C29 | N29: =O28 | O29: 1431 | P29: =O29-N29 | R29: =R28 | S29: NIGHT | T29: =U28 | U29: 767 | V29: =U29-T29 | AE29: =AF28 | AF29: 7670 | AG29: =AF29-AE29
A30: =A29+1 | B30: DAY | C30: =D29 | D30: 162 | E30: =D30-C30 | F30: 200 | G30: 158 | H30: =G30-G28 | I30: =F30/H30 | N30: =O29 | O30: 1554 | P30: =O30-N30 | R30: =R29+1 | S30: DAY | T30: =U29 | U30: 776 | V30: =U30-T30 | W30: 220 | X30: 770 | Y30: =X30-X28 | Z30: =W30/Y30 | AE30: =AF29 | AF30: 7801 | AG30: =AF30-AE30
A31: =A30 | B31: NIGHT | C31: =D30 | D31: 171 | E31: =D31-C31 | N31: =O30 | O31: 1636 | P31: =O31-N31 | R31: =R30 | S31: NIGHT | T31: =U30 | U31: 782 | V31: =U31-T31 | AE31: =AF30 | AF31: 7874 | AG31: =AF31-AE31
A32: =A31+1 | B32: DAY | C32: =D31 | D32: 180 | E32: =D32-C32 | F32: 150 | G32: 176 | H32: =G32-G30 | I32: =F32/H32 | N32: =O31 | O32: 1770 | P32: =O32-N32 | R32: =R31+1 | S32: DAY | T32: =U31 | U32: 791 | V32: =U32-T32 | W32: 120 | X32: 787 | Y32: =X32-X30 | Z32: =W32/Y32 | AE32: =AF31 | AF32: 7994 | AG32: =AF32-AE32
A33: =A32 | B33: NIGHT | C33: =D32 | D33: 190 | E33: =D33-C33 | N33: =O32 | O33: 1890 | P33: =O33-N33 | R33: =R32 | S33: NIGHT | T33: =U32 | U33: 801 | V33: =U33-T33 | AE33: =AF32 | AF33: 8113 | AG33: =AF33-AE33
A34: =A33+1 | B34: DAY | C34: =D33 | D34: 200 | E34: =D34-C34 | F34: 210 | G34: 193 | H34: =G34-G32 | I34: =F34/H34 | N34: =O33 | O34: 1955 | P34: =O34-N34 | R34: =R33+1 | S34: DAY | T34: =U33 | U34: 808 | V34: =U34-T34 | W34: 260 | X34: 804 | Y34: =X34-X32 | Z34: =W34/Y34 | AE34: =AF33 | AF34: 8171 | AG34: =AF34-AE34
A35: =A34 | B35: NIGHT | C35: =D34 | D35: 205 | E35: =D35-C35 | N35: =O34 | O35: 2010 | P35: =O35-N35 | R35: =R34 | S35: NIGHT | T35: =U34 | U35: 818 | V35: =U35-T35 | AE35: =AF34 | AF35: 8243 | AG35: =AF35-AE35
A36: =A35+1 | B36: DAY | C36: =D35 | D36: 216 | E36: =D36-C36 | F36: 130 | G36: 207 | H36: =G36-G34 | I36: =F36/H36 | N36: =O35 | O36: 2092 | P36: =O36-N36 | R36: =R35+1 | S36: DAY | T36: =U35 | U36: 826 | V36: =U36-T36 | W36: 150 | X36: 820 | Y36: =X36-X34 | Z36: =W36/Y36 | AE36: =AF35 | AF36: 8318 | AG36: =AF36-AE36
A37: =A36 | B37: NIGHT | C37: =D36 | D37: 222 | E37: =D37-C37 | N37: =O36 | O37: 2159 | P37: =O37-N37 | R37: =R36 | S37: NIGHT | T37: =U36 | U37: 835 | V37: =U37-T37 | AE37: =AF36 | AF37: 8427 | AG37: =AF37-AE37
A38: =A37+1 | B38: DAY | C38: =D37 | D38: 229 | E38: =D38-C38 | F38: 200 | G38: 225 | H38: =G38-G36 | I38: =F38/H38 | N38: =O37 | O38: 2243 | P38: =O38-N38 | R38: =R37+1 | S38: DAY | T38: =U37 | U38: 845 | V38: =U38-T38 | W38: 200 | X38: 839 | Y38: =X38-X36 | Z38: =W38/Y38 | AE38: =AF37 | AF38: 8559 | AG38: =AF38-AE38
A39: =A38 | B39: NIGHT | C39: =D38 | D39: 236 | E39: =D39-C39 | N39: =O38 | O39: 2327 | P39: =O39-N39 | R39: =R38 | S39: NIGHT | T39: =U38 | U39: 852 | V39: =U39-T39 | AE39: =AF38 | AF39: 8609 | AG39: =AF39-AE39
A40: =A39+1 | B40: DAY | C40: =D39 | D40: 243 | E40: =D40-C40 | F40: 210 | G40: 239 | H40: =G40-G38 | I40: =F40/H40 | N40: =O39 | O40: 2423 | P40: =O40-N40 | R40: =R39+1 | S40: DAY | T40: =U39 | U40: 858 | V40: =U40-T40 | W40: 150 | X40: 854 | Y40: =X40-X38 | Z40: =W40/Y40 | AE40: =AF39 | AF40: 8667 | AG40: =AF40-AE40
A41: =A40 | B41: NIGHT | C41: =D40 | D41: 249 | E41: =D41-C41 | N41: =O40 | O41: 2478 | P41: =O41-N41 | R41: =R40 | S41: NIGHT | T41: =U40 | U41: 866 | V41: =U41-T41 | AE41: =AF40 | AF41: 8718 | AG41: =AF41-AE41
A42: =A41+1 | B42: DAY | C42: =D41 | D42: 258 | E42: =D42-C42 | F42: 100 | G42: 249 | H42: =G42-G40 | I42: =F42/H42 | N42: =O41 | O42: 2660 | P42: =O42-N42 | R42: =R41+1 | S42: DAY | T42: =U41 | U42: 875 | V42: =U42-T42 | W42: 80 | X42: 867 | Y42: =X42-X40 | Z42: =W42/Y42 | AE42: =AF41 | AF42: 8879 | AG42: =AF42-AE42
A43: =A42 | B43: NIGHT | C43: =D42 | D43: 269 | E43: =D43-C43 | N43: =O42 | O43: 2779 | P43: =O43-N43 | R43: =R42 | S43: NIGHT | T43: =U42 | U43: 883 | V43: =U43-T43 | AE43: =AF42 | AF43: 8965 | AG43: =AF43-AE43
A44: =A43+1 | B44: DAY | C44: =D43 | D44: 279 | E44: =D44-C44 | F44: 250 | G44: 272 | H44: =G44-G42 | I44: =F44/H44 | N44: =O43 | O44: 2886 | P44: =O44-N44 | R44: =R43+1 | S44: DAY | T44: =U43 | U44: 893 | V44: =U44-T44 | W44: 230 | X44: 886 | Y44: =X44-X42 | Z44: =W44/Y44 | AE44: =AF43 | AF44: 9068 | AG44: =AF44-AE44
A45: =A44 | B45: NIGHT | C45: =D44 | D45: 287 | E45: =D45-C45 | N45: =O44 | O45: 3020 | P45: =O45-N45 | R45: =R44 | S45: NIGHT | T45: =U44 | U45: 899 | V45: =U45-T45 | AE45: =AF44 | AF45: 9133 | AG45: =AF45-AE45
A46: =A45+1 | B46: DAY | C46: =D45 | D46: 298 | E46: =D46-C46 | F46: 210 | G46: 291 | H46: =G46-G44 | I46: =F46/H46 | N46: =O45 | O46: 3140 | P46: =O46-N46 | R46: =R45+1 | S46: DAY | T46: =U45 | U46: 911 | V46: =U46-T46 | W46: 210 | X46: 904 | Y46: =X46-X44 | Z46: =W46/Y46 | AE46: =AF45 | AF46: 9317 | AG46: =AF46-AE46
A47: =A46 | B47: NIGHT | C47: =D46 | D47: 303 | E47: =D47-C47 | N47: =O46 | O47: 3235 | P47: =O47-N47 | R47: =R46 | S47: NIGHT | T47: =U46 | U47: 918 | V47: =U47-T47 | AE47: =AF46 | AF47: 9407 | AG47: =AF47-AE47
A48: =A47+1 | B48: DAY | C48: =D47 | D48: 312 | E48: =D48-C48 | F48: 180 | G48: 305 | H48: =G48-G46 | I48: =F48/H48 | N48: =O47 | O48: 3359 | P48: =O48-N48 | R48: =R47+1 | S48: DAY | T48: =U47 | U48: 929 | V48: =U48-T48 | W48: 180 | X48: 924 | Y48: =X48-X46 | Z48: =W48/Y48 | AE48: =AF47 | AF48: 9509 | AG48: =AF48-AE48
A49: =A48 | B49: NIGHT | C49: =D48 | D49: 322 | E49: =D49-C49 | N49: =O48 | O49: 3402 | P49: =O49-N49 | R49: =R48 | S49: NIGHT | T49: =U48 | U49: 934 | V49: =U49-T49 | AE49: =AF48 | AF49: 9566 | AG49: =AF49-AE49
A50: =A49+1 | B50: DAY | C50: =D49 | D50: 332 | E50: =D50-C50 | F50: 150 | G50: 327 | H50: =G50-G48 | I50: =F50/H50 | N50: =O49 | O50: 3502 | P50: =O50-N50 | R50: =R49+1 | S50: DAY | T50: =U49 | U50: 945 | V50: =U50-T50 | W50: 200 | X50: 939 | Y50: =X50-X48 | Z50: =W50/Y50 | AE50: =AF49 | AF50: 9705 | AG50: =AF50-AE50
A51: =A50 | B51: NIGHT | C51: =D50 | D51: 341 | E51: =D51-C51 | N51: =O50 | O51: 3587 | P51: =O51-N51 | R51: =R50 | S51: NIGHT | T51: =U50 | U51: 956 | V51: =U51-T51 | AE51: =AF50 | AF51: 9844 | AG51: =AF51-AE51
A52: =A51+1 | B52: DAY | C52: =D51 | D52: 352 | E52: =D52-C52 | F52: 190 | G52: 352 | H52: =G52-G50 | I52: =F52/H52 | N52: =O51 | O52: 3852 | P52: =O52-N52 | R52: =R51+1 | S52: DAY | T52: =U51 | U52: 967 | V52: =U52-T52 | W52: 210 | X52: 959 | Y52: =X52-X50 | Z52: =W52/Y52 | AE52: =AF51 | AF52: 10065 | AG52: =AF52-AE52
A53: =A52 | B53: NIGHT | C53: =D52 | D53: 359 | E53: =D53-C53 | N53: =O52 | O53: 3951 | P53: =O53-N53 | R53: =R52 | S53: NIGHT | T53: =U52 | U53: 973 | V53: =U53-T53 | AE53: =AF52 | AF53: 10161 | AG53: =AF53-AE53
A54: =A53+1 | B54: DAY | C54: =D53 | D54: 365 | E54: =D54-C54 | F54: 250 | G54: 365 | H54: =G54-G52 | I54: =F54/H54 | N54: =O53 | O54: 4035 | P54: =O54-N54 | R54: =R53+1 | S54: DAY | T54: =U53 | U54: 982 | V54: =U54-T54 | W54: 270 | X54: 980 | Y54: =X54-X52 | Z54: =W54/Y54 | AE54: =AF53 | AF54: 10361 | AG54: =AF54-AE54
A55: =A54 | B55: NIGHT | C55: =D54 | D55: 371 | E55: =D55-C55 | N55: =O54 | O55: 4119 | P55: =O55-N55 | R55: =R54 | S55: NIGHT | T55: =U54 | U55: 992 | V55: =U55-T55 | AE55: =AF54 | AF55: 10441 | AG55: =AF55-AE55
A56: =A55+1 | B56: DAY | C56: =D55 | D56: 381 | E56: =D56-C56 | F56: 100 | G56: 376 | H56: =G56-G52 | I56: =F56/H56 | N56: =O55 | O56: 4191 | P56: =O56-N56 | R56: =R55+1 | S56: DAY | T56: =U55 | U56: 1000 | V56: =U56-T56 | W56: 100 | X56: 996 | Y56: =X56-X54 | Z56: =W56/Y56 | AE56: =AF55 | AF56: 10500 | AG56: =AF56-AE56
A57: =A56 | B57: NIGHT | C57: =D56 | D57: 388 | E57: =D57-C57 | N57: =O56 | O57: 4281 | P57: =O57-N57 | R57: =R56 | S57: NIGHT | T57: =U56 | U57: 1005 | V57: =U57-T57 | AE57: =AF56 | AF57: 10533 | AG57: =AF57-AE57
A58: =A57+1 | B58: DAY | C58: =D57 | D58: 395 | E58: =D58-C58 | F58: 250 | G58: 391 | H58: =G58-G56 | I58: =F58/H58 | N58: =O57 | O58: 4369 | P58: =O58-N58 | R58: =R57+1 | S58: DAY | T58: =U57 | U58: 1015 | V58: =U58-T58 | W58: 220 | X58: 1011 | Y58: =X58-X56 | Z58: =W58/Y58 | AE58: =AF57 | AF58: 10655 | AG58: =AF58-AE58
A59: =A58 | B59: NIGHT | C59: =D58 | D59: 405 | E59: =D59-C59 | N59: =O58 | O59: 4464 | P59: =O59-N59 | R59: =R58 | S59: NIGHT | T59: =U58 | U59: 1027 | V59: =U59-T59 | AE59: =AF58 | AF59: 10788 | AG59: =AF59-AE59
A60: =A59+1 | B60: DAY | C60: =D59 | D60: 414 | E60: =D60-C60 | F60: 200 | G60: 410 | H60: =G60-G58 | I60: =F60/H60 | N60: =O59 | O60: 4604 | P60: =O60-N60 | R60: =R59+1 | S60: DAY | T60: =U59 | U60: 1036 | V60: =U60-T60 | W60: 200 | X60: 1032 | Y60: =X60-X58 | Z60: =W60/Y60 | AE60: =AF59 | AF60: 10906 | AG60: =AF60-AE60
A61: =A60 | B61: NIGHT | C61: =D60 | D61: 422 | E61: =D61-C61 | N61: =O60 | O61: 4663 | P61: =O61-N61 | R61: =R60 | S61: NIGHT | T61: =U60 | U61: 1046 | V61: =U61-T61 | AE61: =AF60 | AF61: 10973 | AG61: =AF61-AE61
A62: =A61+1 | B62: DAY | C62: =D61 | D62: 430 | E62: =D62-C62 | F62: 130 | G62: 426 | H62: =G62-G60 | I62: =F62/H62 | N62: =O61 | O62: 4820 | P62: =O62-N62 | R62: =R61+1 | S62: DAY | T62: =U61 | U62: 1054 | V62: =U62-T62 | W62: 140 | X62: 1048 | Y62: =X62-X60 | Z62: =W62/Y62 | AE62: =AF61 | AF62: 11068 | AG62: =AF62-AE62
A63: =A62 | B63: NIGHT | C63: =D62 | D63: 436 | E63: =D63-C63 | N63: =O62 | O63: 4918 | P63: =O63-N63 | R63: =R62 | S63: NIGHT | T63: =U62 | U63: 1063 | V63: =U63-T63 | AE63: =AF62 | AF63: 11130 | AG63: =AF63-AE63
A64: TOTAL Running Hours: 493 | E64: =SUBTOTAL(9,E4:E63) | F64: =SUBTOTAL(9,F4:F63) | I64: =F64/E64 | J64: NO BREAKDOWN | P64: =SUBTOTAL(9,P4:P63) | R64: TOTAL Running Hours: 512 | V64: =SUBTOTAL(9,V4:V63) | W64: =SUBTOTAL(9,W4:W63) | Z64: =W64/V64 | AA64: NO BREAKDOWN | AG64: =SUBTOTAL(9,AG4:AG63)

Sheet JULY-26
A1: NEW MACHINE NO - SANY-8 | J1: BREAKDOWN TIME/Cooling | R1: NEW MACHINE NO - SANY-9 | AA1: BREAKDOWN TIME/Cooling
A2: DATE | B2: SHIFT | C2: SHIFT START - HMR | D2: SHIFT END - HMR | E2: HOURS | F2: DIESEL | G2: HMR | H2: HOURS | I2: AVERAGE | J2: START TIME | K2: END TIME | L2: TOTAL HRS | M2: Remarks | N2: Container Start Count | O2: Container End Count | P2: Total | R2: DATE | S2: SHIFT | T2: SHIFT START - HMR | U2: SHIFT END - HMR | V2: HOURS | W2: DIESEL | X2: HMR | Y2: HOURS | Z2: AVERAGE | AA2: START TIME | AB2: END TIME | AC2: TOTAL HRS | AD2: Remarks | AE2: Container Start Count | AF2: Container End Count | AG2: Total
G3: 410 | X3: 1048
A4: 46204 | B4: DAY | C4: 436 | D4: 444 | E4: =D4-C4 | F4: 220 | G4: 440 | H4: =G4-G3 | I4: =F4/H4 | N4: 4918 | O4: 5064 | P4: =O4-N4 | R4: 46204 | S4: DAY | T4: 1063 | U4: 1071 | V4: =U4-T4 | W4: 200 | X4: 1068 | Y4: =X4-X3 | Z4: =W4/Y4 | AE4: 11130 | AF4: 11216 | AG4: =AF4-AE4
A5: =A4 | B5: NIGHT | C5: =D4 | D5: 454 | E5: =D5-C5 | N5: =O4 | O5: 5166 | P5: =O5-N5 | R5: =R4 | S5: NIGHT | T5: =U4 | U5: 1078 | V5: =U5-T5 | AE5: =AF4 | AF5: 11313 | AG5: =AF5-AE5
A6: =A5+1 | B6: DAY | C6: =D5 | D6: 462 | E6: =D6-C6 | F6: 140 | G6: 456 | H6: =G6-G4 | I6: =F6/H6 | N6: =O5 | O6: 5343 | P6: =O6-N6 | R6: =R5+1 | S6: DAY | T6: =U5 | U6: 1087 | V6: =U6-T6 | W6: 160 | X6: 1080 | Y6: =X6-X4 | Z6: =W6/Y6 | AE6: =AF5 | AF6: 11465 | AG6: =AF6-AE6
A7: =A6 | B7: NIGHT | C7: =D6 | D7: 471 | E7: =D7-C7 | N7: =O6 | O7: 5550 | P7: =O7-N7 | R7: =R6 | S7: NIGHT | T7: =U6 | U7: 1098 | V7: =U7-T7 | AE7: =AF6 | AF7: 11613 | AG7: =AF7-AE7
A8: =A7+1 | B8: DAY | C8: =D7 | D8: 481 | E8: =D8-C8 | F8: 300 | G8: 474 | H8: =G8-G6 | I8: =F8/H8 | L8: 0.16666667 | M8: PM Service 04:00 hrs | N8: =O7 | O8: 5677 | P8: =O8-N8 | R8: =R7+1 | S8: DAY | T8: =U7 | U8: 1108 | V8: =U8-T8 | W8: 200 | X8: 1102 | Y8: =X8-X6 | Z8: =W8/Y8 | AE8: =AF7 | AF8: 11719 | AG8: =AF8-AE8
A9: =A8 | B9: NIGHT | C9: =D8 | D9: 489 | E9: =D9-C9 | N9: =O8 | O9: 5818 | P9: =O9-N9 | R9: =R8 | S9: NIGHT | T9: =U8 | U9: 1117 | V9: =U9-T9 | AE9: =AF8 | AF9: 11843 | AG9: =AF9-AE9
A10: =A9+1 | B10: DAY | C10: =D9 | D10: 499 | E10: =D10-C10 | F10: 200 | G10: 492 | H10: =G10-G8 | I10: =F10/H10 | N10: =O9 | O10: 5998 | P10: =O10-N10 | R10: =R9+1 | S10: DAY | T10: =U9 | U10: 1127 | V10: =U10-T10 | W10: 200 | X10: 1120 | Y10: =X10-X8 | Z10: =W10/Y10 | AE10: =AF9 | AF10: 11942 | AG10: =AF10-AE10
A11: =A10 | B11: NIGHT | C11: =D10 | D11: 507 | E11: =D11-C11 | N11: =O10 | O11: 6079 | P11: =O11-N11 | R11: =R10 | S11: NIGHT | T11: =U10 | U11: 1133 | V11: =U11-T11 | AE11: =AF10 | AF11: 12001 | AG11: =AF11-AE11
A12: =A11+1 | B12: DAY | C12: =D11 | D12: 516 | E12: =D12-C12 | F12: 170 | G12: 509 | H12: =G12-G10 | I12: =F12/H12 | N12: =O11 | O12: 6170 | P12: =O12-N12 | R12: =R11+1 | S12: DAY | T12: =U11 | U12: 1142 | V12: =U12-T12 | W12: 110 | X12: 1135 | Y12: =X12-X10 | Z12: =W12/Y12 | AE12: =AF11 | AF12: 12066 | AG12: =AF12-AE12
A13: =A12 | B13: NIGHT | C13: =D12 | D13: 519 | E13: =D13-C13 | N13: =O12 | O13: 6196 | P13: =O13-N13 | R13: =R12 | S13: NIGHT | T13: =U12 | U13: 1148 | V13: =U13-T13 | AE13: =AF12 | AF13: 12120 | AG13: =AF13-AE13
A14: =A13+1 | B14: DAY | C14: =D13 | D14: 522 | E14: =D14-C14 | N14: =O13 | O14: 6208 | P14: =O14-N14 | R14: =R13+1 | S14: DAY | T14: =U13 | U14: 1154 | V14: =U14-T14 | W14: 150 | X14: 1148 | Y14: =X14-X12 | Z14: =W14/Y14 | AE14: =AF13 | AF14: 12187 | AG14: =AF14-AE14
A15: =A14 | B15: NIGHT | C15: =D14 | D15: 528 | E15: =D15-C15 | N15: =O14 | O15: 6271 | P15: =O15-N15 | R15: =R14 | S15: NIGHT | T15: =U14 | U15: 1160 | V15: =U15-T15 | AE15: =AF14 | AF15: 12265 | AG15: =AF15-AE15
A16: =A15+1 | B16: DAY | C16: =D15 | D16: 538 | E16: =D16-C16 | F16: 250 | G16: 532 | H16: =G16-G12 | I16: =F16/H16 | N16: =O15 | O16: 6393 | P16: =O16-N16 | R16: =R15+1 | S16: DAY | T16: =U15 | U16: 1169 | V16: =U16-T16 | W16: 180 | X16: 1164 | Y16: =X16-X14 | Z16: =W16/Y16 | AE16: =AF15 | AF16: 12395 | AG16: =AF16-AE16
A17: =A16 | B17: NIGHT | C17: =D16 | D17: 541 | E17: =D17-C17 | N17: =O16 | O17: 6437 | P17: =O17-N17 | R17: =R16 | S17: NIGHT | T17: =U16 | U17: 1174 | V17: =U17-T17 | AE17: =AF16 | AF17: 12453 | AG17: =AF17-AE17
A18: =A17+1 | B18: DAY | C18: =D17 | D18: 550 | E18: =D18-C18 | F18: 110 | G18: 543 | H18: =G18-G16 | I18: =F18/H18 | N18: =O17 | O18: 6597 | P18: =O18-N18 | R18: =R17+1 | S18: DAY | T18: =U17 | U18: 1184 | V18: =U18-T18 | W18: 150 | X18: 1178 | Y18: =X18-X16 | Z18: =W18/Y18 | AE18: =AF17 | AF18: 12607 | AG18: =AF18-AE18
A19: =A18 | B19: NIGHT | C19: =D18 | D19: 557 | E19: =D19-C19 | N19: =O18 | O19: 6739 | P19: =O19-N19 | R19: =R18 | S19: NIGHT | T19: =U18 | U19: 1193 | V19: =U19-T19 | AE19: =AF18 | AF19: 12727 | AG19: =AF19-AE19
A20: =A19+1 | B20: DAY | C20: =D19 | D20: 564 | E20: =D20-C20 | F20: 290 | G20: 560 | H20: =G20-G18 | I20: =F20/H20 | N20: =O19 | O20: 6868 | P20: =O20-N20 | R20: =R19+1 | S20: DAY | T20: =U19 | U20: 1202 | V20: =U20-T20 | W20: 250 | X20: 1196 | Y20: =X20-X18 | Z20: =W20/Y20 | AE20: =AF19 | AF20: 12855 | AG20: =AF20-AE20
A21: =A20 | B21: NIGHT | C21: =D20 | D21: 570 | E21: =D21-C21 | N21: =O20 | O21: 6927 | P21: =O21-N21 | R21: =R20 | S21: NIGHT | T21: =U20 | U21: 1210 | V21: =U21-T21 | AE21: =AF20 | AF21: 12932 | AG21: =AF21-AE21
A22: =A21+1 | B22: DAY | C22: =D21 | D22: 580 | E22: =D22-C22 | F22: 100 | G22: 573 | H22: =G22-G20 | I22: =F22/H22 | N22: =O21 | O22: 7044 | P22: =O22-N22 | R22: =R21+1 | S22: DAY | T22: =U21 | U22: 1218 | V22: =U22-T22 | W22: 70 | X22: 1211 | Y22: =X22-X20 | Z22: =W22/Y22 | AE22: =AF21 | AF22: 13049 | AG22: =AF22-AE22
A23: =A22 | B23: NIGHT | C23: =D22 | D23: 586 | E23: =D23-C23 | N23: =O22 | O23: 7109 | P23: =O23-N23 | R23: =R22 | S23: NIGHT | T23: =U22 | U23: 1224 | V23: =U23-T23 | AE23: =AF22 | AF23: 13150 | AG23: =AF23-AE23
A24: =A23+1 | B24: DAY | C24: =D23 | D24: 596 | E24: =D24-C24 | F24: 230 | G24: 587 | H24: =G24-G22 | I24: =F24/H24 | N24: =O23 | O24: 7309 | P24: =O24-N24 | R24: =R23+1 | S24: DAY | T24: =U23 | U24: 1234 | V24: =U24-T24 | W24: 230 | X24: 1225 | Y24: =X24-X22 | Z24: =W24/Y24 | AE24: =AF23 | AF24: 13301 | AG24: =AF24-AE24
A25: =A24 | B25: NIGHT | C25: =D24 | D25: 603 | E25: =D25-C25 | N25: =O24 | O25: 7423 | P25: =O25-N25 | R25: =R24 | S25: NIGHT | T25: =U24 | U25: 1239 | V25: =U25-T25 | AE25: =AF24 | AF25: 13356 | AG25: =AF25-AE25
A26: =A25+1 | B26: DAY | C26: =D25 | D26: 613 | E26: =D26-C26 | F26: 180 | G26: 605 | H26: =G26-G24 | I26: =F26/H26 | N26: =O25 | O26: 7586 | P26: =O26-N26 | R26: =R25+1 | S26: DAY | T26: =U25 | U26: 1250 | V26: =U26-T26 | W26: 150 | X26: 1241 | Y26: =X26-X24 | Z26: =W26/Y26 | AE26: =AF25 | AF26: 13506 | AG26: =AF26-AE26
A27: =A26 | B27: NIGHT | C27: =D26 | D27: 622 | E27: =D27-C27 | N27: =O26 | O27: 7727 | P27: =O27-N27 | R27: =R26 | S27: NIGHT | T27: =U26 | U27: 1260 | V27: =U27-T27 | AE27: =AF26 | AF27: 13666 | AG27: =AF27-AE27
A28: =A27+1 | B28: DAY | C28: =D27 | D28: 628 | E28: =D28-C28 | F28: 330 | G28: 625 | H28: =G28-G26 | I28: =F28/H28 | N28: =O27 | O28: 7845 | P28: =O28-N28 | R28: =R27+1 | S28: DAY | T28: =U27 | U28: 1268 | V28: =U28-T28 | W28: 270 | X28: 1264 | Y28: =X28-X26 | Z28: =W28/Y28 | AE28: =AF27 | AF28: 13752 | AG28: =AF28-AE28
A29: =A28 | B29: NIGHT | C29: =D28 | D29: 637 | E29: =D29-C29 | N29: =O28 | O29: 7939 | P29: =O29-N29 | R29: =R28 | S29: NIGHT | T29: =U28 | U29: 1276 | V29: =U29-T29 | AE29: =AF28 | AF29: 13860 | AG29: =AF29-AE29
A30: =A29+1 | B30: DAY | C30: =D29 | D30: 646 | E30: =D30-C30 | F30: 220 | G30: 642 | H30: =G30-G28 | I30: =F30/H30 | N30: =O29 | O30: 8183 | P30: =O30-N30 | R30: =R29+1 | S30: DAY | T30: =U29 | U30: 1286 | V30: =U30-T30 | W30: 200 | X30: 1281 | Y30: =X30-X28 | Z30: =W30/Y30 | AE30: =AF29 | AF30: 14055 | AG30: =AF30-AE30
A31: =A30 | B31: NIGHT | C31: =D30 | D31: 654 | E31: =D31-C31 | N31: =O30 | O31: 8277 | P31: =O31-N31 | R31: =R30 | S31: NIGHT | T31: =U30 | U31: 1294 | V31: =U31-T31 | AE31: =AF30 | AF31: 14182 | AG31: =AF31-AE31
A32: =A31+1 | B32: DAY | C32: =D31 | D32: 662 | E32: =D32-C32 | F32: 160 | G32: 657 | H32: =G32-G30 | I32: =F32/H32 | N32: =O31 | O32: 8352 | P32: =O32-N32 | R32: =R31+1 | S32: DAY | T32: =U31 | U32: 1301 | V32: =U32-T32 | W32: 200 | X32: 1297 | Y32: =X32-X30 | Z32: =W32/Y32 | AE32: =AF31 | AF32: 14279 | AG32: =AF32-AE32
A33: =A32 | B33: NIGHT | C33: =D32 | D33: 671 | E33: =D33-C33 | N33: =O32 | O33: 8443 | P33: =O33-N33 | R33: =R32 | S33: NIGHT | T33: =U32 | U33: 1312 | V33: =U33-T33 | AE33: =AF32 | AF33: 14408 | AG33: =AF33-AE33
A34: =A33+1 | B34: DAY | C34: =D33 | D34: 679 | E34: =D34-C34 | F34: 200 | G34: 678 | H34: =G34-G32 | I34: =F34/H34 | N34: =O33 | O34: 8550 | P34: =O34-N34 | R34: =R33+1 | S34: DAY | T34: =U33 | U34: 1320 | V34: =U34-T34 | W34: 200 | X34: 1318 | Y34: =X34-X32 | Z34: =W34/Y34 | AE34: =AF33 | AF34: 14513 | AG34: =AF34-AE34
A35: =A34 | B35: NIGHT | C35: =D34 | D35: 686 | E35: =D35-C35 | N35: =O34 | O35: 8647 | P35: =O35-N35 | R35: =R34 | S35: NIGHT | T35: =U34 | U35: 1328 | V35: =U35-T35 | AE35: =AF34 | AF35: 14595 | AG35: =AF35-AE35
A36: =A35+1 | B36: DAY | C36: =D35 | D36: 695 | E36: =D36-C36 | F36: 190 | G36: 689 | H36: =G36-G34 | I36: =F36/H36 | N36: =O35 | O36: 8771 | P36: =O36-N36 | R36: =R35+1 | S36: DAY | T36: =U35 | U36: 1337 | V36: =U36-T36 | W36: 200 | X36: 1332 | Y36: =X36-X34 | Z36: =W36/Y36 | AE36: =AF35 | AF36: 14719 | AG36: =AF36-AE36
A37: =A36 | B37: NIGHT | C37: =D36 | D37: 704 | E37: =D37-C37 | N37: =O36 | O37: 8919 | P37: =O37-N37 | R37: =R36 | S37: NIGHT | T37: =U36 | U37: 1346 | V37: =U37-T37 | AE37: =AF36 | AF37: 14838 | AG37: =AF37-AE37
A38: =A37+1 | B38: DAY | C38: =D37 | D38: 714 | E38: =D38-C38 | F38: 200 | G38: 707 | H38: =G38-G36 | I38: =F38/H38 | N38: =O37 | O38: 9098 | P38: =O38-N38 | R38: =R37+1 | S38: DAY | T38: =U37 | U38: 1355 | V38: =U38-T38 | W38: 210 | X38: 1349 | Y38: =X38-X36 | Z38: =W38/Y38 | AE38: =AF37 | AF38: 14955 | AG38: =AF38-AE38
A39: =A38 | B39: NIGHT | C39: =D38 | D39: 721 | E39: =D39-C39 | N39: =O38 | O39: 9188 | P39: =O39-N39 | R39: =R38 | S39: NIGHT | T39: =U38 | U39: 1361 | V39: =U39-T39 | AE39: =AF38 | AF39: 15034 | AG39: =AF39-AE39
A40: =A39+1 | B40: DAY | C40: =D39 | D40: 729 | E40: =D40-C40 | F40: 168 | G40: 722 | H40: =G40-G38 | I40: =F40/H40 | N40: =O39 | O40: 9309 | P40: =O40-N40 | R40: =R39+1 | S40: DAY | T40: =U39 | U40: 1371 | V40: =U40-T40 | W40: 150 | X40: 1362 | Y40: =X40-X38 | Z40: =W40/Y40 | AE40: =AF39 | AF40: 15208 | AG40: =AF40-AE40
A41: =A40 | B41: NIGHT | C41: =D40 | D41: 737 | E41: =D41-C41 | N41: =O40 | O41: 9405 | P41: =O41-N41 | R41: =R40 | S41: NIGHT | T41: =U40 | U41: 1380 | V41: =U41-T41 | AE41: =AF40 | AF41: 15303 | AG41: =AF41-AE41
A42: =A41+1 | B42: DAY | C42: =D41 | D42: 746 | E42: =D42-C42 | F42: 220 | G42: 739 | H42: =G42-G40 | I42: =F42/H42 | N42: =O41 | O42: 9584 | P42: =O42-N42 | R42: =R41+1 | S42: DAY | T42: =U41 | U42: 1389 | V42: =U42-T42 | W42: 260 | X42: 1382 | Y42: =X42-X40 | Z42: =W42/Y42 | AE42: =AF41 | AF42: 15348 | AG42: =AF42-AE42
A43: =A42 | B43: NIGHT | C43: =D42 | D43: 752 | E43: =D43-C43 | N43: =O42 | O43: 9634 | P43: =O43-N43 | R43: =R42 | S43: NIGHT | T43: =U42 | U43: 1395 | V43: =U43-T43 | AE43: =AF42 | AF43: 15501 | AG43: =AF43-AE43
A44: =A43+1 | B44: DAY | C44: =D43 | D44: 758 | E44: =D44-C44 | F44: 200 | G44: 753 | H44: =G44-G42 | I44: =F44/H44 | N44: =O43 | O44: 9736 | P44: =O44-N44 | R44: =R43+1 | S44: DAY | T44: =U43 | U44: 1401 | V44: =U44-T44 | W44: 180 | X44: 1396 | Y44: =X44-X42 | Z44: =W44/Y44 | AE44: =AF43 | AF44: 15613 | AG44: =AF44-AE44
A45: =A44 | B45: NIGHT | C45: =D44 | D45: 762 | E45: =D45-C45 | N45: =O44 | O45: 9768 | P45: =O45-N45 | R45: =R44 | S45: NIGHT | T45: =U44 | U45: 1409 | V45: =U45-T45 | AE45: =AF44 | AF45: 15690 | AG45: =AF45-AE45
A46: =A45+1 | B46: DAY | C46: =D45 | D46: 766 | E46: =D46-C46 | F46: 130 | G46: 763 | H46: =G46-G44 | I46: =F46/H46 | N46: =O45 | O46: 9828 | P46: =O46-N46 | R46: =R45+1 | S46: DAY | T46: =U45 | U46: 1414 | V46: =U46-T46 | W46: 101 | X46: 1409 | Y46: =X46-X44 | Z46: =W46/Y46 | AE46: =AF45 | AF46: 15768 | AG46: =AF46-AE46
A47: =A46 | B47: NIGHT | C47: =D46 | D47: 770 | E47: =D47-C47 | N47: =O46 | O47: 9853 | P47: =O47-N47 | R47: =R46 | S47: NIGHT | T47: =U46 | U47: 1417 | V47: =U47-T47 | AE47: =AF46 | AF47: 15818 | AG47: =AF47-AE47
A48: =A47+1 | B48: DAY | C48: =D47 | D48: 776 | E48: =D48-C48 | F48: 150 | G48: 772 | H48: =G48-G46 | I48: =F48/H48 | N48: =O47 | O48: 9897 | P48: =O48-N48 | R48: =R47+1 | S48: DAY | T48: =U47 | U48: 1421 | V48: =U48-T48 | W48: 180 | X48: 1419 | Y48: =X48-X46 | Z48: =W48/Y48 | AE48: =AF47 | AF48: 15839 | AG48: =AF48-AE48
A49: =A48 | B49: NIGHT | C49: =D48 | D49: 783 | E49: =D49-C49 | N49: =O48 | O49: 9989 | P49: =O49-N49 | R49: =R48 | S49: NIGHT | T49: =U48 | U49: 1428 | V49: =U49-T49 | AA49: 0.10416667 | AB49: 0.25 | AC49: =AB49-AA49 | AD49: Oil service | AE49: =AF48 | AF49: 15898 | AG49: =AF49-AE49
A50: =A49+1 | B50: DAY | C50: =D49 | D50: 793 | E50: =D50-C50 | F50: 100 | G50: 783 | H50: =G50-G48 | I50: =F50/H50 | N50: =O49 | O50: 10179 | P50: =O50-N50 | R50: =R49+1 | S50: DAY | T50: =U49 | U50: 1439 | V50: =U50-T50 | W50: 100 | X50: 1429 | Y50: =X50-X48 | Z50: =W50/Y50 | AE50: =AF49 | AF50: 16068 | AG50: =AF50-AE50
A51: =A50 | B51: NIGHT | C51: =D50 | D51: 801 | E51: =D51-C51 | N51: =O50 | O51: 10295 | P51: =O51-N51 | R51: =R50 | S51: NIGHT | T51: =U50 | U51: 1448 | V51: =U51-T51 | AE51: =AF50 | AF51: 16206 | AG51: =AF51-AE51
A52: =A51+1 | B52: DAY | C52: =D51 | D52: 808 | E52: =D52-C52 | F52: 290 | G52: 803 | H52: =G52-G50 | I52: =F52/H52 | N52: =O51 | O52: 10441 | P52: =O52-N52 | R52: =R51+1 | S52: DAY | T52: =U51 | U52: 1458 | V52: =U52-T52 | W52: 300 | X52: 1453 | Y52: =X52-X50 | Z52: =W52/Y52 | AE52: =AF51 | AF52: 16351 | AG52: =AF52-AE52
A53: =A52 | B53: NIGHT | C53: =D52 | D53: 819 | E53: =D53-C53 | N53: =O52 | O53: 10606 | P53: =O53-N53 | R53: =R52 | S53: NIGHT | T53: =U52 | U53: 1466 | V53: =U53-T53 | AE53: =AF52 | AF53: 16515 | AG53: =AF53-AE53
A54: =A53+1 | B54: DAY | C54: =D53 | D54: 829 | E54: =D54-C54 | F54: 220 | G54: 820 | H54: =G54-G52 | I54: =F54/H54 | N54: =O53 | O54: 10788 | P54: =O54-N54 | R54: =R53+1 | S54: DAY | T54: =U53 | U54: 1477 | V54: =U54-T54 | W54: 180 | X54: 1468 | Y54: =X54-X52 | Z54: =W54/Y54 | AE54: =AF53 | AF54: 16637 | AG54: =AF54-AE54
A55: =A54 | B55: NIGHT | C55: =D54 | D55: 840 | E55: =D55-C55 | N55: =O54 | O55: 11003 | P55: =O55-N55 | R55: =R54 | S55: NIGHT | T55: =U54 | U55: 1488 | V55: =U55-T55 | AE55: =AF54 | AF55: 16845 | AG55: =AF55-AE55
A56: =A55+1 | B56: DAY | C56: =D55 | D56: 848 | E56: =D56-C56 | F56: 330 | G56: 843 | H56: =G56-G54 | I56: =F56/H56 | N56: =O55 | O56: 11130 | P56: =O56-N56 | R56: =R55+1 | S56: DAY | T56: =U55 | U56: 1497 | V56: =U56-T56 | W56: 360 | X56: 1492 | Y56: =X56-X54 | Z56: =W56/Y56 | AE56: =AF55 | AF56: 16980 | AG56: =AF56-AE56
A57: =A56 | B57: NIGHT | C57: =D56 | D57: 855 | E57: =D57-C57 | N57: =O56 | O57: 11222 | P57: =O57-N57 | R57: =R56 | S57: NIGHT | T57: =U56 | U57: 1503 | V57: =U57-T57 | AE57: =AF56 | AF57: 17041 | AG57: =AF57-AE57
A58: =A57+1 | B58: DAY | C58: =D57 | D58: 863 | E58: =D58-C58 | F58: 201 | G58: 860 | H58: =G58-G56 | I58: =F58/H58 | N58: =O57 | O58: 11319 | P58: =O58-N58 | R58: =R57+1 | S58: DAY | T58: =U57 | U58: 1510 | V58: =U58-T58 | W58: 200 | X58: 1509 | Y58: =X58-X56 | Z58: =W58/Y58 | AE58: =AF57 | AF58: 17168 | AG58: =AF58-AE58
A59: =A58 | B59: NIGHT | C59: =D58 | D59: 869 | E59: =D59-C59 | N59: =O58 | O59: 11431 | P59: =O59-N59 | R59: =R58 | S59: NIGHT | T59: =U58 | U59: 1517 | V59: =U59-T59 | AE59: =AF58 | AF59: 17273 | AG59: =AF59-AE59
A60: =A59+1 | B60: DAY | C60: =D59 | D60: 880 | E60: =D60-C60 | F60: 240 | G60: 872 | H60: =G60-G58 | I60: =F60/H60 | N60: =O59 | O60: 11546 | P60: =O60-N60 | R60: =R59+1 | S60: DAY | T60: =U59 | U60: 1527 | V60: =U60-T60 | W60: 200 | X60: 1523 | Y60: =X60-X58 | Z60: =W60/Y60 | AE60: =AF59 | AF60: 17423 | AG60: =AF60-AE60
A61: =A60 | B61: NIGHT | C61: =D60 | D61: 887 | E61: =D61-C61 | N61: =O60 | O61: 11620 | P61: =O61-N61 | R61: =R60 | S61: NIGHT | T61: =U60 | U61: 1534 | V61: =U61-T61 | AE61: =AF60 | AF61: 17523 | AG61: =AF61-AE61
A62: =A61+1 | B62: DAY | C62: =D61 | D62: 897 | E62: =D62-C62 | F62: 250 | G62: 893 | H62: =G62-G60 | I62: =F62/H62 | N62: =O61 | O62: 11752 | P62: =O62-N62 | R62: =R61+1 | S62: DAY | T62: =U61 | U62: 1543 | V62: =U62-T62 | W62: 150 | X62: 1537 | Y62: =X62-X60 | Z62: =W62/Y62 | AE62: =AF61 | AF62: 17647 | AG62: =AF62-AE62
A63: =A62 | B63: NIGHT | C63: =D62 | D63: 904 | E63: =D63-C63 | N63: =O62 | O63: 11862 | P63: =O63-N63 | R63: =R62 | S63: NIGHT | T63: =U62 | U63: 1550 | V63: =U63-T63 | AE63: =AF62 | AF63: 17714 | AG63: =AF63-AE63
A64: =A63+1 | B64: DAY | C64: =D63 | D64: 912 | E64: =D64-C64 | F64: 170 | G64: 906 | H64: =G64-G62 | I64: =F64/H64 | N64: =O63 | O64: 11984 | P64: =O64-N64 | R64: =R63+1 | S64: DAY | T64: =U63 | U64: 1559 | V64: =U64-T64 | W64: 220 | X64: 1553 | Y64: =X64-X62 | Z64: =W64/Y64 | AE64: =AF63 | AF64: 17859 | AG64: =AF64-AE64
A65: =A64 | B65: NIGHT | C65: =D64 | D65: 922 | E65: =D65-C65 | N65: =O64 | O65: 12086 | P65: =O65-N65 | R65: =R64 | S65: NIGHT | T65: =U64 | U65: 1565 | V65: =U65-T65 | AE65: =AF64 | AF65: 17917 | AG65: =AF65-AE65
A66: TOTAL Running Hours: 486 | E66: =SUBTOTAL(9,E4:E65) | F66: =SUBTOTAL(9,F4:F65) | I66: =F66/E66 | J66: 04:00 HRS | P66: =SUBTOTAL(9,P4:P65) | R66: TOTAL Running Hours: 502 | V66: =SUBTOTAL(9,V4:V65) | W66: =SUBTOTAL(9,W4:W65) | Z66: =W66/V66 | AA66: 3:30 HRS | AG66: =SUBTOTAL(9,AG4:AG65)

Sheet Aug-26
A1: NEW MACHINE NO - SANY-8 | J1: BREAKDOWN TIME/Cooling | R1: NEW MACHINE NO - SANY-9 | AA1: BREAKDOWN TIME/Cooling
A2: DATE | B2: SHIFT | C2: SHIFT START - HMR | D2: SHIFT END - HMR | E2: HOURS | F2: DIESEL | G2: HMR | H2: HOURS | I2: AVERAGE | J2: START TIME | K2: END TIME | L2: TOTAL HRS | M2: Remarks | N2: Container Start Count | O2: Container End Count | P2: Total | R2: DATE | S2: SHIFT | T2: SHIFT START - HMR | U2: SHIFT END - HMR | V2: HOURS | W2: DIESEL | X2: HMR | Y2: HOURS | Z2: AVERAGE | AA2: START TIME | AB2: END TIME | AC2: TOTAL HRS | AD2: Remarks | AE2: Container Start Count | AF2: Container End Count | AG2: Total
G3: 906 | X3: 1553
A4: 46235 | B4: DAY | C4: 922 | D4: 930 | E4: =D4-C4 | F4: 270 | G4: 927 | H4: =G4-G3 | I4: =F4/H4 | N4: 12086 | O4: 12246 | P4: =O4-N4 | R4: 46235 | S4: DAY | T4: 1565 | U4: 1574 | V4: =U4-T4 | W4: 200 | X4: 1570 | Y4: =X4-X3 | Z4: =W4/Y4 | AE4: 17917 | AF4: 18065 | AG4: =AF4-AE4
A5: =A4 | B5: NIGHT | C5: =D4 | D5: 941 | E5: =D5-C5 | N5: =O4 | O5: 12376 | P5: =O5-N5 | R5: =R4 | S5: NIGHT | T5: =U4 | U5: 1584 | V5: =U5-T5 | AE5: =AF4 | AF5: 18208 | AG5: =AF5-AE5
A6: =A5+1 | B6: DAY | C6: =D5 | D6: 950 | E6: =D6-C6 | F6: 240 | G6: 946 | H6: =G6-G4 | I6: =F6/H6 | N6: =O5 | O6: 12504 | P6: =O6-N6 | R6: =R5+1 | S6: DAY | T6: =U5 | U6: 1594 | V6: =U6-T6 | W6: 230 | X6: 1588 | Y6: =X6-X4 | Z6: =W6/Y6 | AE6: =AF5 | AF6: 18374 | AG6: =AF6-AE6
A7: =A6 | B7: NIGHT | C7: =D6 | D7: 960 | E7: =D7-C7 | N7: =O6 | O7: 12652 | P7: =O7-N7 | R7: =R6 | S7: NIGHT | T7: =U6 | U7: 1602 | V7: =U7-T7 | AE7: =AF6 | AF7: 18508 | AG7: =AF7-AE7
A8: =A7+1 | B8: DAY | C8: =D7 | D8: 970 | E8: =D8-C8 | F8: 230 | G8: 963 | H8: =G8-G6 | I8: =F8/H8 | N8: =O7 | O8: 12822 | P8: =O8-N8 | R8: =R7+1 | S8: DAY | T8: =U7 | U8: 1613 | V8: =U8-T8 | W8: 250 | X8: 1606 | Y8: =X8-X6 | Z8: =W8/Y8 | AE8: =AF7 | AF8: 18745 | AG8: =AF8-AE8
A9: =A8 | B9: NIGHT | C9: =D8 | D9: 978 | E9: =D9-C9 | N9: =O8 | O9: 12903 | P9: =O9-N9 | R9: =R8 | S9: NIGHT | T9: =U8 | U9: 1621 | V9: =U9-T9 | AE9: =AF8 | AF9: 18844 | AG9: =AF9-AE9
A10: =A9+1 | B10: DAY | C10: =D9 | D10: 987 | E10: =D10-C10 | F10: 230 | G10: 981 | H10: =G10-G8 | I10: =F10/H10 | N10: =O9 | O10: 13029 | P10: =O10-N10 | R10: =R9+1 | S10: DAY | T10: =U9 | U10: 1630 | V10: =U10-T10 | W10: 250 | X10: 1623 | Y10: =X10-X8 | Z10: =W10/Y10 | AE10: =AF9 | AF10: 19010 | AG10: =AF10-AE10
A11: =A10 | B11: NIGHT | C11: =D10 | D11: 997 | E11: =D11-C11 | N11: =O10 | O11: 13125 | P11: =O11-N11 | R11: =R10 | S11: NIGHT | T11: =U10 | U11: 1637 | V11: =U11-T11 | AE11: =AF10 | AF11: 19102 | AG11: =AF11-AE11
A12: =A11+1 | B12: DAY | C12: =D11 | D12: 1006 | E12: =D12-C12 | F12: 270 | G12: 1000 | H12: =G12-G10 | I12: =F12/H12 | N12: =O11 | O12: 13276 | P12: =O12-N12 | R12: =R11+1 | S12: DAY | T12: =U11 | U12: 1646 | V12: =U12-T12 | W12: 250 | X12: 1640 | Y12: =X12-X10 | Z12: =W12/Y12 | AE12: =AF11 | AF12: 19231 | AG12: =AF12-AE12
A13: =A12 | B13: NIGHT | C13: =D12 | D13: 1011 | E13: =D13-C13 | N13: =O12 | O13: 13335 | P13: =O13-N13 | R13: =R12 | S13: NIGHT | T13: =U12 | U13: 1654 | V13: =U13-T13 | AE13: =AF12 | AF13: 19338 | AG13: =AF13-AE13
A14: =A13+1 | B14: DAY | C14: =D13 | D14: 1020 | E14: =D14-C14 | F14: 150 | G14: 1014 | H14: =G14-G12 | I14: =F14/H14 | N14: =O13 | O14: 13493 | P14: =O14-N14 | R14: =R13+1 | S14: DAY | T14: =U13 | U14: 1661 | V14: =U14-T14 | W14: 200 | X14: 1657 | Y14: =X14-X12 | Z14: =W14/Y14 | AE14: =AF13 | AF14: 19437 | AG14: =AF14-AE14
A15: =A14 | B15: NIGHT | C15: =D14 | D15: 1027 | E15: =D15-C15 | N15: =O14 | O15: 13602 | P15: =O15-N15 | R15: =R14 | S15: NIGHT | T15: =U14 | U15: 1671 | V15: =U15-T15 | AE15: =AF14 | AF15: 19567 | AG15: =AF15-AE15
A16: =A15+1 | B16: DAY | C16: =D15 | D16: 1037 | E16: =D16-C16 | F16: 250 | G16: 1031 | H16: =G16-G14 | I16: =F16/H16 | N16: =O15 | O16: 13723 | P16: =O16-N16 | R16: =R15+1 | S16: DAY | T16: =U15 | U16: 1676 | V16: =U16-T16 | W16: 200 | X16: 1673 | Y16: =X16-X14 | Z16: =W16/Y16 | AE16: =AF15 | AF16: 19625 | AG16: =AF16-AE16
A17: =A16 | B17: NIGHT | C17: =D16 | D17: 1044 | E17: =D17-C17 | N17: =O16 | O17: 13815 | P17: =O17-N17 | R17: =R16 | S17: NIGHT | T17: =U16 | U17: 1684 | V17: =U17-T17 | AE17: =AF16 | AF17: 19707 | AG17: =AF17-AE17
A18: =A17+1 | B18: DAY | C18: =D17 | D18: 1055 | E18: =D18-C18 | F18: 230 | G18: 1048 | H18: =G18-G16 | I18: =F18/H18 | N18: =O17 | O18: 13940 | P18: =O18-N18 | R18: =R17+1 | S18: DAY | T18: =U17 | U18: 1695 | V18: =U18-T18 | W18: 170 | X18: 1687 | Y18: =X18-X16 | Z18: =W18/Y18 | AE18: =AF17 | AF18: 19880 | AG18: =AF18-AE18
A19: =A18 | B19: NIGHT | C19: =D18 | D19: 1061 | E19: =D19-C19 | N19: =O18 | O19: 14042 | P19: =O19-N19 | R19: =R18 | S19: NIGHT | T19: =U18 | U19: 1703 | V19: =U19-T19 | AE19: =AF18 | AF19: 19976 | AG19: =AF19-AE19
A20: =A19+1 | B20: DAY | C20: =D19 | D20: 1072 | E20: =D20-C20 | F20: 200 | G20: 1064 | H20: =G20-G18 | I20: =F20/H20 | N20: =O19 | O20: 14184 | P20: =O20-N20 | R20: =R19+1 | S20: DAY | T20: =U19 | U20: 1714 | V20: =U20-T20 | W20: 230 | X20: 1706 | Y20: =X20-X18 | Z20: =W20/Y20 | AE20: =AF19 | AF20: 20146 | AG20: =AF20-AE20
A21: =A20 | B21: NIGHT | C21: =D20 | D21: 1082 | E21: =D21-C21 | N21: =O20 | O21: 14336 | P21: =O21-N21 | R21: =R20 | S21: NIGHT | T21: =U20 | U21: 1725 | V21: =U21-T21 | AE21: =AF20 | AF21: 20331 | AG21: =AF21-AE21
A22: =A21+1 | B22: DAY | C22: =D21 | D22: 1092 | E22: =D22-C22 | F22: 340 | G22: 1087 | H22: =G22-G20 | I22: =F22/H22 | N22: =O21 | O22: 14493 | P22: =O22-N22 | R22: =R21+1 | S22: DAY | T22: =U21 | U22: 1736 | V22: =U22-T22 | W22: 350 | X22: 1731 | Y22: =X22-X20 | Z22: =W22/Y22 | AE22: =AF21 | AF22: 20573 | AG22: =AF22-AE22
A23: =A22 | B23: NIGHT | C23: =D22 | D23: 1100 | E23: =D23-C23 | N23: =O22 | O23: 14616 | P23: =O23-N23 | R23: =R22 | S23: NIGHT | T23: =U22 | U23: 1746 | V23: =U23-T23 | AE23: =AF22 | AF23: 20754 | AG23: =AF23-AE23
A24: =A23+1 | B24: DAY | C24: =D23 | D24: 1108 | E24: =D24-C24 | F24: 240 | G24: 1104 | H24: =G24-G22 | I24: =F24/H24 | N24: =O23 | O24: 14770 | P24: =O24-N24 | R24: =R23+1 | S24: DAY | T24: =U23 | U24: 1755 | V24: =U24-T24 | W24: 260 | X24: 1752 | Y24: =X24-X22 | Z24: =W24/Y24 | AE24: =AF23 | AF24: 20877 | AG24: =AF24-AE24
A25: =A24 | B25: NIGHT | C25: =D24 | D25: 1116 | E25: =D25-C25 | N25: =O24 | O25: 14867 | P25: =O25-N25 | R25: =R24 | S25: NIGHT | T25: =U24 | U25: 1762 | V25: =U25-T25 | AE25: =AF24 | AF25: 20947 | AG25: =AF25-AE25
A26: =A25+1 | B26: DAY | C26: =D25 | D26: 1121 | E26: =D26-C26 | F26: 180 | G26: 1118 | H26: =G26-G24 | I26: =F26/H26 | N26: =O25 | O26: 14963 | P26: =O26-N26 | R26: =R25+1 | S26: DAY | T26: =U25 | U26: 1769 | V26: =U26-T26 | W26: 150 | X26: 1764 | Y26: =X26-X24 | Z26: =W26/Y26 | AE26: =AF25 | AF26: 21030 | AG26: =AF26-AE26
A27: =A26 | B27: NIGHT | C27: =D26 | D27: 1130 | E27: =D27-C27 | N27: =O26 | O27: 15002 | P27: =O27-N27 | R27: =R26 | S27: NIGHT | T27: =U26 | U27: 1776 | V27: =U27-T27 | AE27: =AF26 | AF27: 21093 | AG27: =AF27-AE27
A28: =A27+1 | B28: DAY | C28: =D27 | D28: 1139 | E28: =D28-C28 | F28: 150 | G28: 1132 | H28: =G28-G26 | I28: =F28/H28 | N28: =O27 | O28: 15199 | P28: =O28-N28 | R28: =R27+1 | S28: DAY | T28: =U27 | U28: 1786 | V28: =U28-T28 | W28: 160 | X28: 1779 | Y28: =X28-X26 | Z28: =W28/Y28 | AE28: =AF27 | AF28: 21289 | AG28: =AF28-AE28
A29: =A28 | B29: NIGHT | C29: =D28 | D29: 1148 | E29: =D29-C29 | N29: =O28 | O29: 15302 | P29: =O29-N29 | R29: =R28 | S29: NIGHT | T29: =U28 | U29: 1794 | V29: =U29-T29 | AE29: =AF28 | AF29: 21364 | AG29: =AF29-AE29
A30: =A29+1 | B30: DAY | C30: =D29 | D30: 1156 | E30: =D30-C30 | F30: 250 | G30: 1157 | H30: =G30-G28 | I30: =F30/H30 | N30: =O29 | O30: 15426 | P30: =O30-N30 | R30: =R29+1 | S30: DAY | T30: =U29 | U30: 1804 | V30: =U30-T30 | W30: 250 | X30: 1798 | Y30: =X30-X28 | Z30: =W30/Y30 | AE30: =AF29 | AF30: 21521 | AG30: =AF30-AE30
A31: =A30 | B31: NIGHT | C31: =D30 | D31: 1167 | E31: =D31-C31 | N31: =O30 | O31: 15537 | P31: =O31-N31 | R31: =R30 | S31: NIGHT | T31: =U30 | U31: 1814 | V31: =U31-T31 | AE31: =AF30 | AF31: 21687 | AG31: =AF31-AE31
A32: =A31+1 | B32: DAY | C32: =D31 | D32: 1177 | E32: =D32-C32 | F32: 230 | G32: 1171 | H32: =G32-G30 | I32: =F32/H32 | N32: =O31 | O32: 15699 | P32: =O32-N32 | R32: =R31+1 | S32: DAY | T32: =U31 | U32: 1823 | V32: =U32-T32 | W32: 260 | X32: 1818 | Y32: =X32-X30 | Z32: =W32/Y32 | AE32: =AF31 | AF32: 21824 | AG32: =AF32-AE32
A33: =A32 | B33: NIGHT | C33: =D32 | D33: 1184 | E33: =D33-C33 | N33: =O32 | O33: 15767 | P33: =O33-N33 | R33: =R32 | S33: NIGHT | T33: =U32 | U33: 1828 | V33: =U33-T33 | AE33: =AF32 | AF33: 21888 | AG33: =AF33-AE33
A34: =A33+1 | B34: DAY | C34: =D33 | D34: 1194 | E34: =D34-C34 | F34: 150 | G34: 1187 | H34: =G34-G32 | I34: =F34/H34 | N34: =O33 | O34: 15903 | P34: =O34-N34 | R34: =R33+1 | S34: DAY | T34: =U33 | U34: 1837 | V34: =U34-T34 | W34: 110 | X34: 1831 | Y34: =X34-X32 | Z34: =W34/Y34 | AE34: =AF33 | AF34: 22035 | AG34: =AF34-AE34
A35: =A34 | B35: NIGHT | C35: =D34 | D35: 1203 | E35: =D35-C35 | N35: =O34 | O35: 16038 | P35: =O35-N35 | R35: =R34 | S35: NIGHT | T35: =U34 | U35: 1847 | V35: =U35-T35 | AE35: =AF34 | AF35: 22153 | AG35: =AF35-AE35
A36: =A35+1 | B36: DAY | C36: =D35 | D36: 1213 | E36: =D36-C36 | F36: 320 | G36: 1209 | H36: =G36-G34 | I36: =F36/H36 | N36: =O35 | O36: 16217 | P36: =O36-N36 | R36: =R35+1 | S36: DAY | T36: =U35 | U36: 1857 | V36: =U36-T36 | W36: 340 | X36: 1853 | Y36: =X36-X34 | Z36: =W36/Y36 | AE36: =AF35 | AF36: 22354 | AG36: =AF36-AE36
A37: =A36 | B37: NIGHT | C37: =D36 | D37: 1223 | E37: =D37-C37 | N37: =O36 | O37: 16367 | P37: =O37-N37 | R37: =R36 | S37: NIGHT | T37: =U36 | U37: 1869 | V37: =U37-T37 | AE37: =AF36 | AF37: 22562 | AG37: =AF37-AE37
A38: =A37+1 | B38: DAY | C38: =D37 | D38: 1231 | E38: =D38-C38 | F38: 240 | N38: =O37 | O38: 16481 | P38: =O38-N38 | R38: =R37+1 | S38: DAY | T38: =U37 | U38: 1879 | V38: =U38-T38 | W38: 270 | X38: 1873 | Y38: =X38-X36 | Z38: =W38/Y38 | AE38: =AF37 | AF38: 22720 | AG38: =AF38-AE38
A39: =A38 | B39: NIGHT | C39: =D38 | D39: 1239 | E39: =D39-C39 | N39: =O38 | O39: 16576 | P39: =O39-N39 | R39: =R38 | S39: NIGHT | T39: =U38 | U39: 1887 | V39: =U39-T39 | AE39: =AF38 | AF39: 22874 | AG39: =AF39-AE39
A40: =A39+1 | B40: DAY | C40: =D39 | D40: 1250 | E40: =D40-C40 | F40: 300 | G40: 1241 | H40: =G40-G36 | I40: =F40/H40 | N40: =O39 | O40: 16726 | P40: =O40-N40 | R40: =R39+1 | S40: DAY | T40: =U39 | U40: 1898 | V40: =U40-T40 | W40: 240 | X40: 1893 | Y40: =X40-X38 | Z40: =W40/Y40 | AE40: =AF39 | AF40: 23053 | AG40: =AF40-AE40
A41: =A40 | B41: NIGHT | C41: =D40 | D41: 1260 | E41: =D41-C41 | N41: =O40 | O41: 16845 | P41: =O41-N41 | R41: =R40 | S41: NIGHT | T41: =U40 | U41: 1909 | V41: =U41-T41 | AE41: =AF40 | AF41: 23204 | AG41: =AF41-AE41
A42: =A41+1 | B42: DAY | C42: =D41 | D42: 1269 | E42: =D42-C42 | F42: 200 | G42: 1265 | H42: =G42-G40 | I42: =F42/H42 | N42: =O41 | O42: 16974 | P42: =O42-N42 | Q42: NAZEER | R42: =R41+1 | S42: DAY | T42: =U41 | U42: 1919 | V42: =U42-T42 | W42: 270 | X42: 1915 | Y42: =X42-X40 | Z42: =W42/Y42 | AE42: =AF41 | AF42: 23370 | AG42: =AF42-AE42
A43: =A42 | B43: NIGHT | C43: =D42 | D43: 1274 | E43: =D43-C43 | N43: =O42 | O43: 17071 | P43: =O43-N43 | Q43: PANKAJ | R43: =R42 | S43: NIGHT | T43: =U42 | U43: 1926 | V43: =U43-T43 | AE43: =AF42 | AF43: 23445 | AG43: =AF43-AE43
A44: =A43+1 | B44: DAY | C44: =D43 | D44: 1284 | E44: =D44-C44 | F44: 250 | G44: 1280 | H44: =G44-G42 | I44: =F44/H44 | N44: =O43 | O44: 17205 | P44: =O44-N44 | Q44: SAIDULLA | R44: =R43+1 | S44: DAY | T44: =U43 | U44: 1936 | V44: =U44-T44 | W44: 200 | X44: 1932 | Y44: =X44-X42 | Z44: =W44/Y44 | AE44: =AF43 | AF44: 23586 | AG44: =AF44-AE44
A45: =A44 | B45: NIGHT | C45: =D44 | D45: 1293 | E45: =D45-C45 | N45: =O44 | O45: 17335 | P45: =O45-N45 | Q45: PANKAJ | R45: =R44 | S45: NIGHT | T45: =U44 | U45: 1945 | V45: =U45-T45 | AE45: =AF44 | AF45: 23697 | AG45: =AF45-AE45
A46: =A45+1 | B46: DAY | C46: =D45 | D46: 1304 | E46: =D46-C46 | F46: 210 | G46: 1297 | H46: =G46-G44 | I46: =F46/H46 | N46: =O45 | O46: 17481 | P46: =O46-N46 | Q46: SAIDULLA | R46: =R45+1 | S46: DAY | T46: =U45 | U46: 1956 | V46: =U46-T46 | W46: 170 | X46: 1949 | Y46: =X46-X44 | Z46: =W46/Y46 | AE46: =AF45 | AF46: 23837 | AG46: =AF46-AE46
A47: =A46 | B47: NIGHT | C47: =D46 | D47: 1314 | E47: =D47-C47 | N47: =O46 | O47: 17621 | P47: =O47-N47 | Q47: NAZEER | R47: =R46 | S47: NIGHT | T47: =U46 | U47: 1967 | V47: =U47-T47 | AE47: =AF46 | AF47: 24025 | AG47: =AF47-AE47
A48: =A47+1 | B48: DAY | C48: =D47 | D48: 1318 | E48: =D48-C48 | F48: 200 | G48: 1314 | H48: =G48-G46 | I48: =F48/H48 | N48: =O47 | O48: 17670 | P48: =O48-N48 | Q48: PANKAJ | R48: =R47+1 | S48: DAY | T48: =U47 | U48: 1974 | V48: =U48-T48 | W48: 250 | X48: 1968 | Y48: =X48-X46 | Z48: =W48/Y48 | AE48: =AF47 | AF48: 24128 | AG48: =AF48-AE48
A49: =A48 | B49: NIGHT | C49: =D48 | D49: 1328 | E49: =D49-C49 | N49: =O48 | O49: 17782 | P49: =O49-N49 | Q49: NAZEER | R49: =R48 | S49: NIGHT | T49: =U48 | U49: 1983 | V49: =U49-T49 | AE49: =AF48 | AF49: 24240 | AG49: =AF49-AE49
A50: =A49+1 | B50: DAY | C50: =D49 | D50: 1337 | E50: =D50-C50 | F50: 250 | G50: 1331 | H50: =G50-G48 | I50: =F50/H50 | N50: =O49 | O50: 17969 | P50: =O50-N50 | Q50: PANKAJ | R50: =R49+1 | S50: DAY | T50: =U49 | U50: 1993 | V50: =U50-T50 | W50: 220 | X50: 1986 | Y50: =X50-X48 | Z50: =W50/Y50 | AE50: =AF49 | AF50: 24397 | AG50: =AF50-AE50
A51: =A50 | B51: NIGHT | C51: =D50 | D51: 1347 | E51: =D51-C51 | N51: =O50 | O51: 18079 | P51: =O51-N51 | Q51: SAIDULLA | R51: =R50 | S51: NIGHT | T51: =U50 | U51: 2003 | V51: =U51-T51 | AE51: =AF50 | AF51: 24520 | AG51: =AF51-AE51
A52: =A51+1 | B52: DAY | C52: 1347 | D52: 1356 | E52: =D52-C52 | F52: 260 | G52: 1359 | H52: =G52-G50 | I52: =F52/H52 | N52: 18079 | O52: 18195 | P52: =O52-N52 | Q52: NAZEER | R52: =R51+1 | S52: DAY | T52: 2003 | U52: 2013 | V52: =U52-T52 | W52: 270 | X52: 2009 | Y52: =X52-X50 | Z52: =W52/Y52 | AE52: 24520 | AF52: 24640 | AG52: =AF52-AE52
A53: =A52 | B53: NIGHT | C53: 1356 | D53: 1366 | E53: =D53-C53 | N53: 18195 | O53: 18295 | P53: =O53-N53 | Q53: SAIDULLA | R53: =R52 | S53: NIGHT | T53: 2013 | U53: 2022 | V53: =U53-T53 | AE53: 24640 | AF53: 24732 | AG53: =AF53-AE53
A54: =A53+1 | B54: DAY | C54: =D53 | D54: 1377 | E54: =D54-C54 | F54: 140 | G54: 1370 | H54: =G54-G52 | I54: =F54/H54 | N54: =O53 | O54: 18478 | P54: =O54-N54 | Q54: RAJKUMAR | R54: =R53+1 | S54: DAY | T54: =U53 | U54: 2032 | V54: =U54-T54 | W54: 150 | X54: 2026 | Y54: =X54-X52 | Z54: =W54/Y54 | AE54: =AF53 | AF54: 24886 | AG54: =AF54-AE54
A55: =A54 | B55: NIGHT | C55: =D54 | D55: 1383 | E55: =D55-C55 | N55: =O54 | O55: 18600 | P55: =O55-N55 | Q55: PANKAJ | R55: =R54 | S55: NIGHT | T55: =U54 | U55: 2041 | V55: =U55-T55 | AE55: =AF54 | AF55: 24958 | AG55: =AF55-AE55
A56: =A55+1 | B56: DAY | C56: =D55 | D56: 1392 | E56: =D56-C56 | F56: 300 | G56: 1387 | H56: =G56-G54 | I56: =F56/H56 | N56: =O55 | O56: 18712 | P56: =O56-N56 | Q56: NAZEER | R56: =R55+1 | S56: DAY | T56: =U55 | U56: 2051 | V56: =U56-T56 | W56: 260 | X56: 2046 | Y56: =X56-X54 | Z56: =W56/Y56 | AE56: =AF55 | AF56: 25102 | AG56: =AF56-AE56
A57: =A56 | B57: NIGHT | C57: =D56 | D57: 1396 | E57: =D57-C57 | N57: =O56 | O57: 18763 | P57: =O57-N57 | Q57: PANKAJ | R57: =R56 | S57: NIGHT | T57: =U56 | U57: 2059 | V57: =U57-T57 | AE57: =AF56 | AF57: 25182 | AG57: =AF57-AE57
A58: =A57+1 | B58: DAY | C58: =D57 | D58: 1406 | E58: =D58-C58 | F58: 200 | G58: 1402 | H58: =G58-G56 | I58: =F58/H58 | N58: =O57 | O58: 18882 | P58: =O58-N58 | Q58: SAIDULLA | R58: =R57+1 | S58: DAY | T58: =U57 | U58: 2069 | V58: =U58-T58 | W58: 220 | X58: 2064 | Y58: =X58-X56 | Z58: =W58/Y58 | AE58: =AF57 | AF58: 25266 | AG58: =AF58-AE58
A59: =A58 | B59: NIGHT | C59: =D58 | D59: 1414 | E59: =D59-C59 | N59: =O58 | O59: 18981 | P59: =O59-N59 | Q59: NAZEER | R59: =R58 | S59: NIGHT | T59: =U58 | U59: 2077 | V59: =U59-T59 | AE59: =AF58 | AF59: 25376 | AG59: =AF59-AE59
A60: =A59+1 | B60: DAY | C60: =D59 | D60: 1423 | E60: =D60-C60 | F60: 200 | G60: 1418 | H60: =G60-G58 | I60: =F60/H60 | N60: =O59 | O60: 19136 | P60: =O60-N60 | Q60: PANKAJ | R60: =R59+1 | S60: DAY | T60: =U59 | U60: 2086 | V60: =U60-T60 | W60: 180 | X60: 2079 | Y60: =X60-X58 | Z60: =W60/Y60 | AE60: =AF59 | AF60: 25531 | AG60: =AF60-AE60
A61: =A60 | B61: NIGHT | C61: =D60 | D61: 1433 | E61: =D61-C61 | N61: =O60 | O61: 19293 | P61: =O61-N61 | Q61: KANHAIYA | R61: =R60 | S61: NIGHT | T61: =U60 | U61: 2096 | V61: =U61-T61 | W61: 180 | X61: 2096 | Y61: =X61-X60 | Z61: =W61/Y61 | AE61: =AF60 | AF61: 25679 | AG61: =AF61-AE61
A62: =A61+1 | B62: DAY | C62: =D61 | D62: 1443 | E62: =D62-C62 | F62: 160 | G62: 1433 | H62: =G62-G60 | I62: =F62/H62 | N62: =O61 | O62: 19505 | P62: =O62-N62 | Q62: PANKAJ | R62: =R61+1 | S62: DAY | T62: =U61 | U62: 2107 | V62: =U62-T62 | AE62: =AF61 | AF62: 25861 | AG62: =AF62-AE62
A63: =A62 | B63: NIGHT | C63: =D62 | D63: 1453 | E63: =D63-C63 | N63: =O62 | O63: 19638 | P63: =O63-N63 | Q63: SAIDULLA | R63: =R62 | S63: NIGHT | T63: =U62 | U63: 2118 | V63: =U63-T63 | AE63: =AF62 | AF63: 26063 | AG63: =AF63-AE63
A64: =A63+1 | B64: DAY | C64: =D63 | D64: 1462 | E64: =D64-C64 | F64: 370 | G64: 1456 | H64: =G64-G62 | I64: =F64/H64 | N64: =O63 | O64: 19777 | P64: =O64-N64 | Q64: PANKAJ | R64: =R63+1 | S64: DAY | T64: =U63 | U64: 2127 | V64: =U64-T64 | W64: 380 | X64: 2121 | Y64: =X64-X61 | Z64: =W64/Y64 | AE64: =AF63 | AF64: 26270 | AG64: =AF64-AE64 | AH64: RAJKUMAR
A65: =A64 | B65: NIGHT | C65: =D64 | D65: 1471 | E65: =D65-C65 | N65: =O64 | O65: 19882 | P65: =O65-N65 | Q65: SAIDULLA | R65: =R64 | S65: NIGHT | T65: =U64 | U65: 2137 | V65: =U65-T65 | AE65: =AF64 | AF65: 26442 | AG65: =AF65-AE65 | AH65: KANHAIYA
A66: TOTAL Running Hours: | E66: =SUBTOTAL(9,E4:E65) | F66: =SUBTOTAL(9,F4:F65) | I66: =F66/E66 | P66: =SUBTOTAL(9,P4:P65) | R66: TOTAL Running Hours: | V66: =SUBTOTAL(9,V4:V65) | W66: =SUBTOTAL(9,W4:W65) | Z66: =W66/V66 | AG66: =SUBTOTAL(9,AG4:AG65)
C67: Maximum Running | E67: 540 | T67: Maximum Running | V67: 540
C68: Extra Running | E68: =E66-E67 | T68: Extra Running | V68: =V66-V67
C70: Raise tax invoice with full hiring charges | R70: Raise tax invoice with full hiring charges
C71: Poonam Goswami | R71: Poonam Goswami
C72: 46280 | R72: 46280
C73: No excessive running hours Bill raised as per Amit ji and Vikas Sir | R73: No excessive running hours Bill raised as per Amit ji and Vikas Sir

Sheet Sep-26
A1: NEW MACHINE NO - SANY-8 | J1: BREAKDOWN TIME/Cooling | R1: NEW MACHINE NO - SANY-9 | AA1: BREAKDOWN TIME/Cooling
A2: Date | B2: Shift | C2: Starting HMR | D2: Closing HMR | E2: HOURS | F2: Diesel Issued (Ltr) | G2: HMR at Diesel Fill | H2: HOURS | I2: Avg. Diesel Consumption (Ltr/Hr) | J2: Shift Start Time | K2: Shift End Time | L2: TOTAL HRS | M2: Remarks | N2: Container Start Count | O2: Container End Count | P2: Total | Q2: Remark | R2: Date | S2: Shift | T2: Starting HMR | U2: Closing HMR | V2: HOURS | W2: Diesel Issued (Ltr) | X2: HMR at Diesel Fill | Y2: HOURS | Z2: Avg. Diesel Consumption (Ltr/Hr) | AA2: Shift Start Time | AB2: Shift End Time | AC2: TOTAL HRS | AD2: Remarks | AE2: Container Start Count | AF2: Container End Count | AG2: Total | AH2: Remark
G3: 1456 | X3: 2121
A4: 46266 | B4: DAY | C4: ='Aug-26'!D65 | D4: 1481 | E4: =IF(OR(C4="",D4=""),0,D4-C4) | F4: 240 | G4: 1476 | H4: =IF(OR(G3="",G4=""),"",G4-G3) | I4: =IFERROR(F4/H4,0) | N4: 19882 | O4: 20010 | P4: =IF(OR(N4="",O4=""),0,O4-N4) | Q4: NAZEER | R4: 46266 | S4: DAY | T4: 2137 | U4: 2147 | V4: =IF(OR(T4="",U4=""),0,U4-T4) | W4: 250 | X4: 2143 | Y4: =IF(OR(X3="",X4=""),"",X4-X3) | Z4: =IFERROR(W4/Y4,0) | AE4: 26442 | AF4: 26601 | AG4: =IF(OR(AE4="",AF4=""),0,AF4-AE4) | AH4: AMAN
A5: 46266 | B5: NIGHT | C5: =D4 | D5: 1486 | E5: =IF(OR(C5="",D5=""),0,D5-C5) | N5: =O4 | O5: 20081 | P5: =IF(OR(N5="",O5=""),0,O5-N5) | Q5: PANKAJ | R5: 46266 | S5: NIGHT | T5: =U4 | U5: 2154 | V5: =IF(OR(T5="",U5=""),0,U5-T5) | AE5: =AF4 | AF5: 26739 | AG5: =IF(OR(AE5="",AF5=""),0,AF5-AE5) | AH5: RAJKUMAR
A6: 46267 | B6: DAY | C6: =D5 | D6: 1496 | E6: =IF(OR(C6="",D6=""),0,D6-C6) | F6: 150 | G6: 1488 | H6: =IF(OR(G4="",G6=""),"",G6-G4) | I6: =IFERROR(F6/H6,0) | N6: =O5 | O6: 20174 | P6: =IF(OR(N6="",O6=""),0,O6-N6) | Q6: SAIDULLA | R6: 46267 | S6: DAY | T6: =U5 | U6: 2164 | V6: =IF(OR(T6="",U6=""),0,U6-T6) | W6: 150 | X6: 2175 | Y6: =IF(OR(X4="",X6=""),"",X6-X4) | Z6: =IFERROR(W6/Y6,0) | AE6: =AF5 | AF6: 26875 | AG6: =IF(OR(AE6="",AF6=""),0,AF6-AE6) | AH6: KANHAIYA
A7: 46267 | B7: NIGHT | C7: =D6 | D7: 1504 | E7: =IF(OR(C7="",D7=""),0,D7-C7) | N7: =O6 | O7: 20284 | P7: =IF(OR(N7="",O7=""),0,O7-N7) | Q7: NAZEER | R7: 46267 | S7: NIGHT | T7: =U6 | U7: 2175 | V7: =IF(OR(T7="",U7=""),0,U7-T7) | AE7: =AF6 | AF7: 27042 | AG7: =IF(OR(AE7="",AF7=""),0,AF7-AE7) | AH7: AMAN
A8: 46268 | B8: DAY | C8: =D7 | D8: 1514 | E8: =IF(OR(C8="",D8=""),0,D8-C8) | F8: 200 | G8: 1507 | H8: =IF(OR(G6="",G8=""),"",G8-G6) | I8: =IFERROR(F8/H8,0) | N8: =O7 | O8: 20418 | P8: =IF(OR(N8="",O8=""),0,O8-N8) | Q8: SAIDULLA | R8: 46268 | S8: DAY | T8: =U7 | U8: 2185 | V8: =IF(OR(T8="",U8=""),0,U8-T8) | W8: 240 | X8: 2179 | Y8: =IF(OR(X6="",X8=""),"",X8-X6) | Z8: =IFERROR(W8/Y8,0) | AE8: =AF7 | AF8: 27150 | AG8: =IF(OR(AE8="",AF8=""),0,AF8-AE8) | AH8: KANHAIYA
A9: 46268 | B9: NIGHT | C9: =D8 | D9: 1522 | E9: =IF(OR(C9="",D9=""),0,D9-C9) | N9: =O8 | O9: 20505 | P9: =IF(OR(N9="",O9=""),0,O9-N9) | Q9: NAZEER | R9: 46268 | S9: NIGHT | T9: =U8 | U9: 2194 | V9: =IF(OR(T9="",U9=""),0,U9-T9) | AE9: =AF8 | AF9: 27266 | AG9: =IF(OR(AE9="",AF9=""),0,AF9-AE9) | AH9: AMAN
A10: 46269 | B10: DAY | C10: =D9 | D10: 1530 | E10: =IF(OR(C10="",D10=""),0,D10-C10) | F10: 240 | G10: 1525 | H10: =IF(OR(G8="",G10=""),"",G10-G8) | I10: =IFERROR(F10/H10,0) | N10: =O9 | O10: 20658 | P10: =IF(OR(N10="",O10=""),0,O10-N10) | Q10: PANKAJ | R10: 46269 | S10: DAY | T10: =U9 | U10: 2204 | V10: =IF(OR(T10="",U10=""),0,U10-T10) | W10: 190 | X10: 2198 | Y10: =IF(OR(X8="",X10=""),"",X10-X8) | Z10: =IFERROR(W10/Y10,0) | AE10: =AF9 | AF10: 27418 | AG10: =IF(OR(AE10="",AF10=""),0,AF10-AE10) | AH10: SAIDULLAH
A11: 46269 | B11: NIGHT | C11: =D10 | D11: 1538 | E11: =IF(OR(C11="",D11=""),0,D11-C11) | N11: =O10 | O11: 20757 | P11: =IF(OR(N11="",O11=""),0,O11-N11) | Q11: KANHAIYA | R11: 46269 | S11: NIGHT | T11: =U10 | U11: 2213 | V11: =IF(OR(T11="",U11=""),0,U11-T11) | AE11: =AF10 | AF11: 27580 | AG11: =IF(OR(AE11="",AF11=""),0,AF11-AE11) | AH11: RAJKUMAR
A12: 46270 | B12: DAY | C12: =D11 | D12: 1546 | E12: =IF(OR(C12="",D12=""),0,D12-C12) | F12: 210 | G12: 1541 | H12: =IF(OR(G10="",G12=""),"",G12-G10) | I12: =IFERROR(F12/H12,0) | N12: =O11 | O12: 20874 | P12: =IF(OR(N12="",O12=""),0,O12-N12) | Q12: PANKAJ | R12: 46270 | S12: DAY | T12: =U11 | U12: 2223 | V12: =IF(OR(T12="",U12=""),0,U12-T12) | W12: 210 | X12: 2216 | Y12: =IF(OR(X10="",X12=""),"",X12-X10) | Z12: =IFERROR(W12/Y12,0) | AE12: =AF11 | AF12: 27706 | AG12: =IF(OR(AE12="",AF12=""),0,AF12-AE12) | AH12: SAIDULLAH
A13: 46270 | B13: NIGHT | C13: =D12 | D13: 1556 | E13: =IF(OR(C13="",D13=""),0,D13-C13) | N13: =O12 | O13: 20994 | P13: =IF(OR(N13="",O13=""),0,O13-N13) | Q13: KANHAIYA | R13: 46270 | S13: NIGHT | T13: =U12 | U13: 2232 | V13: =IF(OR(T13="",U13=""),0,U13-T13) | AE13: =AF12 | AF13: 27843 | AG13: =IF(OR(AE13="",AF13=""),0,AF13-AE13) | AH13: RAJKUMAR
A14: 46271 | B14: DAY | C14: =D13 | D14: 1566 | E14: =IF(OR(C14="",D14=""),0,D14-C14) | F14: 250 | G14: 1562 | H14: =IF(OR(G12="",G14=""),"",G14-G12) | I14: =IFERROR(F14/H14,0) | N14: =O13 | O14: 21100 | P14: =IF(OR(N14="",O14=""),0,O14-N14) | Q14: SAIDULLA | R14: 46271 | S14: DAY | T14: =U13 | U14: 2241 | V14: =IF(OR(T14="",U14=""),0,U14-T14) | W14: 212 | X14: 2234 | Y14: =IF(OR(X12="",X14=""),"",X14-X12) | Z14: =IFERROR(W14/Y14,0) | AE14: =AF13 | AF14: 27994 | AG14: =IF(OR(AE14="",AF14=""),0,AF14-AE14) | AH14: AMAN
A15: 46271 | B15: NIGHT | C15: =D14 | D15: 1573 | E15: =IF(OR(C15="",D15=""),0,D15-C15) | N15: =O14 | O15: 21224 | P15: =IF(OR(N15="",O15=""),0,O15-N15) | Q15: PANKAJ | R15: 46271 | S15: NIGHT | T15: =U14 | U15: 2248 | V15: =IF(OR(T15="",U15=""),0,U15-T15) | AE15: =AF14 | AF15: 28066 | AG15: =IF(OR(AE15="",AF15=""),0,AF15-AE15) | AH15: KANHAIYA
A16: 46272 | B16: DAY | C16: =D15 | D16: 1581 | E16: =IF(OR(C16="",D16=""),0,D16-C16) | F16: 240 | G16: 1577 | H16: =IF(OR(G14="",G16=""),"",G16-G14) | I16: =IFERROR(F16/H16,0) | N16: =O15 | O16: 21312 | P16: =IF(OR(N16="",O16=""),0,O16-N16) | Q16: NAZEER | R16: 46272 | S16: DAY | T16: =U15 | U16: 2257 | V16: =IF(OR(T16="",U16=""),0,U16-T16) | W16: 280 | X16: 2252 | Y16: =IF(OR(X14="",X16=""),"",X16-X14) | Z16: =IFERROR(W16/Y16,0) | AE16: =AF15 | AF16: 28151 | AG16: =IF(OR(AE16="",AF16=""),0,AF16-AE16) | AH16: AMAN
A17: 46272 | B17: NIGHT | C17: =D16 | D17: 1589 | E17: =IF(OR(C17="",D17=""),0,D17-C17) | N17: =O16 | O17: 21450 | P17: =IF(OR(N17="",O17=""),0,O17-N17) | Q17: PANKAJ | R17: 46272 | S17: NIGHT | T17: =U16 | U17: 2267 | V17: =IF(OR(T17="",U17=""),0,U17-T17) | AE17: =AF16 | AF17: 28360 | AG17: =IF(OR(AE17="",AF17=""),0,AF17-AE17) | AH17: RAJKUMAR
A18: 46273 | B18: DAY | C18: =D17 | D18: 1600 | E18: =IF(OR(C18="",D18=""),0,D18-C18) | F18: 260 | G18: 1595 | H18: =IF(OR(G16="",G18=""),"",G18-G16) | I18: =IFERROR(F18/H18,0) | N18: =O17 | O18: 21631 | P18: =IF(OR(N18="",O18=""),0,O18-N18) | Q18: KANHAIYA | R18: 46273 | S18: DAY | T18: =U17 | U18: 2277 | V18: =IF(OR(T18="",U18=""),0,U18-T18) | W18: 200 | X18: 2273 | Y18: =IF(OR(X16="",X18=""),"",X18-X16) | Z18: =IFERROR(W18/Y18,0) | AE18: =AF17 | AF18: 28519 | AG18: =IF(OR(AE18="",AF18=""),0,AF18-AE18) | AH18: NAZEER
A19: 46273 | B19: NIGHT | C19: =D18 | D19: 1608 | E19: =IF(OR(C19="",D19=""),0,D19-C19) | N19: =O18 | O19: 21762 | P19: =IF(OR(N19="",O19=""),0,O19-N19) | Q19: RAJKUMAR | R19: 46273 | S19: NIGHT | T19: =U18 | U19: 2286 | V19: =IF(OR(T19="",U19=""),0,U19-T19) | AE19: =AF18 | AF19: 28635 | AG19: =IF(OR(AE19="",AF19=""),0,AF19-AE19) | AH19: AMAN
A20: 46274 | B20: DAY | C20: =D19 | D20: 1618 | E20: =IF(OR(C20="",D20=""),0,D20-C20) | F20: 200 | G20: 1613 | H20: =IF(OR(G18="",G20=""),"",G20-G18) | I20: =IFERROR(F20/H20,0) | N20: =O19 | O20: 21846 | P20: =IF(OR(N20="",O20=""),0,O20-N20) | Q20: SAIDULLA | R20: 46274 | S20: DAY | T20: =U19 | U20: 2296 | V20: =IF(OR(T20="",U20=""),0,U20-T20) | W20: 220 | X20: 2290 | Y20: =IF(OR(X18="",X20=""),"",X20-X18) | Z20: =IFERROR(W20/Y20,0) | AE20: =AF19 | AF20: 28749 | AG20: =IF(OR(AE20="",AF20=""),0,AF20-AE20) | AH20: KANHAIYA
A21: 46274 | B21: NIGHT | C21: =D20 | D21: 1627 | E21: =IF(OR(C21="",D21=""),0,D21-C21) | N21: =O20 | O21: 22039 | P21: =IF(OR(N21="",O21=""),0,O21-N21) | Q21: PANKAJ | R21: 46274 | S21: NIGHT | T21: =U20 | U21: 2305 | V21: =IF(OR(T21="",U21=""),0,U21-T21) | AE21: =AF20 | AF21: 28913 | AG21: =IF(OR(AE21="",AF21=""),0,AF21-AE21) | AH21: NAZEER
A22: 46275 | B22: DAY | C22: =D21 | D22: 1638 | E22: =IF(OR(C22="",D22=""),0,D22-C22) | F22: 300 | G22: 1633 | H22: =IF(OR(G20="",G22=""),"",G22-G20) | I22: =IFERROR(F22/H22,0) | N22: =O21 | O22: 22301 | P22: =IF(OR(N22="",O22=""),0,O22-N22) | Q22: AMAN | R22: 46275 | S22: DAY | T22: =U21 | U22: 2315 | V22: =IF(OR(T22="",U22=""),0,U22-T22) | W22: 290 | X22: 2311 | Y22: =IF(OR(X20="",X22=""),"",X22-X20) | Z22: =IFERROR(W22/Y22,0) | AE22: =AF21 | AF22: 29153 | AG22: =IF(OR(AE22="",AF22=""),0,AF22-AE22) | AH22: RAJKUMAR
A23: 46275 | B23: NIGHT | C23: =D22 | D23: 1646 | E23: =IF(OR(C23="",D23=""),0,D23-C23) | N23: =O22 | O23: 22378 | P23: =IF(OR(N23="",O23=""),0,O23-N23) | Q23: SAIDULLA | R23: 46275 | S23: NIGHT | T23: =U22 | U23: 2323 | V23: =IF(OR(T23="",U23=""),0,U23-T23) | AE23: =AF22 | AF23: 29257 | AG23: =IF(OR(AE23="",AF23=""),0,AF23-AE23) | AH23: NAZEER
A24: 46276 | B24: DAY | C24: =D23 | D24: 1655 | E24: =IF(OR(C24="",D24=""),0,D24-C24) | F24: 240 | G24: 1650 | H24: =IF(OR(G22="",G24=""),"",G24-G22) | I24: =IFERROR(F24/H24,0) | N24: =O23 | O24: 22494 | P24: =IF(OR(N24="",O24=""),0,O24-N24) | Q24: PANKAJ | R24: 46276 | S24: DAY | T24: =U23 | U24: 2331 | V24: =IF(OR(T24="",U24=""),0,U24-T24) | W24: 220 | X24: 2327 | Y24: =IF(OR(X22="",X24=""),"",X24-X22) | Z24: =IFERROR(W24/Y24,0) | AE24: =AF23 | AF24: 29424 | AG24: =IF(OR(AE24="",AF24=""),0,AF24-AE24) | AH24: RAJKUMAR
A25: 46276 | B25: NIGHT | C25: =D24 | D25: 1664 | E25: =IF(OR(C25="",D25=""),0,D25-C25) | N25: =O24 | O25: 22609 | P25: =IF(OR(N25="",O25=""),0,O25-N25) | Q25: SAIDULLA | R25: 46276 | S25: NIGHT | T25: =U24 | U25: 2340 | V25: =IF(OR(T25="",U25=""),0,U25-T25) | AE25: =AF24 | AF25: 29546 | AG25: =IF(OR(AE25="",AF25=""),0,AF25-AE25) | AH25: NAZEER
A26: 46277 | B26: DAY | C26: =D25 | D26: 1673 | E26: =IF(OR(C26="",D26=""),0,D26-C26) | F26: 170 | G26: 1670 | H26: =IF(OR(G24="",G26=""),"",G26-G24) | I26: =IFERROR(F26/H26,0) | N26: =O25 | O26: 22745 | P26: =IF(OR(N26="",O26=""),0,O26-N26) | Q26: NAZEER | R26: 46277 | S26: DAY | T26: =U25 | U26: 2351 | V26: =IF(OR(T26="",U26=""),0,U26-T26) | W26: 210 | X26: 2345 | Y26: =IF(OR(X24="",X26=""),"",X26-X24) | Z26: =IFERROR(W26/Y26,0) | AE26: =AF25 | AF26: 29700 | AG26: =IF(OR(AE26="",AF26=""),0,AF26-AE26) | AH26: AMAN
A27: 46277 | B27: NIGHT | C27: =D26 | D27: 1681 | E27: =IF(OR(C27="",D27=""),0,D27-C27) | N27: =O26 | O27: 22894 | P27: =IF(OR(N27="",O27=""),0,O27-N27) | Q27: PANKAJ | R27: 46277 | S27: NIGHT | T27: =U26 | U27: 2359 | V27: =IF(OR(T27="",U27=""),0,U27-T27) | AE27: =AF26 | AF27: 29820 | AG27: =IF(OR(AE27="",AF27=""),0,AF27-AE27) | AH27: RAJKUMAR
A28: 46278 | B28: DAY | C28: =D27 | D28: 1690 | E28: =IF(OR(C28="",D28=""),0,D28-C28) | F28: 280 | G28: 1684 | H28: =IF(OR(G26="",G28=""),"",G28-G26) | I28: =IFERROR(F28/H28,0) | N28: =O27 | O28: 23042 | P28: =IF(OR(N28="",O28=""),0,O28-N28) | Q28: NAZEER | R28: 46278 | S28: DAY | T28: =U27 | U28: 2369 | V28: =IF(OR(T28="",U28=""),0,U28-T28) | W28: 230 | X28: 2363 | Y28: =IF(OR(X26="",X28=""),"",X28-X26) | Z28: =IFERROR(W28/Y28,0) | AE28: =AF27 | AF28: 30002 | AG28: =IF(OR(AE28="",AF28=""),0,AF28-AE28) | AH28: AMAN
A29: 46278 | B29: NIGHT | C29: =D28 | D29: 1697 | E29: =IF(OR(C29="",D29=""),0,D29-C29) | N29: =O28 | O29: 23160 | P29: =IF(OR(N29="",O29=""),0,O29-N29) | Q29: PANKAJ | R29: 46278 | S29: NIGHT | T29: =U28 | U29: 2379 | V29: =IF(OR(T29="",U29=""),0,U29-T29) | AE29: =AF28 | AF29: 30221 | AG29: =IF(OR(AE29="",AF29=""),0,AF29-AE29) | AH29: RAJKUMAR
A30: 46279 | B30: DAY | C30: =D29 | D30: 1706 | E30: =IF(OR(C30="",D30=""),0,D30-C30) | F30: 250 | G30: 1700 | H30: =IF(OR(G28="",G30=""),"",G30-G28) | I30: =IFERROR(F30/H30,0) | N30: =O29 | O30: 23324 | P30: =IF(OR(N30="",O30=""),0,O30-N30) | Q30: SAIDULLA | R30: 46279 | S30: DAY | T30: =U29 | U30: 2389 | V30: =IF(OR(T30="",U30=""),0,U30-T30) | W30: 270 | X30: 2384 | Y30: =IF(OR(X28="",X30=""),"",X30-X28) | Z30: =IFERROR(W30/Y30,0) | AE30: =AF29 | AF30: 30381 | AG30: =IF(OR(AE30="",AF30=""),0,AF30-AE30) | AH30: KANHAIYA
A31: 46279 | B31: NIGHT | C31: =D30 | D31: 1716 | E31: =IF(OR(C31="",D31=""),0,D31-C31) | N31: =O30 | O31: 23461 | P31: =IF(OR(N31="",O31=""),0,O31-N31) | Q31: NAZEER | R31: 46279 | S31: NIGHT | T31: =U30 | U31: 2399 | V31: =IF(OR(T31="",U31=""),0,U31-T31) | AE31: =AF30 | AF31: 30597 | AG31: =IF(OR(AE31="",AF31=""),0,AF31-AE31) | AH31: AMAN
A32: 46280 | B32: DAY | C32: =D31 | D32: 1726 | E32: =IF(OR(C32="",D32=""),0,D32-C32) | F32: 270 | G32: 1720 | H32: =IF(OR(G30="",G32=""),"",G32-G30) | I32: =IFERROR(F32/H32,0) | N32: =O31 | O32: 23628 | P32: =IF(OR(N32="",O32=""),0,O32-N32) | Q32: SAIDULLA | R32: 46280 | S32: DAY | T32: =U31 | U32: 2408 | V32: =IF(OR(T32="",U32=""),0,U32-T32) | W32: 270 | X32: 2404 | Y32: =IF(OR(X30="",X32=""),"",X32-X30) | Z32: =IFERROR(W32/Y32,0) | AE32: =AF31 | AF32: 30720 | AG32: =IF(OR(AE32="",AF32=""),0,AF32-AE32) | AH32: KANHAIYA
A33: 46280 | B33: NIGHT | C33: =D32 | D33: 1736 | E33: =IF(OR(C33="",D33=""),0,D33-C33) | N33: =O32 | O33: 23768 | P33: =IF(OR(N33="",O33=""),0,O33-N33) | Q33: NAZEER | R33: 46280 | S33: NIGHT | T33: =U32 | U33: 2416 | V33: =IF(OR(T33="",U33=""),0,U33-T33) | AE33: =AF32 | AF33: 30858 | AG33: =IF(OR(AE33="",AF33=""),0,AF33-AE33) | AH33: AMAN
A34: 46281 | B34: DAY | C34: =D33 | D34: 1742 | E34: =IF(OR(C34="",D34=""),0,D34-C34) | F34: 160 | G34: 1737 | H34: =IF(OR(G32="",G34=""),"",G34-G32) | I34: =IFERROR(F34/H34,0) | N34: =O33 | O34: 23846 | P34: =IF(OR(N34="",O34=""),0,O34-N34) | Q34: PANKAJ | R34: 46281 | S34: DAY | T34: =U33 | U34: 2423 | V34: =IF(OR(T34="",U34=""),0,U34-T34) | W34: 180 | X34: 2419 | Y34: =IF(OR(X32="",X34=""),"",X34-X32) | Z34: =IFERROR(W34/Y34,0) | AE34: =AF33 | AF34: 30970 | AG34: =IF(OR(AE34="",AF34=""),0,AF34-AE34) | AH34: RAJKUMAR
A35: 46281 | B35: NIGHT | C35: =D34 | D35: 1751 | E35: =IF(OR(C35="",D35=""),0,D35-C35) | N35: =O34 | O35: 23970 | P35: =IF(OR(N35="",O35=""),0,O35-N35) | Q35: SAIDULLA | R35: 46281 | S35: NIGHT | T35: =U34 | U35: 2432 | V35: =IF(OR(T35="",U35=""),0,U35-T35) | AE35: =AF34 | AF35: 31149 | AG35: =IF(OR(AE35="",AF35=""),0,AF35-AE35) | AH35: AMAN
A36: 46282 | B36: DAY | C36: =D35 | D36: 1759 | E36: =IF(OR(C36="",D36=""),0,D36-C36) | F36: 270 | G36: 1756 | H36: =IF(OR(G34="",G36=""),"",G36-G34) | I36: =IFERROR(F36/H36,0) | N36: =O35 | O36: 24105 | P36: =IF(OR(N36="",O36=""),0,O36-N36) | Q36: PANKAJ | R36: 46282 | S36: DAY | T36: =U35 | U36: 2441 | V36: =IF(OR(T36="",U36=""),0,U36-T36) | W36: 270 | X36: 2437 | Y36: =IF(OR(X34="",X36=""),"",X36-X34) | Z36: =IFERROR(W36/Y36,0) | AE36: =AF35 | AF36: 31354 | AG36: =IF(OR(AE36="",AF36=""),0,AF36-AE36) | AH36: RAJKUMAR
A37: 46282 | B37: NIGHT | C37: =D36 | D37: 1768 | E37: =IF(OR(C37="",D37=""),0,D37-C37) | N37: =O36 | O37: 24174 | P37: =IF(OR(N37="",O37=""),0,O37-N37) | Q37: SAIDULLA | R37: 46282 | S37: NIGHT | T37: =U36 | U37: 2446 | V37: =IF(OR(T37="",U37=""),0,U37-T37) | AE37: =AF36 | AF37: 31415 | AG37: =IF(OR(AE37="",AF37=""),0,AF37-AE37) | AH37: NAZEER
A38: 46283 | B38: DAY | C38: =D37 | D38: 1777 | E38: =IF(OR(C38="",D38=""),0,D38-C38) | F38: 180 | G38: 1772 | H38: =IF(OR(G36="",G38=""),"",G38-G36) | I38: =IFERROR(F38/H38,0) | N38: =O37 | O38: 24330 | P38: =IF(OR(N38="",O38=""),0,O38-N38) | Q38: Rajkumar | R38: 46283 | S38: DAY | T38: =U37 | U38: 2457 | V38: =IF(OR(T38="",U38=""),0,U38-T38) | W38: 180 | X38: 2452 | Y38: =IF(OR(X36="",X38=""),"",X38-X36) | Z38: =IFERROR(W38/Y38,0) | AE38: =AF37 | AF38: 31562 | AG38: =IF(OR(AE38="",AF38=""),0,AF38-AE38) | AH38: aman
A39: 46283 | B39: NIGHT | C39: =D38 | D39: 1785 | E39: =IF(OR(C39="",D39=""),0,D39-C39) | N39: =O38 | O39: 24400 | P39: =IF(OR(N39="",O39=""),0,O39-N39) | Q39: saidullah | R39: 46283 | S39: NIGHT | T39: =U38 | U39: 2763 | V39: =IF(OR(T39="",U39=""),0,U39-T39) | AE39: =AF38 | AF39: 31674 | AG39: =IF(OR(AE39="",AF39=""),0,AF39-AE39) | AH39: pankaj
A40: 46284 | B40: DAY | C40: =D39 | D40: 1792 | E40: =IF(OR(C40="",D40=""),0,D40-C40) | F40: 110 | H40: =IF(OR(G38="",G40=""),"",G40-G38) | I40: =IFERROR(F40/H40,0) | N40: =O39 | O40: 24495 | P40: =IF(OR(N40="",O40=""),0,O40-N40) | R40: 46284 | S40: DAY | T40: =U39 | U40: 2472 | V40: =IF(OR(T40="",U40=""),0,U40-T40) | W40: 190 | X40: 2467 | Y40: =IF(OR(X38="",X40=""),"",X40-X38) | Z40: =IFERROR(W40/Y40,0) | AE40: =AF39 | AF40: 31811 | AG40: =IF(OR(AE40="",AF40=""),0,AF40-AE40)
A41: 46284 | B41: NIGHT | C41: =D40 | D41: 1799 | E41: =IF(OR(C41="",D41=""),0,D41-C41) | N41: =O40 | O41: 24638 | P41: =IF(OR(N41="",O41=""),0,O41-N41) | R41: 46284 | S41: NIGHT | T41: =U40 | U41: 2479 | V41: =IF(OR(T41="",U41=""),0,U41-T41) | AE41: =AF40 | AF41: 31937 | AG41: =IF(OR(AE41="",AF41=""),0,AF41-AE41)
A42: 46285 | B42: DAY | C42: =D41 | D42: 1809 | E42: =IF(OR(C42="",D42=""),0,D42-C42) | F42: 260 | G42: 1803 | H42: =IF(OR(G40="",G42=""),"",G42-G40) | I42: =IFERROR(F42/H42,0) | N42: =O41 | O42: 24832 | P42: =IF(OR(N42="",O42=""),0,O42-N42) | R42: 46285 | S42: DAY | T42: =U41 | U42: 2488 | V42: =IF(OR(T42="",U42=""),0,U42-T42) | W42: 220 | X42: 2489 | Y42: =IF(OR(X40="",X42=""),"",X42-X40) | Z42: =IFERROR(W42/Y42,0) | AE42: =AF41 | AF42: 32091 | AG42: =IF(OR(AE42="",AF42=""),0,AF42-AE42)
A43: 46285 | B43: NIGHT | C43: =D42 | E43: =IF(OR(C43="",D43=""),0,D43-C43) | N43: =O42 | P43: =IF(OR(N43="",O43=""),0,O43-N43) | R43: 46285 | S43: NIGHT | T43: =U42 | U43: 2496 | V43: =IF(OR(T43="",U43=""),0,U43-T43) | AE43: =AF42 | AF43: 32169 | AG43: =IF(OR(AE43="",AF43=""),0,AF43-AE43)
A44: 46286 | B44: DAY | C44: =D43 | D44: 1824 | E44: =IF(OR(C44="",D44=""),0,D44-C44) | F44: 230 | G44: 1820 | H44: =IF(OR(G42="",G44=""),"",G44-G42) | I44: =IFERROR(F44/H44,0) | N44: =O43 | O44: 25053 | P44: =IF(OR(N44="",O44=""),0,O44-N44) | R44: 46286 | S44: DAY | T44: =U43 | U44: 2503 | V44: =IF(OR(T44="",U44=""),0,U44-T44) | W44: 220 | X44: 2499 | Y44: =IF(OR(X42="",X44=""),"",X44-X42) | Z44: =IFERROR(W44/Y44,0) | AE44: =AF43 | AF44: 32233 | AG44: =IF(OR(AE44="",AF44=""),0,AF44-AE44)
A45: 46286 | B45: NIGHT | C45: =D44 | D45: 1830 | E45: =IF(OR(C45="",D45=""),0,D45-C45) | N45: =O44 | O45: 25130 | P45: =IF(OR(N45="",O45=""),0,O45-N45) | R45: 46286 | S45: NIGHT | T45: =U44 | U45: 2510 | V45: =IF(OR(T45="",U45=""),0,U45-T45) | AE45: =AF44 | AF45: 32325 | AG45: =IF(OR(AE45="",AF45=""),0,AF45-AE45)
A46: 46287 | B46: DAY | C46: =D45 | D46: 1839 | E46: =IF(OR(C46="",D46=""),0,D46-C46) | F46: 151 | G46: 1835 | H46: =IF(OR(G44="",G46=""),"",G46-G44) | I46: =IFERROR(F46/H46,0) | N46: =O45 | O46: 25265 | P46: =IF(OR(N46="",O46=""),0,O46-N46) | R46: 46287 | S46: DAY | T46: =U45 | U46: 2521 | V46: =IF(OR(T46="",U46=""),0,U46-T46) | W46: 160 | X46: 2516 | Y46: =IF(OR(X44="",X46=""),"",X46-X44) | Z46: =IFERROR(W46/Y46,0) | AE46: =AF45 | AF46: 32488 | AG46: =IF(OR(AE46="",AF46=""),0,AF46-AE46)
A47: 46287 | B47: NIGHT | C47: =D46 | D47: 1847 | E47: =IF(OR(C47="",D47=""),0,D47-C47) | N47: =O46 | O47: 25404 | P47: =IF(OR(N47="",O47=""),0,O47-N47) | R47: 46287 | S47: NIGHT | T47: =U46 | U47: 2530 | V47: =IF(OR(T47="",U47=""),0,U47-T47) | AE47: =AF46 | AF47: 32713 | AG47: =IF(OR(AE47="",AF47=""),0,AF47-AE47)
A48: 46288 | B48: DAY | C48: =D47 | D48: 1855 | E48: =IF(OR(C48="",D48=""),0,D48-C48) | F48: 300 | G48: 1852 | H48: =IF(OR(G46="",G48=""),"",G48-G46) | I48: =IFERROR(F48/H48,0) | N48: =O47 | O48: 25519 | P48: =IF(OR(N48="",O48=""),0,O48-N48) | Q48: PANKAJ | R48: 46288 | S48: DAY | T48: =U47 | U48: 2539 | V48: =IF(OR(T48="",U48=""),0,U48-T48) | W48: 300 | X48: 2537 | Y48: =IF(OR(X46="",X48=""),"",X48-X46) | Z48: =IFERROR(W48/Y48,0) | AE48: =AF47 | AF48: 32834 | AG48: =IF(OR(AE48="",AF48=""),0,AF48-AE48) | AH48: KANHAIYA
A49: 46288 | B49: NIGHT | C49: =D48 | D49: 1863 | E49: =IF(OR(C49="",D49=""),0,D49-C49) | N49: =O48 | O49: 25595 | P49: =IF(OR(N49="",O49=""),0,O49-N49) | Q49: NAZEER | R49: 46288 | S49: NIGHT | T49: =U48 | U49: 2546 | V49: =IF(OR(T49="",U49=""),0,U49-T49) | AE49: =AF48 | AF49: 32944 | AG49: =IF(OR(AE49="",AF49=""),0,AF49-AE49) | AH49: RAJKUMAR
A50: 46289 | B50: DAY | C50: =D49 | D50: 1872 | E50: =IF(OR(C50="",D50=""),0,D50-C50) | F50: 180 | G50: 1867 | H50: =IF(OR(G48="",G50=""),"",G50-G48) | I50: =IFERROR(F50/H50,0) | N50: =O49 | O50: 25726 | P50: =IF(OR(N50="",O50=""),0,O50-N50) | Q50: KANHAIYA | R50: 46289 | S50: DAY | T50: =U49 | U50: 2556 | V50: =IF(OR(T50="",U50=""),0,U50-T50) | W50: 130 | X50: 2550 | Y50: =IF(OR(X48="",X50=""),"",X50-X48) | Z50: =IFERROR(W50/Y50,0) | AE50: =AF49 | AF50: 33140 | AG50: =IF(OR(AE50="",AF50=""),0,AF50-AE50) | AH50: aman
A51: 46289 | B51: NIGHT | C51: =D50 | D51: 1880 | E51: =IF(OR(C51="",D51=""),0,D51-C51) | N51: =O50 | O51: 25851 | P51: =IF(OR(N51="",O51=""),0,O51-N51) | Q51: PANKAJ | R51: 46289 | S51: NIGHT | T51: =U50 | U51: 2563 | V51: =IF(OR(T51="",U51=""),0,U51-T51) | AE51: =AF50 | AF51: 33228 | AG51: =IF(OR(AE51="",AF51=""),0,AF51-AE51) | AH51: nazeer
A52: 46290 | B52: DAY | C52: =D51 | E52: =IF(OR(C52="",D52=""),0,D52-C52) | H52: =IF(OR(G50="",G52=""),"",G52-G50) | I52: =IFERROR(F52/H52,0) | N52: =O51 | P52: =IF(OR(N52="",O52=""),0,O52-N52) | R52: 46290 | S52: DAY | T52: =U51 | V52: =IF(OR(T52="",U52=""),0,U52-T52) | Y52: =IF(OR(X50="",X52=""),"",X52-X50) | Z52: =IFERROR(W52/Y52,0) | AE52: =AF51 | AG52: =IF(OR(AE52="",AF52=""),0,AF52-AE52)
A53: 46290 | B53: NIGHT | C53: =D52 | E53: =IF(OR(C53="",D53=""),0,D53-C53) | N53: =O52 | P53: =IF(OR(N53="",O53=""),0,O53-N53) | R53: 46290 | S53: NIGHT | T53: =U52 | V53: =IF(OR(T53="",U53=""),0,U53-T53) | AE53: =AF52 | AG53: =IF(OR(AE53="",AF53=""),0,AF53-AE53)
A54: 46291 | B54: DAY | C54: =D53 | E54: =IF(OR(C54="",D54=""),0,D54-C54) | H54: =IF(OR(G52="",G54=""),"",G54-G52) | I54: =IFERROR(F54/H54,0) | N54: =O53 | P54: =IF(OR(N54="",O54=""),0,O54-N54) | R54: 46291 | S54: DAY | T54: =U53 | V54: =IF(OR(T54="",U54=""),0,U54-T54) | Y54: =IF(OR(X52="",X54=""),"",X54-X52) | Z54: =IFERROR(W54/Y54,0) | AE54: =AF53 | AG54: =IF(OR(AE54="",AF54=""),0,AF54-AE54)
A55: 46291 | B55: NIGHT | C55: =D54 | E55: =IF(OR(C55="",D55=""),0,D55-C55) | N55: =O54 | P55: =IF(OR(N55="",O55=""),0,O55-N55) | R55: 46291 | S55: NIGHT | T55: =U54 | V55: =IF(OR(T55="",U55=""),0,U55-T55) | AE55: =AF54 | AG55: =IF(OR(AE55="",AF55=""),0,AF55-AE55)
A56: 46292 | B56: DAY | C56: =D55 | E56: =IF(OR(C56="",D56=""),0,D56-C56) | H56: =IF(OR(G54="",G56=""),"",G56-G54) | I56: =IFERROR(F56/H56,0) | N56: =O55 | P56: =IF(OR(N56="",O56=""),0,O56-N56) | R56: 46292 | S56: DAY | T56: =U55 | V56: =IF(OR(T56="",U56=""),0,U56-T56) | Y56: =IF(OR(X54="",X56=""),"",X56-X54) | Z56: =IFERROR(W56/Y56,0) | AE56: =AF55 | AG56: =IF(OR(AE56="",AF56=""),0,AF56-AE56)
A57: 46292 | B57: NIGHT | C57: =D56 | E57: =IF(OR(C57="",D57=""),0,D57-C57) | N57: =O56 | P57: =IF(OR(N57="",O57=""),0,O57-N57) | R57: 46292 | S57: NIGHT | T57: =U56 | V57: =IF(OR(T57="",U57=""),0,U57-T57) | AE57: =AF56 | AG57: =IF(OR(AE57="",AF57=""),0,AF57-AE57)
A58: 46293 | B58: DAY | C58: =D57 | E58: =IF(OR(C58="",D58=""),0,D58-C58) | H58: =IF(OR(G56="",G58=""),"",G58-G56) | I58: =IFERROR(F58/H58,0) | N58: =O57 | P58: =IF(OR(N58="",O58=""),0,O58-N58) | R58: 46293 | S58: DAY | T58: =U57 | V58: =IF(OR(T58="",U58=""),0,U58-T58) | Y58: =IF(OR(X56="",X58=""),"",X58-X56) | Z58: =IFERROR(W58/Y58,0) | AE58: =AF57 | AG58: =IF(OR(AE58="",AF58=""),0,AF58-AE58)
A59: 46293 | B59: NIGHT | C59: =D58 | E59: =IF(OR(C59="",D59=""),0,D59-C59) | N59: =O58 | P59: =IF(OR(N59="",O59=""),0,O59-N59) | R59: 46293 | S59: NIGHT | T59: =U58 | V59: =IF(OR(T59="",U59=""),0,U59-T59) | AE59: =AF58 | AG59: =IF(OR(AE59="",AF59=""),0,AF59-AE59)
A60: 46294 | B60: DAY | C60: =D59 | E60: =IF(OR(C60="",D60=""),0,D60-C60) | H60: =IF(OR(G58="",G60=""),"",G60-G58) | I60: =IFERROR(F60/H60,0) | N60: =O59 | P60: =IF(OR(N60="",O60=""),0,O60-N60) | R60: 46294 | S60: DAY | T60: =U59 | V60: =IF(OR(T60="",U60=""),0,U60-T60) | Y60: =IF(OR(X58="",X60=""),"",X60-X58) | Z60: =IFERROR(W60/Y60,0) | AE60: =AF59 | AG60: =IF(OR(AE60="",AF60=""),0,AF60-AE60)
A61: 46294 | B61: NIGHT | C61: =D60 | E61: =IF(OR(C61="",D61=""),0,D61-C61) | N61: =O60 | P61: =IF(OR(N61="",O61=""),0,O61-N61) | R61: 46294 | S61: NIGHT | T61: =U60 | V61: =IF(OR(T61="",U61=""),0,U61-T61) | AE61: =AF60 | AG61: =IF(OR(AE61="",AF61=""),0,AF61-AE61)
A62: 46295 | B62: DAY | C62: =D61 | E62: =IF(OR(C62="",D62=""),0,D62-C62) | H62: =IF(OR(G60="",G62=""),"",G62-G60) | I62: =IFERROR(F62/H62,0) | N62: =O61 | P62: =IF(OR(N62="",O62=""),0,O62-N62) | R62: 46295 | S62: DAY | T62: =U61 | V62: =IF(OR(T62="",U62=""),0,U62-T62) | Y62: =IF(OR(X60="",X62=""),"",X62-X60) | Z62: =IFERROR(W62/Y62,0) | AE62: =AF61 | AG62: =IF(OR(AE62="",AF62=""),0,AF62-AE62)
A63: 46295 | B63: NIGHT | C63: =D62 | E63: =IF(OR(C63="",D63=""),0,D63-C63) | N63: =O62 | P63: =IF(OR(N63="",O63=""),0,O63-N63) | R63: 46295 | S63: NIGHT | T63: =U62 | V63: =IF(OR(T63="",U63=""),0,U63-T63) | AE63: =AF62 | AG63: =IF(OR(AE63="",AF63=""),0,AF63-AE63)
A64: 46296 | B64: DAY | C64: =D63 | E64: =IF(OR(C64="",D64=""),0,D64-C64) | H64: =IF(OR(G62="",G64=""),"",G64-G62) | I64: =IFERROR(F64/H64,0) | N64: =O63 | P64: =IF(OR(N64="",O64=""),0,O64-N64) | R64: 46296 | S64: DAY | T64: =U63 | V64: =IF(OR(T64="",U64=""),0,U64-T64) | Y64: =IF(OR(X62="",X64=""),"",X64-X62) | Z64: =IFERROR(W64/Y64,0) | AE64: =AF63 | AG64: =IF(OR(AE64="",AF64=""),0,AF64-AE64) | AH64: RAJKUMAR
A65: 46296 | B65: NIGHT | C65: =D64 | E65: =IF(OR(C65="",D65=""),0,D65-C65) | N65: =O64 | P65: =IF(OR(N65="",O65=""),0,O65-N65) | R65: 46296 | S65: NIGHT | T65: =U64 | V65: =IF(OR(T65="",U65=""),0,U65-T65) | AE65: =AF64 | AG65: =IF(OR(AE65="",AF65=""),0,AF65-AE65) | AH65: KANHAIYA
A66: TOTAL Running Hours: | E66: =SUBTOTAL(9,E4:E65) | F66: =SUBTOTAL(9,F4:F65) | H66: =SUBTOTAL(9,H4:H65) | I66: =IFERROR(F66/E66,0) | P66: =SUBTOTAL(9,P4:P65) | R66: TOTAL Running Hours: | V66: =SUBTOTAL(9,V4:V65) | W66: =SUBTOTAL(9,W4:W65) | Y66: =SUBTOTAL(9,Y4:Y65) | Z66: =IFERROR(W66/V66,0) | AG66: =SUBTOTAL(9,AG4:AG65)

Sheet SUMMARY
B1: BMCT PORT
B2: XCMG - 8 | F2: SANY - 9
A3: MONTH | B3: Total Diesel Used | C3: Total Running Hours | D3: Container Count | E3: AVERAGE | F3: Total Diesel Used | G3: Total Running Hours | H3: Container Count | I3: AVERAGE
A4: 46113 | B4: ='Apr-26'!F63 | C4: ='Apr-26'!E63 | D4: ='Apr-26'!P63 | E4: =IF(OR(C4="",D4=""),0,D4-C4) | F4: ='Apr-26'!W63 | G4: ='Apr-26'!V63 | H4: ='Apr-26'!AG63 | I4: =IFERROR(F4/H4,0) | J4: Machine running start 29-04-26 | P4: =IF(OR(N4="",O4=""),0,O4-N4) | V4: =IF(OR(T4="",U4=""),0,U4-T4) | Z4: =IFERROR(W4/Y4,0) | AG4: =IF(OR(AE4="",AF4=""),0,AF4-AE4)
A5: 46143 | B5: ='May-26'!F66 | C5: ='May-26'!E66 | D5: ='May-26'!P66 | E5: =IF(OR(C5="",D5=""),0,D5-C5) | F5: ='May-26'!W66 | G5: ='May-26'!V66 | H5: ='May-26'!AG66 | I5: =IFERROR(F5/H5,0)
A6: 46174 | B6: ='June-26'!F64 | C6: ='June-26'!E64 | D6: ='June-26'!P64 | E6: =IF(OR(C6="",D6=""),0,D6-C6) | F6: ='June-26'!W64 | G6: ='June-26'!V64 | H6: ='June-26'!AG64 | I6: =IFERROR(F6/H6,0)
A7: 46204 | B7: ='JULY-26'!F66 | C7: ='JULY-26'!E66 | D7: ='JULY-26'!P66 | E7: =IF(OR(C7="",D7=""),0,D7-C7) | F7: ='JULY-26'!W66 | G7: ='JULY-26'!V66 | H7: ='JULY-26'!AG66 | I7: =IFERROR(F7/H7,0)
A8: 46235 | B8: ='Aug-26'!F66 | C8: ='Aug-26'!E66 | D8: ='Aug-26'!P66 | E8: =IF(OR(C8="",D8=""),0,D8-C8) | F8: ='Aug-26'!W66 | G8: ='Aug-26'!V66 | H8: ='Aug-26'!AG66 | I8: =IFERROR(F8/H8,0)
A9: 46266 | B9: ='Sep-26'!F66 | C9: ='Sep-26'!E66 | D9: ='Sep-26'!P66 | E9: =IF(OR(C9="",D9=""),0,D9-C9) | F9: ='Sep-26'!W66 | G9: ='Sep-26'!V66 | H9: ='Sep-26'!AG66 | I9: =IFERROR(F9/H9,0) | J9: Sep-26 data available through 08-Sep-26
